[
  {
    "info": {
      "browsertime": {
        "version": "8.4.0"
      },
      "url": "https://honolulu.craigslist.org/",
      "timestamp": "2021-05-06T23:40:33+04:00",
      "connectivity": {
        "engine": "external",
        "profile": "native"
      },
      "extra": {}
    },
    "files": {
      "video": [],
      "screenshot": [],
      "timeline": [],
      "consoleLog": [],
      "netLog": [],
      "perfLog": []
    },
    "cdp": {
      "performance": []
    },
    "timestamps": [
      "2021-05-06T23:40:22+04:00",
      "2021-05-06T23:40:44+04:00",
      "2021-05-06T23:41:09+04:00"
    ],
    "browserScripts": [
      {
        "browser": {
          "appConstants": {
            "ACCESSIBILITY": true,
            "ANDROID_PACKAGE_NAME": "org.mozilla.firefox",
            "ASAN": false,
            "ASAN_REPORTER": false,
            "BROWSER_CHROME_URL": "chrome://browser/content/browser.xul",
            "DEBUG": false,
            "DEBUG_JS_MODULES": "",
            "DLL_PREFIX": "lib",
            "DLL_SUFFIX": ".so",
            "EARLY_BETA_OR_EARLIER": false,
            "FENNEC_NIGHTLY": false,
            "HAVE_SHELL_SERVICE": false,
            "HAVE_USR_LIB64_DIR": false,
            "MENUBAR_CAN_AUTOHIDE": false,
            "MOZILLA_OFFICIAL": true,
            "MOZ_ALLOW_LEGACY_EXTENSIONS": false,
            "MOZ_ANDROID_ACTIVITY_STREAM": false,
            "MOZ_ANDROID_HISTORY": true,
            "MOZ_ANDROID_MOZILLA_ONLINE": false,
            "MOZ_APP_NAME": "fennec",
            "MOZ_APP_VERSION": "68.1.1",
            "MOZ_APP_VERSION_DISPLAY": "68.1.1",
            "MOZ_BING_API_CLIENTID": "no-bing-api-clientid",
            "MOZ_BING_API_KEY": "no-bing-api-key",
            "MOZ_BITS_DOWNLOAD": false,
            "MOZ_BUILD_APP": "mobile/android",
            "MOZ_CODE_COVERAGE": false,
            "MOZ_CRASHREPORTER": true,
            "MOZ_DATA_REPORTING": true,
            "MOZ_DEV_EDITION": false,
            "MOZ_GECKO_PROFILER": true,
            "MOZ_GOOGLE_LOCATION_SERVICE_API_KEY": "AIzaSyB2h2OuRcUgy5N-5hsZqiPW6sH3n_rptiQ",
            "MOZ_GOOGLE_SAFEBROWSING_API_KEY": "AIzaSyC7jsptDS3am4tPx4r3nxis7IMjBc5Dovo",
            "MOZ_GRAPHENE": false,
            "MOZ_MACBUNDLE_NAME": "Firefox.app",
            "MOZ_MAINTENANCE_SERVICE": false,
            "MOZ_MOZILLA_API_KEY": "3b4d27dd-703d-4094-8398-4de2c763505a",
            "MOZ_NEW_CERT_STORAGE": false,
            "MOZ_NEW_NOTIFICATION_STORE": false,
            "MOZ_NEW_XULSTORE": false,
            "MOZ_OFFICIAL_BRANDING": false,
            "MOZ_PLACES": false,
            "MOZ_REQUIRE_SIGNING": false,
            "MOZ_SANDBOX": false,
            "MOZ_SERVICES_HEALTHREPORT": true,
            "MOZ_SERVICES_SYNC": false,
            "MOZ_SWITCHBOARD": true,
            "MOZ_SYSTEM_NSS": false,
            "MOZ_TELEMETRY_ON_BY_DEFAULT": false,
            "MOZ_TELEMETRY_REPORTING": true,
            "MOZ_UNSIGNED_SCOPES": 0,
            "MOZ_UPDATER": false,
            "MOZ_UPDATE_CHANNEL": "release",
            "MOZ_WEBRTC": true,
            "MOZ_WIDGET_GTK": false,
            "MOZ_WIDGET_TOOLKIT": "android",
            "NIGHTLY_BUILD": false,
            "OMNIJAR_NAME": "assets/omni.ja",
            "RELEASE_OR_BETA": true,
            "SOURCE_REVISION_URL": "https://hg.mozilla.org/releases/mozilla-esr68/rev/d2e0b9e17b9bc1ef02606c8006b73293f7892ad5",
            "TELEMETRY_PING_FORMAT_VERSION": 4,
            "XP_UNIX": true,
            "isPlatformAndVersionAtLeast": {},
            "isPlatformAndVersionAtMost": {},
            "platform": "android"
          },
          "asyncAppConstants": {
            "ACCESSIBILITY": true,
            "ANDROID_PACKAGE_NAME": "org.mozilla.firefox",
            "ASAN": false,
            "ASAN_REPORTER": false,
            "BROWSER_CHROME_URL": "chrome://browser/content/browser.xul",
            "DEBUG": false,
            "DEBUG_JS_MODULES": "",
            "DLL_PREFIX": "lib",
            "DLL_SUFFIX": ".so",
            "EARLY_BETA_OR_EARLIER": false,
            "FENNEC_NIGHTLY": false,
            "HAVE_SHELL_SERVICE": false,
            "HAVE_USR_LIB64_DIR": false,
            "MENUBAR_CAN_AUTOHIDE": false,
            "MOZILLA_OFFICIAL": true,
            "MOZ_ALLOW_LEGACY_EXTENSIONS": false,
            "MOZ_ANDROID_ACTIVITY_STREAM": false,
            "MOZ_ANDROID_HISTORY": true,
            "MOZ_ANDROID_MOZILLA_ONLINE": false,
            "MOZ_APP_NAME": "fennec",
            "MOZ_APP_VERSION": "68.1.1",
            "MOZ_APP_VERSION_DISPLAY": "68.1.1",
            "MOZ_BING_API_CLIENTID": "no-bing-api-clientid",
            "MOZ_BING_API_KEY": "no-bing-api-key",
            "MOZ_BITS_DOWNLOAD": false,
            "MOZ_BUILD_APP": "mobile/android",
            "MOZ_CODE_COVERAGE": false,
            "MOZ_CRASHREPORTER": true,
            "MOZ_DATA_REPORTING": true,
            "MOZ_DEV_EDITION": false,
            "MOZ_GECKO_PROFILER": true,
            "MOZ_GOOGLE_LOCATION_SERVICE_API_KEY": "AIzaSyB2h2OuRcUgy5N-5hsZqiPW6sH3n_rptiQ",
            "MOZ_GOOGLE_SAFEBROWSING_API_KEY": "AIzaSyC7jsptDS3am4tPx4r3nxis7IMjBc5Dovo",
            "MOZ_GRAPHENE": false,
            "MOZ_MACBUNDLE_NAME": "Firefox.app",
            "MOZ_MAINTENANCE_SERVICE": false,
            "MOZ_MOZILLA_API_KEY": "3b4d27dd-703d-4094-8398-4de2c763505a",
            "MOZ_NEW_CERT_STORAGE": false,
            "MOZ_NEW_NOTIFICATION_STORE": false,
            "MOZ_NEW_XULSTORE": false,
            "MOZ_OFFICIAL_BRANDING": false,
            "MOZ_PLACES": false,
            "MOZ_REQUIRE_SIGNING": false,
            "MOZ_SANDBOX": false,
            "MOZ_SERVICES_HEALTHREPORT": true,
            "MOZ_SERVICES_SYNC": false,
            "MOZ_SWITCHBOARD": true,
            "MOZ_SYSTEM_NSS": false,
            "MOZ_TELEMETRY_ON_BY_DEFAULT": false,
            "MOZ_TELEMETRY_REPORTING": true,
            "MOZ_UNSIGNED_SCOPES": 0,
            "MOZ_UPDATER": false,
            "MOZ_UPDATE_CHANNEL": "release",
            "MOZ_WEBRTC": true,
            "MOZ_WIDGET_GTK": false,
            "MOZ_WIDGET_TOOLKIT": "android",
            "NIGHTLY_BUILD": false,
            "OMNIJAR_NAME": "assets/omni.ja",
            "RELEASE_OR_BETA": true,
            "SOURCE_REVISION_URL": "https://hg.mozilla.org/releases/mozilla-esr68/rev/d2e0b9e17b9bc1ef02606c8006b73293f7892ad5",
            "TELEMETRY_PING_FORMAT_VERSION": 4,
            "XP_UNIX": true,
            "isPlatformAndVersionAtLeast": {},
            "isPlatformAndVersionAtMost": {},
            "platform": "android"
          },
          "userAgent": "Mozilla/5.0 (Android 8.1.0; Mobile; rv:68.0) Gecko/68.0 Firefox/68.0",
          "windowSize": "360x560"
        },
        "pageinfo": {
          "documentHeight": 1321,
          "documentSize": {
            "decodedBodySize": 56907,
            "encodedBodySize": 10785,
            "transferSize": 11420
          },
          "documentTitle": "craigslist: hawaii jobs, apartments, for sale, services, community, and events",
          "documentWidth": 360,
          "domElements": 1471,
          "navigationStartTime": 1620330022772,
          "nextHopProtocol": "http/1.1",
          "resources": {
            "count": 0,
            "duration": 0
          },
          "responsive": true,
          "url": "https://honolulu.craigslist.org/",
          "visualElements": {
            "heroes": [],
            "viewport": {
              "height": 560,
              "width": 360
            }
          }
        },
        "timings": {
          "firstPaint": 2697,
          "loadEventEnd": 4436,
          "navigationTiming": {
            "connectStart": 37,
            "domComplete": 4435,
            "domContentLoadedEventEnd": 3728,
            "domContentLoadedEventStart": 3697,
            "domInteractive": 3625,
            "domainLookupEnd": 37,
            "domainLookupStart": 37,
            "duration": 4436,
            "fetchStart": 3,
            "loadEventEnd": 4436,
            "loadEventStart": 4435,
            "redirectEnd": 0,
            "redirectStart": 0,
            "requestStart": 696,
            "responseEnd": 981,
            "responseStart": 967,
            "secureConnectionStart": 323,
            "startTime": 0,
            "unloadEventEnd": 0,
            "unloadEventStart": 0,
            "workerStart": 0
          },
          "pageTimings": {
            "backEndTime": 967,
            "domContentLoadedTime": 3697,
            "domInteractiveTime": 3625,
            "domainLookupTime": 0,
            "frontEndTime": 3455,
            "pageDownloadTime": 14,
            "pageLoadTime": 4435,
            "redirectionTime": 0,
            "serverConnectionTime": 658,
            "serverResponseTime": 285
          },
          "rumSpeedIndex": 966,
          "timeToContentfulPaint": 2823,
          "timeToDomContentFlushed": 3633,
          "userTimings": {
            "marks": [],
            "measures": []
          }
        }
      },
      {
        "browser": {
          "appConstants": {
            "ACCESSIBILITY": true,
            "ANDROID_PACKAGE_NAME": "org.mozilla.firefox",
            "ASAN": false,
            "ASAN_REPORTER": false,
            "BROWSER_CHROME_URL": "chrome://browser/content/browser.xul",
            "DEBUG": false,
            "DEBUG_JS_MODULES": "",
            "DLL_PREFIX": "lib",
            "DLL_SUFFIX": ".so",
            "EARLY_BETA_OR_EARLIER": false,
            "FENNEC_NIGHTLY": false,
            "HAVE_SHELL_SERVICE": false,
            "HAVE_USR_LIB64_DIR": false,
            "MENUBAR_CAN_AUTOHIDE": false,
            "MOZILLA_OFFICIAL": true,
            "MOZ_ALLOW_LEGACY_EXTENSIONS": false,
            "MOZ_ANDROID_ACTIVITY_STREAM": false,
            "MOZ_ANDROID_HISTORY": true,
            "MOZ_ANDROID_MOZILLA_ONLINE": false,
            "MOZ_APP_NAME": "fennec",
            "MOZ_APP_VERSION": "68.1.1",
            "MOZ_APP_VERSION_DISPLAY": "68.1.1",
            "MOZ_BING_API_CLIENTID": "no-bing-api-clientid",
            "MOZ_BING_API_KEY": "no-bing-api-key",
            "MOZ_BITS_DOWNLOAD": false,
            "MOZ_BUILD_APP": "mobile/android",
            "MOZ_CODE_COVERAGE": false,
            "MOZ_CRASHREPORTER": true,
            "MOZ_DATA_REPORTING": true,
            "MOZ_DEV_EDITION": false,
            "MOZ_GECKO_PROFILER": true,
            "MOZ_GOOGLE_LOCATION_SERVICE_API_KEY": "AIzaSyB2h2OuRcUgy5N-5hsZqiPW6sH3n_rptiQ",
            "MOZ_GOOGLE_SAFEBROWSING_API_KEY": "AIzaSyC7jsptDS3am4tPx4r3nxis7IMjBc5Dovo",
            "MOZ_GRAPHENE": false,
            "MOZ_MACBUNDLE_NAME": "Firefox.app",
            "MOZ_MAINTENANCE_SERVICE": false,
            "MOZ_MOZILLA_API_KEY": "3b4d27dd-703d-4094-8398-4de2c763505a",
            "MOZ_NEW_CERT_STORAGE": false,
            "MOZ_NEW_NOTIFICATION_STORE": false,
            "MOZ_NEW_XULSTORE": false,
            "MOZ_OFFICIAL_BRANDING": false,
            "MOZ_PLACES": false,
            "MOZ_REQUIRE_SIGNING": false,
            "MOZ_SANDBOX": false,
            "MOZ_SERVICES_HEALTHREPORT": true,
            "MOZ_SERVICES_SYNC": false,
            "MOZ_SWITCHBOARD": true,
            "MOZ_SYSTEM_NSS": false,
            "MOZ_TELEMETRY_ON_BY_DEFAULT": false,
            "MOZ_TELEMETRY_REPORTING": true,
            "MOZ_UNSIGNED_SCOPES": 0,
            "MOZ_UPDATER": false,
            "MOZ_UPDATE_CHANNEL": "release",
            "MOZ_WEBRTC": true,
            "MOZ_WIDGET_GTK": false,
            "MOZ_WIDGET_TOOLKIT": "android",
            "NIGHTLY_BUILD": false,
            "OMNIJAR_NAME": "assets/omni.ja",
            "RELEASE_OR_BETA": true,
            "SOURCE_REVISION_URL": "https://hg.mozilla.org/releases/mozilla-esr68/rev/d2e0b9e17b9bc1ef02606c8006b73293f7892ad5",
            "TELEMETRY_PING_FORMAT_VERSION": 4,
            "XP_UNIX": true,
            "isPlatformAndVersionAtLeast": {},
            "isPlatformAndVersionAtMost": {},
            "platform": "android"
          },
          "asyncAppConstants": {
            "ACCESSIBILITY": true,
            "ANDROID_PACKAGE_NAME": "org.mozilla.firefox",
            "ASAN": false,
            "ASAN_REPORTER": false,
            "BROWSER_CHROME_URL": "chrome://browser/content/browser.xul",
            "DEBUG": false,
            "DEBUG_JS_MODULES": "",
            "DLL_PREFIX": "lib",
            "DLL_SUFFIX": ".so",
            "EARLY_BETA_OR_EARLIER": false,
            "FENNEC_NIGHTLY": false,
            "HAVE_SHELL_SERVICE": false,
            "HAVE_USR_LIB64_DIR": false,
            "MENUBAR_CAN_AUTOHIDE": false,
            "MOZILLA_OFFICIAL": true,
            "MOZ_ALLOW_LEGACY_EXTENSIONS": false,
            "MOZ_ANDROID_ACTIVITY_STREAM": false,
            "MOZ_ANDROID_HISTORY": true,
            "MOZ_ANDROID_MOZILLA_ONLINE": false,
            "MOZ_APP_NAME": "fennec",
            "MOZ_APP_VERSION": "68.1.1",
            "MOZ_APP_VERSION_DISPLAY": "68.1.1",
            "MOZ_BING_API_CLIENTID": "no-bing-api-clientid",
            "MOZ_BING_API_KEY": "no-bing-api-key",
            "MOZ_BITS_DOWNLOAD": false,
            "MOZ_BUILD_APP": "mobile/android",
            "MOZ_CODE_COVERAGE": false,
            "MOZ_CRASHREPORTER": true,
            "MOZ_DATA_REPORTING": true,
            "MOZ_DEV_EDITION": false,
            "MOZ_GECKO_PROFILER": true,
            "MOZ_GOOGLE_LOCATION_SERVICE_API_KEY": "AIzaSyB2h2OuRcUgy5N-5hsZqiPW6sH3n_rptiQ",
            "MOZ_GOOGLE_SAFEBROWSING_API_KEY": "AIzaSyC7jsptDS3am4tPx4r3nxis7IMjBc5Dovo",
            "MOZ_GRAPHENE": false,
            "MOZ_MACBUNDLE_NAME": "Firefox.app",
            "MOZ_MAINTENANCE_SERVICE": false,
            "MOZ_MOZILLA_API_KEY": "3b4d27dd-703d-4094-8398-4de2c763505a",
            "MOZ_NEW_CERT_STORAGE": false,
            "MOZ_NEW_NOTIFICATION_STORE": false,
            "MOZ_NEW_XULSTORE": false,
            "MOZ_OFFICIAL_BRANDING": false,
            "MOZ_PLACES": false,
            "MOZ_REQUIRE_SIGNING": false,
            "MOZ_SANDBOX": false,
            "MOZ_SERVICES_HEALTHREPORT": true,
            "MOZ_SERVICES_SYNC": false,
            "MOZ_SWITCHBOARD": true,
            "MOZ_SYSTEM_NSS": false,
            "MOZ_TELEMETRY_ON_BY_DEFAULT": false,
            "MOZ_TELEMETRY_REPORTING": true,
            "MOZ_UNSIGNED_SCOPES": 0,
            "MOZ_UPDATER": false,
            "MOZ_UPDATE_CHANNEL": "release",
            "MOZ_WEBRTC": true,
            "MOZ_WIDGET_GTK": false,
            "MOZ_WIDGET_TOOLKIT": "android",
            "NIGHTLY_BUILD": false,
            "OMNIJAR_NAME": "assets/omni.ja",
            "RELEASE_OR_BETA": true,
            "SOURCE_REVISION_URL": "https://hg.mozilla.org/releases/mozilla-esr68/rev/d2e0b9e17b9bc1ef02606c8006b73293f7892ad5",
            "TELEMETRY_PING_FORMAT_VERSION": 4,
            "XP_UNIX": true,
            "isPlatformAndVersionAtLeast": {},
            "isPlatformAndVersionAtMost": {},
            "platform": "android"
          },
          "userAgent": "Mozilla/5.0 (Android 8.1.0; Mobile; rv:68.0) Gecko/68.0 Firefox/68.0",
          "windowSize": "360x560"
        },
        "pageinfo": {
          "documentHeight": 1321,
          "documentSize": {
            "decodedBodySize": 56907,
            "encodedBodySize": 10785,
            "transferSize": 11420
          },
          "documentTitle": "craigslist: hawaii jobs, apartments, for sale, services, community, and events",
          "documentWidth": 360,
          "domElements": 1471,
          "navigationStartTime": 1620330044372,
          "nextHopProtocol": "http/1.1",
          "resources": {
            "count": 0,
            "duration": 0
          },
          "responsive": true,
          "url": "https://honolulu.craigslist.org/",
          "visualElements": {
            "heroes": [],
            "viewport": {
              "height": 560,
              "width": 360
            }
          }
        },
        "timings": {
          "firstPaint": 4053,
          "loadEventEnd": 5874,
          "navigationTiming": {
            "connectStart": 36,
            "domComplete": 5873,
            "domContentLoadedEventEnd": 5378,
            "domContentLoadedEventStart": 5345,
            "domInteractive": 5224,
            "domainLookupEnd": 33,
            "domainLookupStart": 33,
            "duration": 5874,
            "fetchStart": 3,
            "loadEventEnd": 5874,
            "loadEventStart": 5873,
            "redirectEnd": 0,
            "redirectStart": 0,
            "requestStart": 733,
            "responseEnd": 2209,
            "responseStart": 1025,
            "secureConnectionStart": 318,
            "startTime": 0,
            "unloadEventEnd": 0,
            "unloadEventStart": 0,
            "workerStart": 0
          },
          "pageTimings": {
            "backEndTime": 1025,
            "domContentLoadedTime": 5345,
            "domInteractiveTime": 5224,
            "domainLookupTime": 0,
            "frontEndTime": 3665,
            "pageDownloadTime": 1183,
            "pageLoadTime": 5873,
            "redirectionTime": 0,
            "serverConnectionTime": 697,
            "serverResponseTime": 1475
          },
          "rumSpeedIndex": 1025,
          "timeToContentfulPaint": 4178,
          "timeToDomContentFlushed": 5274,
          "userTimings": {
            "marks": [],
            "measures": []
          }
        }
      },
      {
        "browser": {
          "appConstants": {
            "ACCESSIBILITY": true,
            "ANDROID_PACKAGE_NAME": "org.mozilla.firefox",
            "ASAN": false,
            "ASAN_REPORTER": false,
            "BROWSER_CHROME_URL": "chrome://browser/content/browser.xul",
            "DEBUG": false,
            "DEBUG_JS_MODULES": "",
            "DLL_PREFIX": "lib",
            "DLL_SUFFIX": ".so",
            "EARLY_BETA_OR_EARLIER": false,
            "FENNEC_NIGHTLY": false,
            "HAVE_SHELL_SERVICE": false,
            "HAVE_USR_LIB64_DIR": false,
            "MENUBAR_CAN_AUTOHIDE": false,
            "MOZILLA_OFFICIAL": true,
            "MOZ_ALLOW_LEGACY_EXTENSIONS": false,
            "MOZ_ANDROID_ACTIVITY_STREAM": false,
            "MOZ_ANDROID_HISTORY": true,
            "MOZ_ANDROID_MOZILLA_ONLINE": false,
            "MOZ_APP_NAME": "fennec",
            "MOZ_APP_VERSION": "68.1.1",
            "MOZ_APP_VERSION_DISPLAY": "68.1.1",
            "MOZ_BING_API_CLIENTID": "no-bing-api-clientid",
            "MOZ_BING_API_KEY": "no-bing-api-key",
            "MOZ_BITS_DOWNLOAD": false,
            "MOZ_BUILD_APP": "mobile/android",
            "MOZ_CODE_COVERAGE": false,
            "MOZ_CRASHREPORTER": true,
            "MOZ_DATA_REPORTING": true,
            "MOZ_DEV_EDITION": false,
            "MOZ_GECKO_PROFILER": true,
            "MOZ_GOOGLE_LOCATION_SERVICE_API_KEY": "AIzaSyB2h2OuRcUgy5N-5hsZqiPW6sH3n_rptiQ",
            "MOZ_GOOGLE_SAFEBROWSING_API_KEY": "AIzaSyC7jsptDS3am4tPx4r3nxis7IMjBc5Dovo",
            "MOZ_GRAPHENE": false,
            "MOZ_MACBUNDLE_NAME": "Firefox.app",
            "MOZ_MAINTENANCE_SERVICE": false,
            "MOZ_MOZILLA_API_KEY": "3b4d27dd-703d-4094-8398-4de2c763505a",
            "MOZ_NEW_CERT_STORAGE": false,
            "MOZ_NEW_NOTIFICATION_STORE": false,
            "MOZ_NEW_XULSTORE": false,
            "MOZ_OFFICIAL_BRANDING": false,
            "MOZ_PLACES": false,
            "MOZ_REQUIRE_SIGNING": false,
            "MOZ_SANDBOX": false,
            "MOZ_SERVICES_HEALTHREPORT": true,
            "MOZ_SERVICES_SYNC": false,
            "MOZ_SWITCHBOARD": true,
            "MOZ_SYSTEM_NSS": false,
            "MOZ_TELEMETRY_ON_BY_DEFAULT": false,
            "MOZ_TELEMETRY_REPORTING": true,
            "MOZ_UNSIGNED_SCOPES": 0,
            "MOZ_UPDATER": false,
            "MOZ_UPDATE_CHANNEL": "release",
            "MOZ_WEBRTC": true,
            "MOZ_WIDGET_GTK": false,
            "MOZ_WIDGET_TOOLKIT": "android",
            "NIGHTLY_BUILD": false,
            "OMNIJAR_NAME": "assets/omni.ja",
            "RELEASE_OR_BETA": true,
            "SOURCE_REVISION_URL": "https://hg.mozilla.org/releases/mozilla-esr68/rev/d2e0b9e17b9bc1ef02606c8006b73293f7892ad5",
            "TELEMETRY_PING_FORMAT_VERSION": 4,
            "XP_UNIX": true,
            "isPlatformAndVersionAtLeast": {},
            "isPlatformAndVersionAtMost": {},
            "platform": "android"
          },
          "asyncAppConstants": {
            "ACCESSIBILITY": true,
            "ANDROID_PACKAGE_NAME": "org.mozilla.firefox",
            "ASAN": false,
            "ASAN_REPORTER": false,
            "BROWSER_CHROME_URL": "chrome://browser/content/browser.xul",
            "DEBUG": false,
            "DEBUG_JS_MODULES": "",
            "DLL_PREFIX": "lib",
            "DLL_SUFFIX": ".so",
            "EARLY_BETA_OR_EARLIER": false,
            "FENNEC_NIGHTLY": false,
            "HAVE_SHELL_SERVICE": false,
            "HAVE_USR_LIB64_DIR": false,
            "MENUBAR_CAN_AUTOHIDE": false,
            "MOZILLA_OFFICIAL": true,
            "MOZ_ALLOW_LEGACY_EXTENSIONS": false,
            "MOZ_ANDROID_ACTIVITY_STREAM": false,
            "MOZ_ANDROID_HISTORY": true,
            "MOZ_ANDROID_MOZILLA_ONLINE": false,
            "MOZ_APP_NAME": "fennec",
            "MOZ_APP_VERSION": "68.1.1",
            "MOZ_APP_VERSION_DISPLAY": "68.1.1",
            "MOZ_BING_API_CLIENTID": "no-bing-api-clientid",
            "MOZ_BING_API_KEY": "no-bing-api-key",
            "MOZ_BITS_DOWNLOAD": false,
            "MOZ_BUILD_APP": "mobile/android",
            "MOZ_CODE_COVERAGE": false,
            "MOZ_CRASHREPORTER": true,
            "MOZ_DATA_REPORTING": true,
            "MOZ_DEV_EDITION": false,
            "MOZ_GECKO_PROFILER": true,
            "MOZ_GOOGLE_LOCATION_SERVICE_API_KEY": "AIzaSyB2h2OuRcUgy5N-5hsZqiPW6sH3n_rptiQ",
            "MOZ_GOOGLE_SAFEBROWSING_API_KEY": "AIzaSyC7jsptDS3am4tPx4r3nxis7IMjBc5Dovo",
            "MOZ_GRAPHENE": false,
            "MOZ_MACBUNDLE_NAME": "Firefox.app",
            "MOZ_MAINTENANCE_SERVICE": false,
            "MOZ_MOZILLA_API_KEY": "3b4d27dd-703d-4094-8398-4de2c763505a",
            "MOZ_NEW_CERT_STORAGE": false,
            "MOZ_NEW_NOTIFICATION_STORE": false,
            "MOZ_NEW_XULSTORE": false,
            "MOZ_OFFICIAL_BRANDING": false,
            "MOZ_PLACES": false,
            "MOZ_REQUIRE_SIGNING": false,
            "MOZ_SANDBOX": false,
            "MOZ_SERVICES_HEALTHREPORT": true,
            "MOZ_SERVICES_SYNC": false,
            "MOZ_SWITCHBOARD": true,
            "MOZ_SYSTEM_NSS": false,
            "MOZ_TELEMETRY_ON_BY_DEFAULT": false,
            "MOZ_TELEMETRY_REPORTING": true,
            "MOZ_UNSIGNED_SCOPES": 0,
            "MOZ_UPDATER": false,
            "MOZ_UPDATE_CHANNEL": "release",
            "MOZ_WEBRTC": true,
            "MOZ_WIDGET_GTK": false,
            "MOZ_WIDGET_TOOLKIT": "android",
            "NIGHTLY_BUILD": false,
            "OMNIJAR_NAME": "assets/omni.ja",
            "RELEASE_OR_BETA": true,
            "SOURCE_REVISION_URL": "https://hg.mozilla.org/releases/mozilla-esr68/rev/d2e0b9e17b9bc1ef02606c8006b73293f7892ad5",
            "TELEMETRY_PING_FORMAT_VERSION": 4,
            "XP_UNIX": true,
            "isPlatformAndVersionAtLeast": {},
            "isPlatformAndVersionAtMost": {},
            "platform": "android"
          },
          "userAgent": "Mozilla/5.0 (Android 8.1.0; Mobile; rv:68.0) Gecko/68.0 Firefox/68.0",
          "windowSize": "360x560"
        },
        "pageinfo": {
          "documentHeight": 1321,
          "documentSize": {
            "decodedBodySize": 56907,
            "encodedBodySize": 10785,
            "transferSize": 11420
          },
          "documentTitle": "craigslist: hawaii jobs, apartments, for sale, services, community, and events",
          "documentWidth": 360,
          "domElements": 1471,
          "navigationStartTime": 1620330070206,
          "nextHopProtocol": "http/1.1",
          "resources": {
            "count": 0,
            "duration": 0
          },
          "responsive": true,
          "url": "https://honolulu.craigslist.org/",
          "visualElements": {
            "heroes": [],
            "viewport": {
              "height": 560,
              "width": 360
            }
          }
        },
        "timings": {
          "firstPaint": 2965,
          "loadEventEnd": 5279,
          "navigationTiming": {
            "connectStart": 37,
            "domComplete": 5279,
            "domContentLoadedEventEnd": 3946,
            "domContentLoadedEventStart": 3913,
            "domInteractive": 3846,
            "domainLookupEnd": 37,
            "domainLookupStart": 37,
            "duration": 5279,
            "fetchStart": 3,
            "loadEventEnd": 5279,
            "loadEventStart": 5279,
            "redirectEnd": 0,
            "redirectStart": 0,
            "requestStart": 643,
            "responseEnd": 1224,
            "responseStart": 1219,
            "secureConnectionStart": 291,
            "startTime": 0,
            "unloadEventEnd": 0,
            "unloadEventStart": 0,
            "workerStart": 0
          },
          "pageTimings": {
            "backEndTime": 1219,
            "domContentLoadedTime": 3913,
            "domInteractiveTime": 3846,
            "domainLookupTime": 0,
            "frontEndTime": 4055,
            "pageDownloadTime": 4,
            "pageLoadTime": 5279,
            "redirectionTime": 0,
            "serverConnectionTime": 606,
            "serverResponseTime": 580
          },
          "rumSpeedIndex": 1219,
          "timeToContentfulPaint": 3098,
          "timeToDomContentFlushed": 3856,
          "userTimings": {
            "marks": [],
            "measures": []
          }
        }
      }
    ],
    "visualMetrics": [],
    "cpu": [],
    "extras": [
      {},
      {},
      {}
    ],
    "fullyLoaded": [],
    "errors": [
      [],
      [],
      []
    ],
    "statistics": {
      "browser": {
        "appConstants": {
          "MOZ_UNSIGNED_SCOPES": {
            "median": 0,
            "mean": 0,
            "mdev": 0,
            "stddev": 0,
            "min": 0,
            "p10": 0,
            "p90": 0,
            "p99": 0,
            "max": 0
          },
          "TELEMETRY_PING_FORMAT_VERSION": {
            "median": 4,
            "mean": 4,
            "mdev": 0,
            "stddev": 0,
            "min": 4,
            "p10": 4,
            "p90": 4,
            "p99": 4,
            "max": 4
          }
        },
        "asyncAppConstants": {
          "MOZ_UNSIGNED_SCOPES": {
            "median": 0,
            "mean": 0,
            "mdev": 0,
            "stddev": 0,
            "min": 0,
            "p10": 0,
            "p90": 0,
            "p99": 0,
            "max": 0
          },
          "TELEMETRY_PING_FORMAT_VERSION": {
            "median": 4,
            "mean": 4,
            "mdev": 0,
            "stddev": 0,
            "min": 4,
            "p10": 4,
            "p90": 4,
            "p99": 4,
            "max": 4
          }
        }
      },
      "pageinfo": {
        "documentHeight": {
          "median": 1321,
          "mean": 1321,
          "mdev": 0,
          "stddev": 0,
          "min": 1321,
          "p10": 1321,
          "p90": 1321,
          "p99": 1321,
          "max": 1321
        },
        "documentSize": {
          "decodedBodySize": {
            "median": 56907,
            "mean": 56907,
            "mdev": 0,
            "stddev": 0,
            "min": 56907,
            "p10": 56907,
            "p90": 56907,
            "p99": 56907,
            "max": 56907
          },
          "encodedBodySize": {
            "median": 10785,
            "mean": 10785,
            "mdev": 0,
            "stddev": 0,
            "min": 10785,
            "p10": 10785,
            "p90": 10785,
            "p99": 10785,
            "max": 10785
          },
          "transferSize": {
            "median": 11420,
            "mean": 11420,
            "mdev": 0,
            "stddev": 0,
            "min": 11420,
            "p10": 11420,
            "p90": 11420,
            "p99": 11420,
            "max": 11420
          }
        },
        "documentWidth": {
          "median": 360,
          "mean": 360,
          "mdev": 0,
          "stddev": 0,
          "min": 360,
          "p10": 360,
          "p90": 360,
          "p99": 360,
          "max": 360
        },
        "domElements": {
          "median": 1471,
          "mean": 1471,
          "mdev": 0,
          "stddev": 0,
          "min": 1471,
          "p10": 1471,
          "p90": 1471,
          "p99": 1471,
          "max": 1471
        },
        "navigationStartTime": {
          "median": 1620330044372,
          "mean": 1620330045783,
          "mdev": 0,
          "stddev": 0,
          "min": 1620330022772,
          "p10": 1620330022772,
          "p90": 1620330070206,
          "p99": 1620330070206,
          "max": 1620330070206
        },
        "resources": {
          "count": {
            "median": 0,
            "mean": 0,
            "mdev": 0,
            "stddev": 0,
            "min": 0,
            "p10": 0,
            "p90": 0,
            "p99": 0,
            "max": 0
          },
          "duration": {
            "median": 0,
            "mean": 0,
            "mdev": 0,
            "stddev": 0,
            "min": 0,
            "p10": 0,
            "p90": 0,
            "p99": 0,
            "max": 0
          }
        },
        "visualElements": {
          "viewport": {
            "height": {
              "median": 560,
              "mean": 560,
              "mdev": 0,
              "stddev": 0,
              "min": 560,
              "p10": 560,
              "p90": 560,
              "p99": 560,
              "max": 560
            },
            "width": {
              "median": 360,
              "mean": 360,
              "mdev": 0,
              "stddev": 0,
              "min": 360,
              "p10": 360,
              "p90": 360,
              "p99": 360,
              "max": 360
            }
          }
        }
      },
      "timings": {
        "firstPaint": {
          "median": 2965,
          "mean": 3238,
          "mdev": 338.5319,
          "stddev": 586,
          "min": 2697,
          "p10": 2697,
          "p90": 4053,
          "p99": 4053,
          "max": 4053
        },
        "loadEventEnd": {
          "median": 5279,
          "mean": 5196,
          "mdev": 340.6159,
          "stddev": 590,
          "min": 4436,
          "p10": 4436,
          "p90": 5874,
          "p99": 5874,
          "max": 5874
        },
        "navigationTiming": {
          "connectStart": {
            "median": 37,
            "mean": 37,
            "mdev": 0.2722,
            "stddev": 0,
            "min": 36,
            "p10": 36,
            "p90": 37,
            "p99": 37,
            "max": 37
          },
          "domComplete": {
            "median": 5279,
            "mean": 5196,
            "mdev": 340.643,
            "stddev": 590,
            "min": 4435,
            "p10": 4435,
            "p90": 5873,
            "p99": 5873,
            "max": 5873
          },
          "domContentLoadedEventEnd": {
            "median": 3946,
            "mean": 4351,
            "mdev": 422.5429,
            "stddev": 732,
            "min": 3728,
            "p10": 3728,
            "p90": 5378,
            "p99": 5378,
            "max": 5378
          },
          "domContentLoadedEventStart": {
            "median": 3913,
            "mean": 4318,
            "mdev": 422.2157,
            "stddev": 731,
            "min": 3697,
            "p10": 3697,
            "p90": 5345,
            "p99": 5345,
            "max": 5345
          },
          "domInteractive": {
            "median": 3846,
            "mean": 4232,
            "mdev": 408.4535,
            "stddev": 707,
            "min": 3625,
            "p10": 3625,
            "p90": 5224,
            "p99": 5224,
            "max": 5224
          },
          "domainLookupEnd": {
            "median": 37,
            "mean": 36,
            "mdev": 1.0887,
            "stddev": 2,
            "min": 33,
            "p10": 33,
            "p90": 37,
            "p99": 37,
            "max": 37
          },
          "domainLookupStart": {
            "median": 37,
            "mean": 36,
            "mdev": 1.0887,
            "stddev": 2,
            "min": 33,
            "p10": 33,
            "p90": 37,
            "p99": 37,
            "max": 37
          },
          "duration": {
            "median": 5279,
            "mean": 5196,
            "mdev": 340.6159,
            "stddev": 590,
            "min": 4436,
            "p10": 4436,
            "p90": 5874,
            "p99": 5874,
            "max": 5874
          },
          "fetchStart": {
            "median": 3,
            "mean": 3,
            "mdev": 0,
            "stddev": 0,
            "min": 3,
            "p10": 3,
            "p90": 3,
            "p99": 3,
            "max": 3
          },
          "loadEventEnd": {
            "median": 5279,
            "mean": 5196,
            "mdev": 340.6159,
            "stddev": 590,
            "min": 4436,
            "p10": 4436,
            "p90": 5874,
            "p99": 5874,
            "max": 5874
          },
          "loadEventStart": {
            "median": 5279,
            "mean": 5196,
            "mdev": 340.643,
            "stddev": 590,
            "min": 4435,
            "p10": 4435,
            "p90": 5873,
            "p99": 5873,
            "max": 5873
          },
          "redirectEnd": {
            "median": 0,
            "mean": 0,
            "mdev": 0,
            "stddev": 0,
            "min": 0,
            "p10": 0,
            "p90": 0,
            "p99": 0,
            "max": 0
          },
          "redirectStart": {
            "median": 0,
            "mean": 0,
            "mdev": 0,
            "stddev": 0,
            "min": 0,
            "p10": 0,
            "p90": 0,
            "p99": 0,
            "max": 0
          },
          "requestStart": {
            "median": 696,
            "mean": 691,
            "mdev": 21.3247,
            "stddev": 37,
            "min": 643,
            "p10": 643,
            "p90": 733,
            "p99": 733,
            "max": 733
          },
          "responseEnd": {
            "median": 1224,
            "mean": 1471,
            "mdev": 306.5494,
            "stddev": 531,
            "min": 981,
            "p10": 981,
            "p90": 2209,
            "p99": 2209,
            "max": 2209
          },
          "responseStart": {
            "median": 1025,
            "mean": 1070,
            "mdev": 62.2135,
            "stddev": 108,
            "min": 967,
            "p10": 967,
            "p90": 1219,
            "p99": 1219,
            "max": 1219
          },
          "secureConnectionStart": {
            "median": 318,
            "mean": 311,
            "mdev": 8.1149,
            "stddev": 14,
            "min": 291,
            "p10": 291,
            "p90": 323,
            "p99": 323,
            "max": 323
          },
          "startTime": {
            "median": 0,
            "mean": 0,
            "mdev": 0,
            "stddev": 0,
            "min": 0,
            "p10": 0,
            "p90": 0,
            "p99": 0,
            "max": 0
          },
          "unloadEventEnd": {
            "median": 0,
            "mean": 0,
            "mdev": 0,
            "stddev": 0,
            "min": 0,
            "p10": 0,
            "p90": 0,
            "p99": 0,
            "max": 0
          },
          "unloadEventStart": {
            "median": 0,
            "mean": 0,
            "mdev": 0,
            "stddev": 0,
            "min": 0,
            "p10": 0,
            "p90": 0,
            "p99": 0,
            "max": 0
          },
          "workerStart": {
            "median": 0,
            "mean": 0,
            "mdev": 0,
            "stddev": 0,
            "min": 0,
            "p10": 0,
            "p90": 0,
            "p99": 0,
            "max": 0
          }
        },
        "pageTimings": {
          "backEndTime": {
            "median": 1025,
            "mean": 1070,
            "mdev": 62.2135,
            "stddev": 108,
            "min": 967,
            "p10": 967,
            "p90": 1219,
            "p99": 1219,
            "max": 1219
          },
          "domContentLoadedTime": {
            "median": 3913,
            "mean": 4318,
            "mdev": 422.2157,
            "stddev": 731,
            "min": 3697,
            "p10": 3697,
            "p90": 5345,
            "p99": 5345,
            "max": 5345
          },
          "domInteractiveTime": {
            "median": 3846,
            "mean": 4232,
            "mdev": 408.4535,
            "stddev": 707,
            "min": 3625,
            "p10": 3625,
            "p90": 5224,
            "p99": 5224,
            "max": 5224
          },
          "domainLookupTime": {
            "median": 0,
            "mean": 0,
            "mdev": 0,
            "stddev": 0,
            "min": 0,
            "p10": 0,
            "p90": 0,
            "p99": 0,
            "max": 0
          },
          "frontEndTime": {
            "median": 3665,
            "mean": 3725,
            "mdev": 143.527,
            "stddev": 249,
            "min": 3455,
            "p10": 3455,
            "p90": 4055,
            "p99": 4055,
            "max": 4055
          },
          "pageDownloadTime": {
            "median": 14,
            "mean": 400,
            "mdev": 319.531,
            "stddev": 553,
            "min": 4,
            "p10": 4,
            "p90": 1183,
            "p99": 1183,
            "max": 1183
          },
          "pageLoadTime": {
            "median": 5279,
            "mean": 5196,
            "mdev": 340.643,
            "stddev": 590,
            "min": 4435,
            "p10": 4435,
            "p90": 5873,
            "p99": 5873,
            "max": 5873
          },
          "redirectionTime": {
            "median": 0,
            "mean": 0,
            "mdev": 0,
            "stddev": 0,
            "min": 0,
            "p10": 0,
            "p90": 0,
            "p99": 0,
            "max": 0
          },
          "serverConnectionTime": {
            "median": 658,
            "mean": 654,
            "mdev": 21.5217,
            "stddev": 37,
            "min": 606,
            "p10": 606,
            "p90": 697,
            "p99": 697,
            "max": 697
          },
          "serverResponseTime": {
            "median": 580,
            "mean": 780,
            "mdev": 292.1282,
            "stddev": 506,
            "min": 285,
            "p10": 285,
            "p90": 1475,
            "p99": 1475,
            "max": 1475
          }
        },
        "rumSpeedIndex": {
          "median": 1025,
          "mean": 1070,
          "mdev": 62.3984,
          "stddev": 108,
          "min": 966,
          "p10": 966,
          "p90": 1219,
          "p99": 1219,
          "max": 1219
        },
        "timeToContentfulPaint": {
          "median": 3098,
          "mean": 3366,
          "mdev": 337.6416,
          "stddev": 585,
          "min": 2823,
          "p10": 2823,
          "p90": 4178,
          "p99": 4178,
          "max": 4178
        },
        "timeToDomContentFlushed": {
          "median": 3856,
          "mean": 4254,
          "mdev": 419.5824,
          "stddev": 727,
          "min": 3633,
          "p10": 3633,
          "p90": 5274,
          "p99": 5274,
          "max": 5274
        }
      }
    }
  }
]