[
  {
    "info": {
      "browsertime": {
        "version": "8.4.0"
      },
      "url": "https://www.wayfair.com/contact_us",
      "timestamp": "2021-05-06T21:34:10+04:00",
      "connectivity": {
        "engine": "external",
        "profile": "native"
      },
      "extra": {}
    },
    "files": {
      "video": [],
      "screenshot": [],
      "timeline": [],
      "consoleLog": [],
      "netLog": [],
      "perfLog": []
    },
    "cdp": {
      "performance": []
    },
    "timestamps": [
      "2021-05-06T21:33:58+04:00",
      "2021-05-06T21:34:17+04:00",
      "2021-05-06T21:34:36+04:00"
    ],
    "browserScripts": [
      {
        "browser": {
          "appConstants": {
            "ACCESSIBILITY": true,
            "ANDROID_PACKAGE_NAME": "org.mozilla.firefox",
            "ASAN": false,
            "ASAN_REPORTER": false,
            "BROWSER_CHROME_URL": "chrome://browser/content/browser.xul",
            "DEBUG": false,
            "DEBUG_JS_MODULES": "",
            "DLL_PREFIX": "lib",
            "DLL_SUFFIX": ".so",
            "EARLY_BETA_OR_EARLIER": false,
            "FENNEC_NIGHTLY": false,
            "HAVE_SHELL_SERVICE": false,
            "HAVE_USR_LIB64_DIR": false,
            "MENUBAR_CAN_AUTOHIDE": false,
            "MOZILLA_OFFICIAL": true,
            "MOZ_ALLOW_LEGACY_EXTENSIONS": false,
            "MOZ_ANDROID_ACTIVITY_STREAM": false,
            "MOZ_ANDROID_HISTORY": true,
            "MOZ_ANDROID_MOZILLA_ONLINE": false,
            "MOZ_APP_NAME": "fennec",
            "MOZ_APP_VERSION": "68.1.1",
            "MOZ_APP_VERSION_DISPLAY": "68.1.1",
            "MOZ_BING_API_CLIENTID": "no-bing-api-clientid",
            "MOZ_BING_API_KEY": "no-bing-api-key",
            "MOZ_BITS_DOWNLOAD": false,
            "MOZ_BUILD_APP": "mobile/android",
            "MOZ_CODE_COVERAGE": false,
            "MOZ_CRASHREPORTER": true,
            "MOZ_DATA_REPORTING": true,
            "MOZ_DEV_EDITION": false,
            "MOZ_GECKO_PROFILER": true,
            "MOZ_GOOGLE_LOCATION_SERVICE_API_KEY": "AIzaSyB2h2OuRcUgy5N-5hsZqiPW6sH3n_rptiQ",
            "MOZ_GOOGLE_SAFEBROWSING_API_KEY": "AIzaSyC7jsptDS3am4tPx4r3nxis7IMjBc5Dovo",
            "MOZ_GRAPHENE": false,
            "MOZ_MACBUNDLE_NAME": "Firefox.app",
            "MOZ_MAINTENANCE_SERVICE": false,
            "MOZ_MOZILLA_API_KEY": "3b4d27dd-703d-4094-8398-4de2c763505a",
            "MOZ_NEW_CERT_STORAGE": false,
            "MOZ_NEW_NOTIFICATION_STORE": false,
            "MOZ_NEW_XULSTORE": false,
            "MOZ_OFFICIAL_BRANDING": false,
            "MOZ_PLACES": false,
            "MOZ_REQUIRE_SIGNING": false,
            "MOZ_SANDBOX": false,
            "MOZ_SERVICES_HEALTHREPORT": true,
            "MOZ_SERVICES_SYNC": false,
            "MOZ_SWITCHBOARD": true,
            "MOZ_SYSTEM_NSS": false,
            "MOZ_TELEMETRY_ON_BY_DEFAULT": false,
            "MOZ_TELEMETRY_REPORTING": true,
            "MOZ_UNSIGNED_SCOPES": 0,
            "MOZ_UPDATER": false,
            "MOZ_UPDATE_CHANNEL": "release",
            "MOZ_WEBRTC": true,
            "MOZ_WIDGET_GTK": false,
            "MOZ_WIDGET_TOOLKIT": "android",
            "NIGHTLY_BUILD": false,
            "OMNIJAR_NAME": "assets/omni.ja",
            "RELEASE_OR_BETA": true,
            "SOURCE_REVISION_URL": "https://hg.mozilla.org/releases/mozilla-esr68/rev/d2e0b9e17b9bc1ef02606c8006b73293f7892ad5",
            "TELEMETRY_PING_FORMAT_VERSION": 4,
            "XP_UNIX": true,
            "isPlatformAndVersionAtLeast": {},
            "isPlatformAndVersionAtMost": {},
            "platform": "android"
          },
          "asyncAppConstants": {
            "ACCESSIBILITY": true,
            "ANDROID_PACKAGE_NAME": "org.mozilla.firefox",
            "ASAN": false,
            "ASAN_REPORTER": false,
            "BROWSER_CHROME_URL": "chrome://browser/content/browser.xul",
            "DEBUG": false,
            "DEBUG_JS_MODULES": "",
            "DLL_PREFIX": "lib",
            "DLL_SUFFIX": ".so",
            "EARLY_BETA_OR_EARLIER": false,
            "FENNEC_NIGHTLY": false,
            "HAVE_SHELL_SERVICE": false,
            "HAVE_USR_LIB64_DIR": false,
            "MENUBAR_CAN_AUTOHIDE": false,
            "MOZILLA_OFFICIAL": true,
            "MOZ_ALLOW_LEGACY_EXTENSIONS": false,
            "MOZ_ANDROID_ACTIVITY_STREAM": false,
            "MOZ_ANDROID_HISTORY": true,
            "MOZ_ANDROID_MOZILLA_ONLINE": false,
            "MOZ_APP_NAME": "fennec",
            "MOZ_APP_VERSION": "68.1.1",
            "MOZ_APP_VERSION_DISPLAY": "68.1.1",
            "MOZ_BING_API_CLIENTID": "no-bing-api-clientid",
            "MOZ_BING_API_KEY": "no-bing-api-key",
            "MOZ_BITS_DOWNLOAD": false,
            "MOZ_BUILD_APP": "mobile/android",
            "MOZ_CODE_COVERAGE": false,
            "MOZ_CRASHREPORTER": true,
            "MOZ_DATA_REPORTING": true,
            "MOZ_DEV_EDITION": false,
            "MOZ_GECKO_PROFILER": true,
            "MOZ_GOOGLE_LOCATION_SERVICE_API_KEY": "AIzaSyB2h2OuRcUgy5N-5hsZqiPW6sH3n_rptiQ",
            "MOZ_GOOGLE_SAFEBROWSING_API_KEY": "AIzaSyC7jsptDS3am4tPx4r3nxis7IMjBc5Dovo",
            "MOZ_GRAPHENE": false,
            "MOZ_MACBUNDLE_NAME": "Firefox.app",
            "MOZ_MAINTENANCE_SERVICE": false,
            "MOZ_MOZILLA_API_KEY": "3b4d27dd-703d-4094-8398-4de2c763505a",
            "MOZ_NEW_CERT_STORAGE": false,
            "MOZ_NEW_NOTIFICATION_STORE": false,
            "MOZ_NEW_XULSTORE": false,
            "MOZ_OFFICIAL_BRANDING": false,
            "MOZ_PLACES": false,
            "MOZ_REQUIRE_SIGNING": false,
            "MOZ_SANDBOX": false,
            "MOZ_SERVICES_HEALTHREPORT": true,
            "MOZ_SERVICES_SYNC": false,
            "MOZ_SWITCHBOARD": true,
            "MOZ_SYSTEM_NSS": false,
            "MOZ_TELEMETRY_ON_BY_DEFAULT": false,
            "MOZ_TELEMETRY_REPORTING": true,
            "MOZ_UNSIGNED_SCOPES": 0,
            "MOZ_UPDATER": false,
            "MOZ_UPDATE_CHANNEL": "release",
            "MOZ_WEBRTC": true,
            "MOZ_WIDGET_GTK": false,
            "MOZ_WIDGET_TOOLKIT": "android",
            "NIGHTLY_BUILD": false,
            "OMNIJAR_NAME": "assets/omni.ja",
            "RELEASE_OR_BETA": true,
            "SOURCE_REVISION_URL": "https://hg.mozilla.org/releases/mozilla-esr68/rev/d2e0b9e17b9bc1ef02606c8006b73293f7892ad5",
            "TELEMETRY_PING_FORMAT_VERSION": 4,
            "XP_UNIX": true,
            "isPlatformAndVersionAtLeast": {},
            "isPlatformAndVersionAtMost": {},
            "platform": "android"
          },
          "userAgent": "Mozilla/5.0 (Android 9; Mobile; rv:68.0) Gecko/68.0 Firefox/68.0",
          "windowSize": "360x612"
        },
        "pageinfo": {
          "documentHeight": 612,
          "documentSize": {
            "decodedBodySize": 84306,
            "encodedBodySize": 28537,
            "transferSize": 30535
          },
          "documentTitle": "Wayfair.com - Online Home Store for Furniture, Decor, Outdoors & More |",
          "documentWidth": 360,
          "domElements": 857,
          "navigationStartTime": 1620322438476,
          "nextHopProtocol": "h2",
          "resources": {
            "count": 0,
            "duration": 0
          },
          "responsive": true,
          "url": "https://www.wayfair.com/v/captcha/show?goto=https%3A%2F%2Fwww.wayfair.com%2Fcontact_us%3F&px=1&captcha_status=0",
          "visualElements": {
            "heroes": [
              {
                "filename": null,
                "height": 60,
                "name": "Heading",
                "width": 328,
                "x": 16,
                "y": 32
              }
            ],
            "viewport": {
              "height": 612,
              "width": 360
            }
          }
        },
        "timings": {
          "firstPaint": 1935,
          "loadEventEnd": 4826,
          "navigationTiming": {
            "connectStart": 717,
            "domComplete": 4818,
            "domContentLoadedEventEnd": 2053,
            "domContentLoadedEventStart": 2045,
            "domInteractive": 2034,
            "domainLookupEnd": 717,
            "domainLookupStart": 717,
            "duration": 4826,
            "fetchStart": 717,
            "loadEventEnd": 4826,
            "loadEventStart": 4818,
            "redirectEnd": 703,
            "redirectStart": 3,
            "requestStart": 758,
            "responseEnd": 1128,
            "responseStart": 1086,
            "secureConnectionStart": 0,
            "startTime": 0,
            "unloadEventEnd": 0,
            "unloadEventStart": 0,
            "workerStart": 0
          },
          "pageTimings": {
            "backEndTime": 1086,
            "domContentLoadedTime": 2045,
            "domInteractiveTime": 2034,
            "domainLookupTime": 0,
            "frontEndTime": 3689,
            "pageDownloadTime": 42,
            "pageLoadTime": 4818,
            "redirectionTime": 700,
            "serverConnectionTime": 0,
            "serverResponseTime": 370
          },
          "rumSpeedIndex": 1086,
          "timeToContentfulPaint": 2022,
          "timeToDomContentFlushed": 2056,
          "userTimings": {
            "marks": [
              {
                "name": "wf_done",
                "startTime": 2544.58
              },
              {
                "name": "wf_done_end",
                "startTime": 2545.44
              },
              {
                "name": "wf_postload_start",
                "startTime": 4818.36
              },
              {
                "name": "wf_postload_end",
                "startTime": 5787.12
              },
              {
                "name": "wf_delayed_end",
                "startTime": 9828.4
              }
            ],
            "measures": []
          }
        }
      },
      {
        "browser": {
          "appConstants": {
            "ACCESSIBILITY": true,
            "ANDROID_PACKAGE_NAME": "org.mozilla.firefox",
            "ASAN": false,
            "ASAN_REPORTER": false,
            "BROWSER_CHROME_URL": "chrome://browser/content/browser.xul",
            "DEBUG": false,
            "DEBUG_JS_MODULES": "",
            "DLL_PREFIX": "lib",
            "DLL_SUFFIX": ".so",
            "EARLY_BETA_OR_EARLIER": false,
            "FENNEC_NIGHTLY": false,
            "HAVE_SHELL_SERVICE": false,
            "HAVE_USR_LIB64_DIR": false,
            "MENUBAR_CAN_AUTOHIDE": false,
            "MOZILLA_OFFICIAL": true,
            "MOZ_ALLOW_LEGACY_EXTENSIONS": false,
            "MOZ_ANDROID_ACTIVITY_STREAM": false,
            "MOZ_ANDROID_HISTORY": true,
            "MOZ_ANDROID_MOZILLA_ONLINE": false,
            "MOZ_APP_NAME": "fennec",
            "MOZ_APP_VERSION": "68.1.1",
            "MOZ_APP_VERSION_DISPLAY": "68.1.1",
            "MOZ_BING_API_CLIENTID": "no-bing-api-clientid",
            "MOZ_BING_API_KEY": "no-bing-api-key",
            "MOZ_BITS_DOWNLOAD": false,
            "MOZ_BUILD_APP": "mobile/android",
            "MOZ_CODE_COVERAGE": false,
            "MOZ_CRASHREPORTER": true,
            "MOZ_DATA_REPORTING": true,
            "MOZ_DEV_EDITION": false,
            "MOZ_GECKO_PROFILER": true,
            "MOZ_GOOGLE_LOCATION_SERVICE_API_KEY": "AIzaSyB2h2OuRcUgy5N-5hsZqiPW6sH3n_rptiQ",
            "MOZ_GOOGLE_SAFEBROWSING_API_KEY": "AIzaSyC7jsptDS3am4tPx4r3nxis7IMjBc5Dovo",
            "MOZ_GRAPHENE": false,
            "MOZ_MACBUNDLE_NAME": "Firefox.app",
            "MOZ_MAINTENANCE_SERVICE": false,
            "MOZ_MOZILLA_API_KEY": "3b4d27dd-703d-4094-8398-4de2c763505a",
            "MOZ_NEW_CERT_STORAGE": false,
            "MOZ_NEW_NOTIFICATION_STORE": false,
            "MOZ_NEW_XULSTORE": false,
            "MOZ_OFFICIAL_BRANDING": false,
            "MOZ_PLACES": false,
            "MOZ_REQUIRE_SIGNING": false,
            "MOZ_SANDBOX": false,
            "MOZ_SERVICES_HEALTHREPORT": true,
            "MOZ_SERVICES_SYNC": false,
            "MOZ_SWITCHBOARD": true,
            "MOZ_SYSTEM_NSS": false,
            "MOZ_TELEMETRY_ON_BY_DEFAULT": false,
            "MOZ_TELEMETRY_REPORTING": true,
            "MOZ_UNSIGNED_SCOPES": 0,
            "MOZ_UPDATER": false,
            "MOZ_UPDATE_CHANNEL": "release",
            "MOZ_WEBRTC": true,
            "MOZ_WIDGET_GTK": false,
            "MOZ_WIDGET_TOOLKIT": "android",
            "NIGHTLY_BUILD": false,
            "OMNIJAR_NAME": "assets/omni.ja",
            "RELEASE_OR_BETA": true,
            "SOURCE_REVISION_URL": "https://hg.mozilla.org/releases/mozilla-esr68/rev/d2e0b9e17b9bc1ef02606c8006b73293f7892ad5",
            "TELEMETRY_PING_FORMAT_VERSION": 4,
            "XP_UNIX": true,
            "isPlatformAndVersionAtLeast": {},
            "isPlatformAndVersionAtMost": {},
            "platform": "android"
          },
          "asyncAppConstants": {
            "ACCESSIBILITY": true,
            "ANDROID_PACKAGE_NAME": "org.mozilla.firefox",
            "ASAN": false,
            "ASAN_REPORTER": false,
            "BROWSER_CHROME_URL": "chrome://browser/content/browser.xul",
            "DEBUG": false,
            "DEBUG_JS_MODULES": "",
            "DLL_PREFIX": "lib",
            "DLL_SUFFIX": ".so",
            "EARLY_BETA_OR_EARLIER": false,
            "FENNEC_NIGHTLY": false,
            "HAVE_SHELL_SERVICE": false,
            "HAVE_USR_LIB64_DIR": false,
            "MENUBAR_CAN_AUTOHIDE": false,
            "MOZILLA_OFFICIAL": true,
            "MOZ_ALLOW_LEGACY_EXTENSIONS": false,
            "MOZ_ANDROID_ACTIVITY_STREAM": false,
            "MOZ_ANDROID_HISTORY": true,
            "MOZ_ANDROID_MOZILLA_ONLINE": false,
            "MOZ_APP_NAME": "fennec",
            "MOZ_APP_VERSION": "68.1.1",
            "MOZ_APP_VERSION_DISPLAY": "68.1.1",
            "MOZ_BING_API_CLIENTID": "no-bing-api-clientid",
            "MOZ_BING_API_KEY": "no-bing-api-key",
            "MOZ_BITS_DOWNLOAD": false,
            "MOZ_BUILD_APP": "mobile/android",
            "MOZ_CODE_COVERAGE": false,
            "MOZ_CRASHREPORTER": true,
            "MOZ_DATA_REPORTING": true,
            "MOZ_DEV_EDITION": false,
            "MOZ_GECKO_PROFILER": true,
            "MOZ_GOOGLE_LOCATION_SERVICE_API_KEY": "AIzaSyB2h2OuRcUgy5N-5hsZqiPW6sH3n_rptiQ",
            "MOZ_GOOGLE_SAFEBROWSING_API_KEY": "AIzaSyC7jsptDS3am4tPx4r3nxis7IMjBc5Dovo",
            "MOZ_GRAPHENE": false,
            "MOZ_MACBUNDLE_NAME": "Firefox.app",
            "MOZ_MAINTENANCE_SERVICE": false,
            "MOZ_MOZILLA_API_KEY": "3b4d27dd-703d-4094-8398-4de2c763505a",
            "MOZ_NEW_CERT_STORAGE": false,
            "MOZ_NEW_NOTIFICATION_STORE": false,
            "MOZ_NEW_XULSTORE": false,
            "MOZ_OFFICIAL_BRANDING": false,
            "MOZ_PLACES": false,
            "MOZ_REQUIRE_SIGNING": false,
            "MOZ_SANDBOX": false,
            "MOZ_SERVICES_HEALTHREPORT": true,
            "MOZ_SERVICES_SYNC": false,
            "MOZ_SWITCHBOARD": true,
            "MOZ_SYSTEM_NSS": false,
            "MOZ_TELEMETRY_ON_BY_DEFAULT": false,
            "MOZ_TELEMETRY_REPORTING": true,
            "MOZ_UNSIGNED_SCOPES": 0,
            "MOZ_UPDATER": false,
            "MOZ_UPDATE_CHANNEL": "release",
            "MOZ_WEBRTC": true,
            "MOZ_WIDGET_GTK": false,
            "MOZ_WIDGET_TOOLKIT": "android",
            "NIGHTLY_BUILD": false,
            "OMNIJAR_NAME": "assets/omni.ja",
            "RELEASE_OR_BETA": true,
            "SOURCE_REVISION_URL": "https://hg.mozilla.org/releases/mozilla-esr68/rev/d2e0b9e17b9bc1ef02606c8006b73293f7892ad5",
            "TELEMETRY_PING_FORMAT_VERSION": 4,
            "XP_UNIX": true,
            "isPlatformAndVersionAtLeast": {},
            "isPlatformAndVersionAtMost": {},
            "platform": "android"
          },
          "userAgent": "Mozilla/5.0 (Android 9; Mobile; rv:68.0) Gecko/68.0 Firefox/68.0",
          "windowSize": "360x612"
        },
        "pageinfo": {
          "documentHeight": 612,
          "documentSize": {
            "decodedBodySize": 83360,
            "encodedBodySize": 28275,
            "transferSize": 30272
          },
          "documentTitle": "Wayfair.com - Online Home Store for Furniture, Decor, Outdoors & More |",
          "documentWidth": 360,
          "domElements": 857,
          "navigationStartTime": 1620322457408,
          "nextHopProtocol": "h2",
          "resources": {
            "count": 0,
            "duration": 0
          },
          "responsive": true,
          "url": "https://www.wayfair.com/v/captcha/show?goto=https%3A%2F%2Fwww.wayfair.com%2Fcontact_us%3F&px=1&captcha_status=0",
          "visualElements": {
            "heroes": [
              {
                "filename": null,
                "height": 60,
                "name": "Heading",
                "width": 328,
                "x": 16,
                "y": 32
              }
            ],
            "viewport": {
              "height": 612,
              "width": 360
            }
          }
        },
        "timings": {
          "firstPaint": 2094,
          "loadEventEnd": 5726,
          "navigationTiming": {
            "connectStart": 727,
            "domComplete": 5714,
            "domContentLoadedEventEnd": 2225,
            "domContentLoadedEventStart": 2219,
            "domInteractive": 2205,
            "domainLookupEnd": 727,
            "domainLookupStart": 727,
            "duration": 5726,
            "fetchStart": 727,
            "loadEventEnd": 5726,
            "loadEventStart": 5714,
            "redirectEnd": 715,
            "redirectStart": 3,
            "requestStart": 768,
            "responseEnd": 1077,
            "responseStart": 1077,
            "secureConnectionStart": 0,
            "startTime": 0,
            "unloadEventEnd": 0,
            "unloadEventStart": 0,
            "workerStart": 0
          },
          "pageTimings": {
            "backEndTime": 1077,
            "domContentLoadedTime": 2219,
            "domInteractiveTime": 2205,
            "domainLookupTime": 0,
            "frontEndTime": 4637,
            "pageDownloadTime": 0,
            "pageLoadTime": 5714,
            "redirectionTime": 712,
            "serverConnectionTime": 0,
            "serverResponseTime": 309
          },
          "rumSpeedIndex": 1076,
          "timeToContentfulPaint": 2191,
          "timeToDomContentFlushed": 2251,
          "userTimings": {
            "marks": [
              {
                "name": "wf_done",
                "startTime": 2690.36
              },
              {
                "name": "wf_done_end",
                "startTime": 2691.2200000000003
              },
              {
                "name": "wf_postload_start",
                "startTime": 5715.9400000000005
              },
              {
                "name": "wf_postload_end",
                "startTime": 6110.76
              },
              {
                "name": "wf_delayed_end",
                "startTime": 10723.72
              }
            ],
            "measures": []
          }
        }
      },
      {
        "browser": {
          "appConstants": {
            "ACCESSIBILITY": true,
            "ANDROID_PACKAGE_NAME": "org.mozilla.firefox",
            "ASAN": false,
            "ASAN_REPORTER": false,
            "BROWSER_CHROME_URL": "chrome://browser/content/browser.xul",
            "DEBUG": false,
            "DEBUG_JS_MODULES": "",
            "DLL_PREFIX": "lib",
            "DLL_SUFFIX": ".so",
            "EARLY_BETA_OR_EARLIER": false,
            "FENNEC_NIGHTLY": false,
            "HAVE_SHELL_SERVICE": false,
            "HAVE_USR_LIB64_DIR": false,
            "MENUBAR_CAN_AUTOHIDE": false,
            "MOZILLA_OFFICIAL": true,
            "MOZ_ALLOW_LEGACY_EXTENSIONS": false,
            "MOZ_ANDROID_ACTIVITY_STREAM": false,
            "MOZ_ANDROID_HISTORY": true,
            "MOZ_ANDROID_MOZILLA_ONLINE": false,
            "MOZ_APP_NAME": "fennec",
            "MOZ_APP_VERSION": "68.1.1",
            "MOZ_APP_VERSION_DISPLAY": "68.1.1",
            "MOZ_BING_API_CLIENTID": "no-bing-api-clientid",
            "MOZ_BING_API_KEY": "no-bing-api-key",
            "MOZ_BITS_DOWNLOAD": false,
            "MOZ_BUILD_APP": "mobile/android",
            "MOZ_CODE_COVERAGE": false,
            "MOZ_CRASHREPORTER": true,
            "MOZ_DATA_REPORTING": true,
            "MOZ_DEV_EDITION": false,
            "MOZ_GECKO_PROFILER": true,
            "MOZ_GOOGLE_LOCATION_SERVICE_API_KEY": "AIzaSyB2h2OuRcUgy5N-5hsZqiPW6sH3n_rptiQ",
            "MOZ_GOOGLE_SAFEBROWSING_API_KEY": "AIzaSyC7jsptDS3am4tPx4r3nxis7IMjBc5Dovo",
            "MOZ_GRAPHENE": false,
            "MOZ_MACBUNDLE_NAME": "Firefox.app",
            "MOZ_MAINTENANCE_SERVICE": false,
            "MOZ_MOZILLA_API_KEY": "3b4d27dd-703d-4094-8398-4de2c763505a",
            "MOZ_NEW_CERT_STORAGE": false,
            "MOZ_NEW_NOTIFICATION_STORE": false,
            "MOZ_NEW_XULSTORE": false,
            "MOZ_OFFICIAL_BRANDING": false,
            "MOZ_PLACES": false,
            "MOZ_REQUIRE_SIGNING": false,
            "MOZ_SANDBOX": false,
            "MOZ_SERVICES_HEALTHREPORT": true,
            "MOZ_SERVICES_SYNC": false,
            "MOZ_SWITCHBOARD": true,
            "MOZ_SYSTEM_NSS": false,
            "MOZ_TELEMETRY_ON_BY_DEFAULT": false,
            "MOZ_TELEMETRY_REPORTING": true,
            "MOZ_UNSIGNED_SCOPES": 0,
            "MOZ_UPDATER": false,
            "MOZ_UPDATE_CHANNEL": "release",
            "MOZ_WEBRTC": true,
            "MOZ_WIDGET_GTK": false,
            "MOZ_WIDGET_TOOLKIT": "android",
            "NIGHTLY_BUILD": false,
            "OMNIJAR_NAME": "assets/omni.ja",
            "RELEASE_OR_BETA": true,
            "SOURCE_REVISION_URL": "https://hg.mozilla.org/releases/mozilla-esr68/rev/d2e0b9e17b9bc1ef02606c8006b73293f7892ad5",
            "TELEMETRY_PING_FORMAT_VERSION": 4,
            "XP_UNIX": true,
            "isPlatformAndVersionAtLeast": {},
            "isPlatformAndVersionAtMost": {},
            "platform": "android"
          },
          "asyncAppConstants": {
            "ACCESSIBILITY": true,
            "ANDROID_PACKAGE_NAME": "org.mozilla.firefox",
            "ASAN": false,
            "ASAN_REPORTER": false,
            "BROWSER_CHROME_URL": "chrome://browser/content/browser.xul",
            "DEBUG": false,
            "DEBUG_JS_MODULES": "",
            "DLL_PREFIX": "lib",
            "DLL_SUFFIX": ".so",
            "EARLY_BETA_OR_EARLIER": false,
            "FENNEC_NIGHTLY": false,
            "HAVE_SHELL_SERVICE": false,
            "HAVE_USR_LIB64_DIR": false,
            "MENUBAR_CAN_AUTOHIDE": false,
            "MOZILLA_OFFICIAL": true,
            "MOZ_ALLOW_LEGACY_EXTENSIONS": false,
            "MOZ_ANDROID_ACTIVITY_STREAM": false,
            "MOZ_ANDROID_HISTORY": true,
            "MOZ_ANDROID_MOZILLA_ONLINE": false,
            "MOZ_APP_NAME": "fennec",
            "MOZ_APP_VERSION": "68.1.1",
            "MOZ_APP_VERSION_DISPLAY": "68.1.1",
            "MOZ_BING_API_CLIENTID": "no-bing-api-clientid",
            "MOZ_BING_API_KEY": "no-bing-api-key",
            "MOZ_BITS_DOWNLOAD": false,
            "MOZ_BUILD_APP": "mobile/android",
            "MOZ_CODE_COVERAGE": false,
            "MOZ_CRASHREPORTER": true,
            "MOZ_DATA_REPORTING": true,
            "MOZ_DEV_EDITION": false,
            "MOZ_GECKO_PROFILER": true,
            "MOZ_GOOGLE_LOCATION_SERVICE_API_KEY": "AIzaSyB2h2OuRcUgy5N-5hsZqiPW6sH3n_rptiQ",
            "MOZ_GOOGLE_SAFEBROWSING_API_KEY": "AIzaSyC7jsptDS3am4tPx4r3nxis7IMjBc5Dovo",
            "MOZ_GRAPHENE": false,
            "MOZ_MACBUNDLE_NAME": "Firefox.app",
            "MOZ_MAINTENANCE_SERVICE": false,
            "MOZ_MOZILLA_API_KEY": "3b4d27dd-703d-4094-8398-4de2c763505a",
            "MOZ_NEW_CERT_STORAGE": false,
            "MOZ_NEW_NOTIFICATION_STORE": false,
            "MOZ_NEW_XULSTORE": false,
            "MOZ_OFFICIAL_BRANDING": false,
            "MOZ_PLACES": false,
            "MOZ_REQUIRE_SIGNING": false,
            "MOZ_SANDBOX": false,
            "MOZ_SERVICES_HEALTHREPORT": true,
            "MOZ_SERVICES_SYNC": false,
            "MOZ_SWITCHBOARD": true,
            "MOZ_SYSTEM_NSS": false,
            "MOZ_TELEMETRY_ON_BY_DEFAULT": false,
            "MOZ_TELEMETRY_REPORTING": true,
            "MOZ_UNSIGNED_SCOPES": 0,
            "MOZ_UPDATER": false,
            "MOZ_UPDATE_CHANNEL": "release",
            "MOZ_WEBRTC": true,
            "MOZ_WIDGET_GTK": false,
            "MOZ_WIDGET_TOOLKIT": "android",
            "NIGHTLY_BUILD": false,
            "OMNIJAR_NAME": "assets/omni.ja",
            "RELEASE_OR_BETA": true,
            "SOURCE_REVISION_URL": "https://hg.mozilla.org/releases/mozilla-esr68/rev/d2e0b9e17b9bc1ef02606c8006b73293f7892ad5",
            "TELEMETRY_PING_FORMAT_VERSION": 4,
            "XP_UNIX": true,
            "isPlatformAndVersionAtLeast": {},
            "isPlatformAndVersionAtMost": {},
            "platform": "android"
          },
          "userAgent": "Mozilla/5.0 (Android 9; Mobile; rv:68.0) Gecko/68.0 Firefox/68.0",
          "windowSize": "360x612"
        },
        "pageinfo": {
          "documentHeight": 612,
          "documentSize": {
            "decodedBodySize": 83254,
            "encodedBodySize": 28203,
            "transferSize": 30200
          },
          "documentTitle": "Wayfair.com - Online Home Store for Furniture, Decor, Outdoors & More |",
          "documentWidth": 360,
          "domElements": 857,
          "navigationStartTime": 1620322476320,
          "nextHopProtocol": "h2",
          "resources": {
            "count": 0,
            "duration": 0
          },
          "responsive": true,
          "url": "https://www.wayfair.com/v/captcha/show?goto=https%3A%2F%2Fwww.wayfair.com%2Fcontact_us%3F&px=1&captcha_status=0",
          "visualElements": {
            "heroes": [
              {
                "filename": null,
                "height": 60,
                "name": "Heading",
                "width": 328,
                "x": 16,
                "y": 32
              }
            ],
            "viewport": {
              "height": 612,
              "width": 360
            }
          }
        },
        "timings": {
          "firstPaint": 2096,
          "loadEventEnd": 5282,
          "navigationTiming": {
            "connectStart": 682,
            "domComplete": 5273,
            "domContentLoadedEventEnd": 2223,
            "domContentLoadedEventStart": 2216,
            "domInteractive": 2185,
            "domainLookupEnd": 682,
            "domainLookupStart": 682,
            "duration": 5282,
            "fetchStart": 682,
            "loadEventEnd": 5282,
            "loadEventStart": 5273,
            "redirectEnd": 668,
            "redirectStart": 2,
            "requestStart": 720,
            "responseEnd": 1123,
            "responseStart": 1086,
            "secureConnectionStart": 0,
            "startTime": 0,
            "unloadEventEnd": 0,
            "unloadEventStart": 0,
            "workerStart": 0
          },
          "pageTimings": {
            "backEndTime": 1086,
            "domContentLoadedTime": 2216,
            "domInteractiveTime": 2185,
            "domainLookupTime": 0,
            "frontEndTime": 4150,
            "pageDownloadTime": 37,
            "pageLoadTime": 5273,
            "redirectionTime": 665,
            "serverConnectionTime": 0,
            "serverResponseTime": 403
          },
          "rumSpeedIndex": 1085,
          "timeToContentfulPaint": 2180,
          "timeToDomContentFlushed": 2205,
          "userTimings": {
            "marks": [
              {
                "name": "wf_done",
                "startTime": 2668.68
              },
              {
                "name": "wf_done_end",
                "startTime": 2669.56
              },
              {
                "name": "wf_postload_start",
                "startTime": 5273.8
              },
              {
                "name": "wf_postload_end",
                "startTime": 5925.54
              },
              {
                "name": "wf_delayed_end",
                "startTime": 10323.38
              }
            ],
            "measures": []
          }
        }
      }
    ],
    "visualMetrics": [],
    "cpu": [],
    "extras": [
      {},
      {},
      {}
    ],
    "fullyLoaded": [],
    "errors": [
      [],
      [],
      []
    ],
    "statistics": {
      "browser": {
        "appConstants": {
          "MOZ_UNSIGNED_SCOPES": {
            "median": 0,
            "mean": 0,
            "mdev": 0,
            "stddev": 0,
            "min": 0,
            "p10": 0,
            "p90": 0,
            "p99": 0,
            "max": 0
          },
          "TELEMETRY_PING_FORMAT_VERSION": {
            "median": 4,
            "mean": 4,
            "mdev": 0,
            "stddev": 0,
            "min": 4,
            "p10": 4,
            "p90": 4,
            "p99": 4,
            "max": 4
          }
        },
        "asyncAppConstants": {
          "MOZ_UNSIGNED_SCOPES": {
            "median": 0,
            "mean": 0,
            "mdev": 0,
            "stddev": 0,
            "min": 0,
            "p10": 0,
            "p90": 0,
            "p99": 0,
            "max": 0
          },
          "TELEMETRY_PING_FORMAT_VERSION": {
            "median": 4,
            "mean": 4,
            "mdev": 0,
            "stddev": 0,
            "min": 4,
            "p10": 4,
            "p90": 4,
            "p99": 4,
            "max": 4
          }
        }
      },
      "pageinfo": {
        "documentHeight": {
          "median": 612,
          "mean": 612,
          "mdev": 0,
          "stddev": 0,
          "min": 612,
          "p10": 612,
          "p90": 612,
          "p99": 612,
          "max": 612
        },
        "documentSize": {
          "decodedBodySize": {
            "median": 83360,
            "mean": 83640,
            "mdev": 273.0389,
            "stddev": 473,
            "min": 83254,
            "p10": 83254,
            "p90": 84306,
            "p99": 84306,
            "max": 84306
          },
          "encodedBodySize": {
            "median": 28275,
            "mean": 28338,
            "mdev": 82.8618,
            "stddev": 144,
            "min": 28203,
            "p10": 28203,
            "p90": 28537,
            "p99": 28537,
            "max": 28537
          },
          "transferSize": {
            "median": 30272,
            "mean": 30336,
            "mdev": 83.1282,
            "stddev": 144,
            "min": 30200,
            "p10": 30200,
            "p90": 30535,
            "p99": 30535,
            "max": 30535
          }
        },
        "documentWidth": {
          "median": 360,
          "mean": 360,
          "mdev": 0,
          "stddev": 0,
          "min": 360,
          "p10": 360,
          "p90": 360,
          "p99": 360,
          "max": 360
        },
        "domElements": {
          "median": 857,
          "mean": 857,
          "mdev": 0,
          "stddev": 0,
          "min": 857,
          "p10": 857,
          "p90": 857,
          "p99": 857,
          "max": 857
        },
        "navigationStartTime": {
          "median": 1620322457408,
          "mean": 1620322457401,
          "mdev": 12612.4091,
          "stddev": 21845,
          "min": 1620322438476,
          "p10": 1620322438476,
          "p90": 1620322476320,
          "p99": 1620322476320,
          "max": 1620322476320
        },
        "resources": {
          "count": {
            "median": 0,
            "mean": 0,
            "mdev": 0,
            "stddev": 0,
            "min": 0,
            "p10": 0,
            "p90": 0,
            "p99": 0,
            "max": 0
          },
          "duration": {
            "median": 0,
            "mean": 0,
            "mdev": 0,
            "stddev": 0,
            "min": 0,
            "p10": 0,
            "p90": 0,
            "p99": 0,
            "max": 0
          }
        },
        "visualElements": {
          "heroes": [
            {
              "height": {
                "median": 60,
                "mean": 60,
                "mdev": 0,
                "stddev": 0,
                "min": 60,
                "p10": 60,
                "p90": 60,
                "p99": 60,
                "max": 60
              },
              "width": {
                "median": 328,
                "mean": 328,
                "mdev": 0,
                "stddev": 0,
                "min": 328,
                "p10": 328,
                "p90": 328,
                "p99": 328,
                "max": 328
              },
              "x": {
                "median": 16,
                "mean": 16,
                "mdev": 0,
                "stddev": 0,
                "min": 16,
                "p10": 16,
                "p90": 16,
                "p99": 16,
                "max": 16
              },
              "y": {
                "median": 32,
                "mean": 32,
                "mdev": 0,
                "stddev": 0,
                "min": 32,
                "p10": 32,
                "p90": 32,
                "p99": 32,
                "max": 32
              }
            }
          ],
          "viewport": {
            "height": {
              "median": 612,
              "mean": 612,
              "mdev": 0,
              "stddev": 0,
              "min": 612,
              "p10": 612,
              "p90": 612,
              "p99": 612,
              "max": 612
            },
            "width": {
              "median": 360,
              "mean": 360,
              "mdev": 0,
              "stddev": 0,
              "min": 360,
              "p10": 360,
              "p90": 360,
              "p99": 360,
              "max": 360
            }
          }
        }
      },
      "timings": {
        "firstPaint": {
          "median": 2094,
          "mean": 2042,
          "mdev": 43.549,
          "stddev": 75,
          "min": 1935,
          "p10": 1935,
          "p90": 2096,
          "p99": 2096,
          "max": 2096
        },
        "loadEventEnd": {
          "median": 5282,
          "mean": 5278,
          "mdev": 212.1383,
          "stddev": 367,
          "min": 4826,
          "p10": 4826,
          "p90": 5726,
          "p99": 5726,
          "max": 5726
        },
        "navigationTiming": {
          "connectStart": {
            "median": 717,
            "mean": 709,
            "mdev": 11.1389,
            "stddev": 19,
            "min": 682,
            "p10": 682,
            "p90": 727,
            "p99": 727,
            "max": 727
          },
          "domComplete": {
            "median": 5273,
            "mean": 5268,
            "mdev": 211.1978,
            "stddev": 366,
            "min": 4818,
            "p10": 4818,
            "p90": 5714,
            "p99": 5714,
            "max": 5714
          },
          "domContentLoadedEventEnd": {
            "median": 2223,
            "mean": 2167,
            "mdev": 46.5427,
            "stddev": 81,
            "min": 2053,
            "p10": 2053,
            "p90": 2225,
            "p99": 2225,
            "max": 2225
          },
          "domContentLoadedEventStart": {
            "median": 2216,
            "mean": 2160,
            "mdev": 46.9539,
            "stddev": 81,
            "min": 2045,
            "p10": 2045,
            "p90": 2219,
            "p99": 2219,
            "max": 2219
          },
          "domInteractive": {
            "median": 2185,
            "mean": 2141,
            "mdev": 44.0715,
            "stddev": 76,
            "min": 2034,
            "p10": 2034,
            "p90": 2205,
            "p99": 2205,
            "max": 2205
          },
          "domainLookupEnd": {
            "median": 717,
            "mean": 709,
            "mdev": 11.1389,
            "stddev": 19,
            "min": 682,
            "p10": 682,
            "p90": 727,
            "p99": 727,
            "max": 727
          },
          "domainLookupStart": {
            "median": 717,
            "mean": 709,
            "mdev": 11.1389,
            "stddev": 19,
            "min": 682,
            "p10": 682,
            "p90": 727,
            "p99": 727,
            "max": 727
          },
          "duration": {
            "median": 5282,
            "mean": 5278,
            "mdev": 212.1383,
            "stddev": 367,
            "min": 4826,
            "p10": 4826,
            "p90": 5726,
            "p99": 5726,
            "max": 5726
          },
          "fetchStart": {
            "median": 717,
            "mean": 709,
            "mdev": 11.1389,
            "stddev": 19,
            "min": 682,
            "p10": 682,
            "p90": 727,
            "p99": 727,
            "max": 727
          },
          "loadEventEnd": {
            "median": 5282,
            "mean": 5278,
            "mdev": 212.1383,
            "stddev": 367,
            "min": 4826,
            "p10": 4826,
            "p90": 5726,
            "p99": 5726,
            "max": 5726
          },
          "loadEventStart": {
            "median": 5273,
            "mean": 5268,
            "mdev": 211.1978,
            "stddev": 366,
            "min": 4818,
            "p10": 4818,
            "p90": 5714,
            "p99": 5714,
            "max": 5714
          },
          "redirectEnd": {
            "median": 703,
            "mean": 695,
            "mdev": 11.5117,
            "stddev": 20,
            "min": 668,
            "p10": 668,
            "p90": 715,
            "p99": 715,
            "max": 715
          },
          "redirectStart": {
            "median": 3,
            "mean": 3,
            "mdev": 0.2722,
            "stddev": 0,
            "min": 2,
            "p10": 2,
            "p90": 3,
            "p99": 3,
            "max": 3
          },
          "requestStart": {
            "median": 758,
            "mean": 749,
            "mdev": 11.9381,
            "stddev": 21,
            "min": 720,
            "p10": 720,
            "p90": 768,
            "p99": 768,
            "max": 768
          },
          "responseEnd": {
            "median": 1123,
            "mean": 1109,
            "mdev": 13.2525,
            "stddev": 23,
            "min": 1077,
            "p10": 1077,
            "p90": 1128,
            "p99": 1128,
            "max": 1128
          },
          "responseStart": {
            "median": 1086,
            "mean": 1083,
            "mdev": 2.4495,
            "stddev": 4,
            "min": 1077,
            "p10": 1077,
            "p90": 1086,
            "p99": 1086,
            "max": 1086
          },
          "secureConnectionStart": {
            "median": 0,
            "mean": 0,
            "mdev": 0,
            "stddev": 0,
            "min": 0,
            "p10": 0,
            "p90": 0,
            "p99": 0,
            "max": 0
          },
          "startTime": {
            "median": 0,
            "mean": 0,
            "mdev": 0,
            "stddev": 0,
            "min": 0,
            "p10": 0,
            "p90": 0,
            "p99": 0,
            "max": 0
          },
          "unloadEventEnd": {
            "median": 0,
            "mean": 0,
            "mdev": 0,
            "stddev": 0,
            "min": 0,
            "p10": 0,
            "p90": 0,
            "p99": 0,
            "max": 0
          },
          "unloadEventStart": {
            "median": 0,
            "mean": 0,
            "mdev": 0,
            "stddev": 0,
            "min": 0,
            "p10": 0,
            "p90": 0,
            "p99": 0,
            "max": 0
          },
          "workerStart": {
            "median": 0,
            "mean": 0,
            "mdev": 0,
            "stddev": 0,
            "min": 0,
            "p10": 0,
            "p90": 0,
            "p99": 0,
            "max": 0
          }
        },
        "pageTimings": {
          "backEndTime": {
            "median": 1086,
            "mean": 1083,
            "mdev": 2.4495,
            "stddev": 4,
            "min": 1077,
            "p10": 1077,
            "p90": 1086,
            "p99": 1086,
            "max": 1086
          },
          "domContentLoadedTime": {
            "median": 2216,
            "mean": 2160,
            "mdev": 46.9539,
            "stddev": 81,
            "min": 2045,
            "p10": 2045,
            "p90": 2219,
            "p99": 2219,
            "max": 2219
          },
          "domInteractiveTime": {
            "median": 2185,
            "mean": 2141,
            "mdev": 44.0715,
            "stddev": 76,
            "min": 2034,
            "p10": 2034,
            "p90": 2205,
            "p99": 2205,
            "max": 2205
          },
          "domainLookupTime": {
            "median": 0,
            "mean": 0,
            "mdev": 0,
            "stddev": 0,
            "min": 0,
            "p10": 0,
            "p90": 0,
            "p99": 0,
            "max": 0
          },
          "frontEndTime": {
            "median": 4150,
            "mean": 4159,
            "mdev": 223.4738,
            "stddev": 387,
            "min": 3689,
            "p10": 3689,
            "p90": 4637,
            "p99": 4637,
            "max": 4637
          },
          "pageDownloadTime": {
            "median": 37,
            "mean": 26,
            "mdev": 10.8149,
            "stddev": 19,
            "min": 0,
            "p10": 0,
            "p90": 42,
            "p99": 42,
            "max": 42
          },
          "pageLoadTime": {
            "median": 5273,
            "mean": 5268,
            "mdev": 211.1978,
            "stddev": 366,
            "min": 4818,
            "p10": 4818,
            "p90": 5714,
            "p99": 5714,
            "max": 5714
          },
          "redirectionTime": {
            "median": 700,
            "mean": 692,
            "mdev": 11.5117,
            "stddev": 20,
            "min": 665,
            "p10": 665,
            "p90": 712,
            "p99": 712,
            "max": 712
          },
          "serverConnectionTime": {
            "median": 0,
            "mean": 0,
            "mdev": 0,
            "stddev": 0,
            "min": 0,
            "p10": 0,
            "p90": 0,
            "p99": 0,
            "max": 0
          },
          "serverResponseTime": {
            "median": 370,
            "mean": 361,
            "mdev": 22.4813,
            "stddev": 39,
            "min": 309,
            "p10": 309,
            "p90": 403,
            "p99": 403,
            "max": 403
          }
        },
        "rumSpeedIndex": {
          "median": 1085,
          "mean": 1082,
          "mdev": 2.5963,
          "stddev": 4,
          "min": 1076,
          "p10": 1076,
          "p90": 1086,
          "p99": 1086,
          "max": 1086
        },
        "timeToContentfulPaint": {
          "median": 2180,
          "mean": 2131,
          "mdev": 44.5745,
          "stddev": 77,
          "min": 2022,
          "p10": 2022,
          "p90": 2191,
          "p99": 2191,
          "max": 2191
        },
        "timeToDomContentFlushed": {
          "median": 2205,
          "mean": 2171,
          "mdev": 48.0517,
          "stddev": 83,
          "min": 2056,
          "p10": 2056,
          "p90": 2251,
          "p99": 2251,
          "max": 2251
        },
        "userTimings": {
          "marks": {
            "wf_done": {
              "median": 2669,
              "mean": 2635,
              "mdev": 37.0798,
              "stddev": 64,
              "min": 2545,
              "p10": 2545,
              "p90": 2690,
              "p99": 2690,
              "max": 2690
            },
            "wf_done_end": {
              "median": 2670,
              "mean": 2635,
              "mdev": 37.0819,
              "stddev": 64,
              "min": 2545,
              "p10": 2545,
              "p90": 2691,
              "p99": 2691,
              "max": 2691
            },
            "wf_postload_start": {
              "median": 5274,
              "mean": 5269,
              "mdev": 211.5694,
              "stddev": 366,
              "min": 4818,
              "p10": 4818,
              "p90": 5716,
              "p99": 5716,
              "max": 5716
            },
            "wf_postload_end": {
              "median": 5926,
              "mean": 5941,
              "mdev": 76.5481,
              "stddev": 133,
              "min": 5787,
              "p10": 5787,
              "p90": 6111,
              "p99": 6111,
              "max": 6111
            },
            "wf_delayed_end": {
              "median": 10323,
              "mean": 10292,
              "mdev": 211.4216,
              "stddev": 366,
              "min": 9828,
              "p10": 9828,
              "p90": 10724,
              "p99": 10724,
              "max": 10724
            }
          }
        }
      }
    }
  }
]