[
  {
    "info": {
      "browsertime": {
        "version": "8.4.0"
      },
      "url": "https://sportsmedicine.mayoclinic.org/",
      "timestamp": "2021-05-07T17:50:46+04:00",
      "connectivity": {
        "engine": "external",
        "profile": "native"
      },
      "extra": {}
    },
    "files": {
      "video": [],
      "screenshot": [],
      "timeline": [],
      "consoleLog": [],
      "netLog": [],
      "perfLog": []
    },
    "cdp": {
      "performance": []
    },
    "timestamps": [
      "2021-05-07T17:50:21+04:00",
      "2021-05-07T17:51:00+04:00",
      "2021-05-07T17:52:17+04:00"
    ],
    "browserScripts": [
      {
        "browser": {
          "appConstants": {
            "ACCESSIBILITY": true,
            "ANDROID_PACKAGE_NAME": "org.mozilla.firefox",
            "ASAN": false,
            "ASAN_REPORTER": false,
            "BROWSER_CHROME_URL": "chrome://browser/content/browser.xul",
            "DEBUG": false,
            "DEBUG_JS_MODULES": "",
            "DLL_PREFIX": "lib",
            "DLL_SUFFIX": ".so",
            "EARLY_BETA_OR_EARLIER": false,
            "FENNEC_NIGHTLY": false,
            "HAVE_SHELL_SERVICE": false,
            "HAVE_USR_LIB64_DIR": false,
            "MENUBAR_CAN_AUTOHIDE": false,
            "MOZILLA_OFFICIAL": true,
            "MOZ_ALLOW_LEGACY_EXTENSIONS": false,
            "MOZ_ANDROID_ACTIVITY_STREAM": false,
            "MOZ_ANDROID_HISTORY": true,
            "MOZ_ANDROID_MOZILLA_ONLINE": false,
            "MOZ_APP_NAME": "fennec",
            "MOZ_APP_VERSION": "68.1.1",
            "MOZ_APP_VERSION_DISPLAY": "68.1.1",
            "MOZ_BING_API_CLIENTID": "no-bing-api-clientid",
            "MOZ_BING_API_KEY": "no-bing-api-key",
            "MOZ_BITS_DOWNLOAD": false,
            "MOZ_BUILD_APP": "mobile/android",
            "MOZ_CODE_COVERAGE": false,
            "MOZ_CRASHREPORTER": true,
            "MOZ_DATA_REPORTING": true,
            "MOZ_DEV_EDITION": false,
            "MOZ_GECKO_PROFILER": true,
            "MOZ_GOOGLE_LOCATION_SERVICE_API_KEY": "AIzaSyB2h2OuRcUgy5N-5hsZqiPW6sH3n_rptiQ",
            "MOZ_GOOGLE_SAFEBROWSING_API_KEY": "AIzaSyC7jsptDS3am4tPx4r3nxis7IMjBc5Dovo",
            "MOZ_GRAPHENE": false,
            "MOZ_MACBUNDLE_NAME": "Firefox.app",
            "MOZ_MAINTENANCE_SERVICE": false,
            "MOZ_MOZILLA_API_KEY": "3b4d27dd-703d-4094-8398-4de2c763505a",
            "MOZ_NEW_CERT_STORAGE": false,
            "MOZ_NEW_NOTIFICATION_STORE": false,
            "MOZ_NEW_XULSTORE": false,
            "MOZ_OFFICIAL_BRANDING": false,
            "MOZ_PLACES": false,
            "MOZ_REQUIRE_SIGNING": false,
            "MOZ_SANDBOX": false,
            "MOZ_SERVICES_HEALTHREPORT": true,
            "MOZ_SERVICES_SYNC": false,
            "MOZ_SWITCHBOARD": true,
            "MOZ_SYSTEM_NSS": false,
            "MOZ_TELEMETRY_ON_BY_DEFAULT": false,
            "MOZ_TELEMETRY_REPORTING": true,
            "MOZ_UNSIGNED_SCOPES": 0,
            "MOZ_UPDATER": false,
            "MOZ_UPDATE_CHANNEL": "release",
            "MOZ_WEBRTC": true,
            "MOZ_WIDGET_GTK": false,
            "MOZ_WIDGET_TOOLKIT": "android",
            "NIGHTLY_BUILD": false,
            "OMNIJAR_NAME": "assets/omni.ja",
            "RELEASE_OR_BETA": true,
            "SOURCE_REVISION_URL": "https://hg.mozilla.org/releases/mozilla-esr68/rev/d2e0b9e17b9bc1ef02606c8006b73293f7892ad5",
            "TELEMETRY_PING_FORMAT_VERSION": 4,
            "XP_UNIX": true,
            "isPlatformAndVersionAtLeast": {},
            "isPlatformAndVersionAtMost": {},
            "platform": "android"
          },
          "asyncAppConstants": {
            "ACCESSIBILITY": true,
            "ANDROID_PACKAGE_NAME": "org.mozilla.firefox",
            "ASAN": false,
            "ASAN_REPORTER": false,
            "BROWSER_CHROME_URL": "chrome://browser/content/browser.xul",
            "DEBUG": false,
            "DEBUG_JS_MODULES": "",
            "DLL_PREFIX": "lib",
            "DLL_SUFFIX": ".so",
            "EARLY_BETA_OR_EARLIER": false,
            "FENNEC_NIGHTLY": false,
            "HAVE_SHELL_SERVICE": false,
            "HAVE_USR_LIB64_DIR": false,
            "MENUBAR_CAN_AUTOHIDE": false,
            "MOZILLA_OFFICIAL": true,
            "MOZ_ALLOW_LEGACY_EXTENSIONS": false,
            "MOZ_ANDROID_ACTIVITY_STREAM": false,
            "MOZ_ANDROID_HISTORY": true,
            "MOZ_ANDROID_MOZILLA_ONLINE": false,
            "MOZ_APP_NAME": "fennec",
            "MOZ_APP_VERSION": "68.1.1",
            "MOZ_APP_VERSION_DISPLAY": "68.1.1",
            "MOZ_BING_API_CLIENTID": "no-bing-api-clientid",
            "MOZ_BING_API_KEY": "no-bing-api-key",
            "MOZ_BITS_DOWNLOAD": false,
            "MOZ_BUILD_APP": "mobile/android",
            "MOZ_CODE_COVERAGE": false,
            "MOZ_CRASHREPORTER": true,
            "MOZ_DATA_REPORTING": true,
            "MOZ_DEV_EDITION": false,
            "MOZ_GECKO_PROFILER": true,
            "MOZ_GOOGLE_LOCATION_SERVICE_API_KEY": "AIzaSyB2h2OuRcUgy5N-5hsZqiPW6sH3n_rptiQ",
            "MOZ_GOOGLE_SAFEBROWSING_API_KEY": "AIzaSyC7jsptDS3am4tPx4r3nxis7IMjBc5Dovo",
            "MOZ_GRAPHENE": false,
            "MOZ_MACBUNDLE_NAME": "Firefox.app",
            "MOZ_MAINTENANCE_SERVICE": false,
            "MOZ_MOZILLA_API_KEY": "3b4d27dd-703d-4094-8398-4de2c763505a",
            "MOZ_NEW_CERT_STORAGE": false,
            "MOZ_NEW_NOTIFICATION_STORE": false,
            "MOZ_NEW_XULSTORE": false,
            "MOZ_OFFICIAL_BRANDING": false,
            "MOZ_PLACES": false,
            "MOZ_REQUIRE_SIGNING": false,
            "MOZ_SANDBOX": false,
            "MOZ_SERVICES_HEALTHREPORT": true,
            "MOZ_SERVICES_SYNC": false,
            "MOZ_SWITCHBOARD": true,
            "MOZ_SYSTEM_NSS": false,
            "MOZ_TELEMETRY_ON_BY_DEFAULT": false,
            "MOZ_TELEMETRY_REPORTING": true,
            "MOZ_UNSIGNED_SCOPES": 0,
            "MOZ_UPDATER": false,
            "MOZ_UPDATE_CHANNEL": "release",
            "MOZ_WEBRTC": true,
            "MOZ_WIDGET_GTK": false,
            "MOZ_WIDGET_TOOLKIT": "android",
            "NIGHTLY_BUILD": false,
            "OMNIJAR_NAME": "assets/omni.ja",
            "RELEASE_OR_BETA": true,
            "SOURCE_REVISION_URL": "https://hg.mozilla.org/releases/mozilla-esr68/rev/d2e0b9e17b9bc1ef02606c8006b73293f7892ad5",
            "TELEMETRY_PING_FORMAT_VERSION": 4,
            "XP_UNIX": true,
            "isPlatformAndVersionAtLeast": {},
            "isPlatformAndVersionAtMost": {},
            "platform": "android"
          },
          "userAgent": "Mozilla/5.0 (Android 8.1.0; Mobile; rv:68.0) Gecko/68.0 Firefox/68.0",
          "windowSize": "360x560"
        },
        "pageinfo": {
          "documentHeight": 4116,
          "documentSize": {
            "decodedBodySize": 30516,
            "encodedBodySize": 6954,
            "transferSize": 7428
          },
          "documentTitle": "Mayo Clinic Orthopedics and Sports Medicine",
          "documentWidth": 3237,
          "domElements": 390,
          "navigationStartTime": 1620395460396,
          "nextHopProtocol": "h2",
          "resources": {
            "count": 0,
            "duration": 0
          },
          "responsive": true,
          "url": "https://sportsmedicine.mayoclinic.org/",
          "visualElements": {
            "heroes": [],
            "viewport": {
              "height": 560,
              "width": 360
            }
          }
        },
        "timings": {
          "firstPaint": 5781,
          "loadEventEnd": 12004,
          "navigationTiming": {
            "connectStart": 143,
            "domComplete": 11785,
            "domContentLoadedEventEnd": 6752,
            "domContentLoadedEventStart": 6679,
            "domInteractive": 6424,
            "domainLookupEnd": 143,
            "domainLookupStart": 142,
            "duration": 12004,
            "fetchStart": 3,
            "loadEventEnd": 12004,
            "loadEventStart": 11786,
            "redirectEnd": 0,
            "redirectStart": 0,
            "requestStart": 651,
            "responseEnd": 988,
            "responseStart": 988,
            "secureConnectionStart": 339,
            "startTime": 0,
            "unloadEventEnd": 0,
            "unloadEventStart": 0,
            "workerStart": 0
          },
          "pageTimings": {
            "backEndTime": 988,
            "domContentLoadedTime": 6679,
            "domInteractiveTime": 6424,
            "domainLookupTime": 0,
            "frontEndTime": 10798,
            "pageDownloadTime": 0,
            "pageLoadTime": 11786,
            "redirectionTime": 0,
            "serverConnectionTime": 507,
            "serverResponseTime": 337
          },
          "rumSpeedIndex": 987,
          "timeToContentfulPaint": 6310,
          "timeToDomContentFlushed": 6609,
          "userTimings": {
            "marks": [],
            "measures": []
          }
        }
      },
      {
        "browser": {
          "appConstants": {
            "ACCESSIBILITY": true,
            "ANDROID_PACKAGE_NAME": "org.mozilla.firefox",
            "ASAN": false,
            "ASAN_REPORTER": false,
            "BROWSER_CHROME_URL": "chrome://browser/content/browser.xul",
            "DEBUG": false,
            "DEBUG_JS_MODULES": "",
            "DLL_PREFIX": "lib",
            "DLL_SUFFIX": ".so",
            "EARLY_BETA_OR_EARLIER": false,
            "FENNEC_NIGHTLY": false,
            "HAVE_SHELL_SERVICE": false,
            "HAVE_USR_LIB64_DIR": false,
            "MENUBAR_CAN_AUTOHIDE": false,
            "MOZILLA_OFFICIAL": true,
            "MOZ_ALLOW_LEGACY_EXTENSIONS": false,
            "MOZ_ANDROID_ACTIVITY_STREAM": false,
            "MOZ_ANDROID_HISTORY": true,
            "MOZ_ANDROID_MOZILLA_ONLINE": false,
            "MOZ_APP_NAME": "fennec",
            "MOZ_APP_VERSION": "68.1.1",
            "MOZ_APP_VERSION_DISPLAY": "68.1.1",
            "MOZ_BING_API_CLIENTID": "no-bing-api-clientid",
            "MOZ_BING_API_KEY": "no-bing-api-key",
            "MOZ_BITS_DOWNLOAD": false,
            "MOZ_BUILD_APP": "mobile/android",
            "MOZ_CODE_COVERAGE": false,
            "MOZ_CRASHREPORTER": true,
            "MOZ_DATA_REPORTING": true,
            "MOZ_DEV_EDITION": false,
            "MOZ_GECKO_PROFILER": true,
            "MOZ_GOOGLE_LOCATION_SERVICE_API_KEY": "AIzaSyB2h2OuRcUgy5N-5hsZqiPW6sH3n_rptiQ",
            "MOZ_GOOGLE_SAFEBROWSING_API_KEY": "AIzaSyC7jsptDS3am4tPx4r3nxis7IMjBc5Dovo",
            "MOZ_GRAPHENE": false,
            "MOZ_MACBUNDLE_NAME": "Firefox.app",
            "MOZ_MAINTENANCE_SERVICE": false,
            "MOZ_MOZILLA_API_KEY": "3b4d27dd-703d-4094-8398-4de2c763505a",
            "MOZ_NEW_CERT_STORAGE": false,
            "MOZ_NEW_NOTIFICATION_STORE": false,
            "MOZ_NEW_XULSTORE": false,
            "MOZ_OFFICIAL_BRANDING": false,
            "MOZ_PLACES": false,
            "MOZ_REQUIRE_SIGNING": false,
            "MOZ_SANDBOX": false,
            "MOZ_SERVICES_HEALTHREPORT": true,
            "MOZ_SERVICES_SYNC": false,
            "MOZ_SWITCHBOARD": true,
            "MOZ_SYSTEM_NSS": false,
            "MOZ_TELEMETRY_ON_BY_DEFAULT": false,
            "MOZ_TELEMETRY_REPORTING": true,
            "MOZ_UNSIGNED_SCOPES": 0,
            "MOZ_UPDATER": false,
            "MOZ_UPDATE_CHANNEL": "release",
            "MOZ_WEBRTC": true,
            "MOZ_WIDGET_GTK": false,
            "MOZ_WIDGET_TOOLKIT": "android",
            "NIGHTLY_BUILD": false,
            "OMNIJAR_NAME": "assets/omni.ja",
            "RELEASE_OR_BETA": true,
            "SOURCE_REVISION_URL": "https://hg.mozilla.org/releases/mozilla-esr68/rev/d2e0b9e17b9bc1ef02606c8006b73293f7892ad5",
            "TELEMETRY_PING_FORMAT_VERSION": 4,
            "XP_UNIX": true,
            "isPlatformAndVersionAtLeast": {},
            "isPlatformAndVersionAtMost": {},
            "platform": "android"
          },
          "asyncAppConstants": {
            "ACCESSIBILITY": true,
            "ANDROID_PACKAGE_NAME": "org.mozilla.firefox",
            "ASAN": false,
            "ASAN_REPORTER": false,
            "BROWSER_CHROME_URL": "chrome://browser/content/browser.xul",
            "DEBUG": false,
            "DEBUG_JS_MODULES": "",
            "DLL_PREFIX": "lib",
            "DLL_SUFFIX": ".so",
            "EARLY_BETA_OR_EARLIER": false,
            "FENNEC_NIGHTLY": false,
            "HAVE_SHELL_SERVICE": false,
            "HAVE_USR_LIB64_DIR": false,
            "MENUBAR_CAN_AUTOHIDE": false,
            "MOZILLA_OFFICIAL": true,
            "MOZ_ALLOW_LEGACY_EXTENSIONS": false,
            "MOZ_ANDROID_ACTIVITY_STREAM": false,
            "MOZ_ANDROID_HISTORY": true,
            "MOZ_ANDROID_MOZILLA_ONLINE": false,
            "MOZ_APP_NAME": "fennec",
            "MOZ_APP_VERSION": "68.1.1",
            "MOZ_APP_VERSION_DISPLAY": "68.1.1",
            "MOZ_BING_API_CLIENTID": "no-bing-api-clientid",
            "MOZ_BING_API_KEY": "no-bing-api-key",
            "MOZ_BITS_DOWNLOAD": false,
            "MOZ_BUILD_APP": "mobile/android",
            "MOZ_CODE_COVERAGE": false,
            "MOZ_CRASHREPORTER": true,
            "MOZ_DATA_REPORTING": true,
            "MOZ_DEV_EDITION": false,
            "MOZ_GECKO_PROFILER": true,
            "MOZ_GOOGLE_LOCATION_SERVICE_API_KEY": "AIzaSyB2h2OuRcUgy5N-5hsZqiPW6sH3n_rptiQ",
            "MOZ_GOOGLE_SAFEBROWSING_API_KEY": "AIzaSyC7jsptDS3am4tPx4r3nxis7IMjBc5Dovo",
            "MOZ_GRAPHENE": false,
            "MOZ_MACBUNDLE_NAME": "Firefox.app",
            "MOZ_MAINTENANCE_SERVICE": false,
            "MOZ_MOZILLA_API_KEY": "3b4d27dd-703d-4094-8398-4de2c763505a",
            "MOZ_NEW_CERT_STORAGE": false,
            "MOZ_NEW_NOTIFICATION_STORE": false,
            "MOZ_NEW_XULSTORE": false,
            "MOZ_OFFICIAL_BRANDING": false,
            "MOZ_PLACES": false,
            "MOZ_REQUIRE_SIGNING": false,
            "MOZ_SANDBOX": false,
            "MOZ_SERVICES_HEALTHREPORT": true,
            "MOZ_SERVICES_SYNC": false,
            "MOZ_SWITCHBOARD": true,
            "MOZ_SYSTEM_NSS": false,
            "MOZ_TELEMETRY_ON_BY_DEFAULT": false,
            "MOZ_TELEMETRY_REPORTING": true,
            "MOZ_UNSIGNED_SCOPES": 0,
            "MOZ_UPDATER": false,
            "MOZ_UPDATE_CHANNEL": "release",
            "MOZ_WEBRTC": true,
            "MOZ_WIDGET_GTK": false,
            "MOZ_WIDGET_TOOLKIT": "android",
            "NIGHTLY_BUILD": false,
            "OMNIJAR_NAME": "assets/omni.ja",
            "RELEASE_OR_BETA": true,
            "SOURCE_REVISION_URL": "https://hg.mozilla.org/releases/mozilla-esr68/rev/d2e0b9e17b9bc1ef02606c8006b73293f7892ad5",
            "TELEMETRY_PING_FORMAT_VERSION": 4,
            "XP_UNIX": true,
            "isPlatformAndVersionAtLeast": {},
            "isPlatformAndVersionAtMost": {},
            "platform": "android"
          },
          "userAgent": "Mozilla/5.0 (Android 8.1.0; Mobile; rv:68.0) Gecko/68.0 Firefox/68.0",
          "windowSize": "360x560"
        },
        "pageinfo": {
          "documentHeight": 4116,
          "documentSize": {
            "decodedBodySize": 30516,
            "encodedBodySize": 6954,
            "transferSize": 7428
          },
          "documentTitle": "Mayo Clinic Orthopedics and Sports Medicine",
          "documentWidth": 3237,
          "domElements": 390,
          "navigationStartTime": 1620395537980,
          "nextHopProtocol": "h2",
          "resources": {
            "count": 0,
            "duration": 0
          },
          "responsive": true,
          "url": "https://sportsmedicine.mayoclinic.org/",
          "visualElements": {
            "heroes": [],
            "viewport": {
              "height": 560,
              "width": 360
            }
          }
        },
        "timings": {
          "firstPaint": 7057,
          "loadEventEnd": 26748,
          "navigationTiming": {
            "connectStart": 126,
            "domComplete": 25677,
            "domContentLoadedEventEnd": 7822,
            "domContentLoadedEventStart": 7743,
            "domInteractive": 7635,
            "domainLookupEnd": 126,
            "domainLookupStart": 126,
            "duration": 26748,
            "fetchStart": 3,
            "loadEventEnd": 26748,
            "loadEventStart": 25677,
            "redirectEnd": 0,
            "redirectStart": 0,
            "requestStart": 603,
            "responseEnd": 933,
            "responseStart": 932,
            "secureConnectionStart": 334,
            "startTime": 0,
            "unloadEventEnd": 0,
            "unloadEventStart": 0,
            "workerStart": 0
          },
          "pageTimings": {
            "backEndTime": 932,
            "domContentLoadedTime": 7743,
            "domInteractiveTime": 7635,
            "domainLookupTime": 0,
            "frontEndTime": 24745,
            "pageDownloadTime": 0,
            "pageLoadTime": 25677,
            "redirectionTime": 0,
            "serverConnectionTime": 476,
            "serverResponseTime": 329
          },
          "rumSpeedIndex": 932,
          "timeToContentfulPaint": 7579,
          "timeToDomContentFlushed": 7943,
          "userTimings": {
            "marks": [],
            "measures": []
          }
        }
      }
    ],
    "visualMetrics": [],
    "cpu": [],
    "extras": [
      {},
      {},
      {}
    ],
    "fullyLoaded": [],
    "errors": [
      [
        "UrlLoadError",
        "Failed to load https://sportsmedicine.mayoclinic.org/"
      ],
      [],
      []
    ],
    "statistics": {
      "browser": {
        "appConstants": {
          "MOZ_UNSIGNED_SCOPES": {
            "median": 0,
            "mean": 0,
            "mdev": 0,
            "stddev": 0,
            "min": 0,
            "p10": 0,
            "p90": 0,
            "p99": 0,
            "max": 0
          },
          "TELEMETRY_PING_FORMAT_VERSION": {
            "median": 4,
            "mean": 4,
            "mdev": 0,
            "stddev": 0,
            "min": 4,
            "p10": 4,
            "p90": 4,
            "p99": 4,
            "max": 4
          }
        },
        "asyncAppConstants": {
          "MOZ_UNSIGNED_SCOPES": {
            "median": 0,
            "mean": 0,
            "mdev": 0,
            "stddev": 0,
            "min": 0,
            "p10": 0,
            "p90": 0,
            "p99": 0,
            "max": 0
          },
          "TELEMETRY_PING_FORMAT_VERSION": {
            "median": 4,
            "mean": 4,
            "mdev": 0,
            "stddev": 0,
            "min": 4,
            "p10": 4,
            "p90": 4,
            "p99": 4,
            "max": 4
          }
        }
      },
      "pageinfo": {
        "documentHeight": {
          "median": 4116,
          "mean": 4116,
          "mdev": 0,
          "stddev": 0,
          "min": 4116,
          "p10": 4116,
          "p90": 4116,
          "p99": 4116,
          "max": 4116
        },
        "documentSize": {
          "decodedBodySize": {
            "median": 30516,
            "mean": 30516,
            "mdev": 0,
            "stddev": 0,
            "min": 30516,
            "p10": 30516,
            "p90": 30516,
            "p99": 30516,
            "max": 30516
          },
          "encodedBodySize": {
            "median": 6954,
            "mean": 6954,
            "mdev": 0,
            "stddev": 0,
            "min": 6954,
            "p10": 6954,
            "p90": 6954,
            "p99": 6954,
            "max": 6954
          },
          "transferSize": {
            "median": 7428,
            "mean": 7428,
            "mdev": 0,
            "stddev": 0,
            "min": 7428,
            "p10": 7428,
            "p90": 7428,
            "p99": 7428,
            "max": 7428
          }
        },
        "documentWidth": {
          "median": 3237,
          "mean": 3237,
          "mdev": 0,
          "stddev": 0,
          "min": 3237,
          "p10": 3237,
          "p90": 3237,
          "p99": 3237,
          "max": 3237
        },
        "domElements": {
          "median": 390,
          "mean": 390,
          "mdev": 0,
          "stddev": 0,
          "min": 390,
          "p10": 390,
          "p90": 390,
          "p99": 390,
          "max": 390
        },
        "navigationStartTime": {
          "median": 1620395499188,
          "mean": 1620395499188,
          "mdev": 28377.9204,
          "stddev": 40132,
          "min": 1620395460396,
          "p10": 1620395460396,
          "p90": 1620395537980,
          "p99": 1620395537980,
          "max": 1620395537980
        },
        "resources": {
          "count": {
            "median": 0,
            "mean": 0,
            "mdev": 0,
            "stddev": 0,
            "min": 0,
            "p10": 0,
            "p90": 0,
            "p99": 0,
            "max": 0
          },
          "duration": {
            "median": 0,
            "mean": 0,
            "mdev": 0,
            "stddev": 0,
            "min": 0,
            "p10": 0,
            "p90": 0,
            "p99": 0,
            "max": 0
          }
        },
        "visualElements": {
          "viewport": {
            "height": {
              "median": 560,
              "mean": 560,
              "mdev": 0,
              "stddev": 0,
              "min": 560,
              "p10": 560,
              "p90": 560,
              "p99": 560,
              "max": 560
            },
            "width": {
              "median": 360,
              "mean": 360,
              "mdev": 0,
              "stddev": 0,
              "min": 360,
              "p10": 360,
              "p90": 360,
              "p99": 360,
              "max": 360
            }
          }
        }
      },
      "timings": {
        "firstPaint": {
          "median": 6419,
          "mean": 6419,
          "mdev": 451.1341,
          "stddev": 638,
          "min": 5781,
          "p10": 5781,
          "p90": 7057,
          "p99": 7057,
          "max": 7057
        },
        "loadEventEnd": {
          "median": 19376,
          "mean": 19376,
          "mdev": 5212.7912,
          "stddev": 7372,
          "min": 12004,
          "p10": 12004,
          "p90": 26748,
          "p99": 26748,
          "max": 26748
        },
        "navigationTiming": {
          "connectStart": {
            "median": 135,
            "mean": 135,
            "mdev": 6.0104,
            "stddev": 9,
            "min": 126,
            "p10": 126,
            "p90": 143,
            "p99": 143,
            "max": 143
          },
          "domComplete": {
            "median": 18731,
            "mean": 18731,
            "mdev": 4911.5637,
            "stddev": 6946,
            "min": 11785,
            "p10": 11785,
            "p90": 25677,
            "p99": 25677,
            "max": 25677
          },
          "domContentLoadedEventEnd": {
            "median": 7287,
            "mean": 7287,
            "mdev": 378.3021,
            "stddev": 535,
            "min": 6752,
            "p10": 6752,
            "p90": 7822,
            "p99": 7822,
            "max": 7822
          },
          "domContentLoadedEventStart": {
            "median": 7211,
            "mean": 7211,
            "mdev": 376.1808,
            "stddev": 532,
            "min": 6679,
            "p10": 6679,
            "p90": 7743,
            "p99": 7743,
            "max": 7743
          },
          "domInteractive": {
            "median": 7030,
            "mean": 7030,
            "mdev": 428.1532,
            "stddev": 606,
            "min": 6424,
            "p10": 6424,
            "p90": 7635,
            "p99": 7635,
            "max": 7635
          },
          "domainLookupEnd": {
            "median": 135,
            "mean": 135,
            "mdev": 6.0104,
            "stddev": 9,
            "min": 126,
            "p10": 126,
            "p90": 143,
            "p99": 143,
            "max": 143
          },
          "domainLookupStart": {
            "median": 134,
            "mean": 134,
            "mdev": 5.6569,
            "stddev": 8,
            "min": 126,
            "p10": 126,
            "p90": 142,
            "p99": 142,
            "max": 142
          },
          "duration": {
            "median": 19376,
            "mean": 19376,
            "mdev": 5212.7912,
            "stddev": 7372,
            "min": 12004,
            "p10": 12004,
            "p90": 26748,
            "p99": 26748,
            "max": 26748
          },
          "fetchStart": {
            "median": 3,
            "mean": 3,
            "mdev": 0,
            "stddev": 0,
            "min": 3,
            "p10": 3,
            "p90": 3,
            "p99": 3,
            "max": 3
          },
          "loadEventEnd": {
            "median": 19376,
            "mean": 19376,
            "mdev": 5212.7912,
            "stddev": 7372,
            "min": 12004,
            "p10": 12004,
            "p90": 26748,
            "p99": 26748,
            "max": 26748
          },
          "loadEventStart": {
            "median": 18732,
            "mean": 18732,
            "mdev": 4911.2101,
            "stddev": 6946,
            "min": 11786,
            "p10": 11786,
            "p90": 25677,
            "p99": 25677,
            "max": 25677
          },
          "redirectEnd": {
            "median": 0,
            "mean": 0,
            "mdev": 0,
            "stddev": 0,
            "min": 0,
            "p10": 0,
            "p90": 0,
            "p99": 0,
            "max": 0
          },
          "redirectStart": {
            "median": 0,
            "mean": 0,
            "mdev": 0,
            "stddev": 0,
            "min": 0,
            "p10": 0,
            "p90": 0,
            "p99": 0,
            "max": 0
          },
          "requestStart": {
            "median": 627,
            "mean": 627,
            "mdev": 16.9706,
            "stddev": 24,
            "min": 603,
            "p10": 603,
            "p90": 651,
            "p99": 651,
            "max": 651
          },
          "responseEnd": {
            "median": 961,
            "mean": 961,
            "mdev": 19.4454,
            "stddev": 28,
            "min": 933,
            "p10": 933,
            "p90": 988,
            "p99": 988,
            "max": 988
          },
          "responseStart": {
            "median": 960,
            "mean": 960,
            "mdev": 19.799,
            "stddev": 28,
            "min": 932,
            "p10": 932,
            "p90": 988,
            "p99": 988,
            "max": 988
          },
          "secureConnectionStart": {
            "median": 337,
            "mean": 337,
            "mdev": 1.7678,
            "stddev": 3,
            "min": 334,
            "p10": 334,
            "p90": 339,
            "p99": 339,
            "max": 339
          },
          "startTime": {
            "median": 0,
            "mean": 0,
            "mdev": 0,
            "stddev": 0,
            "min": 0,
            "p10": 0,
            "p90": 0,
            "p99": 0,
            "max": 0
          },
          "unloadEventEnd": {
            "median": 0,
            "mean": 0,
            "mdev": 0,
            "stddev": 0,
            "min": 0,
            "p10": 0,
            "p90": 0,
            "p99": 0,
            "max": 0
          },
          "unloadEventStart": {
            "median": 0,
            "mean": 0,
            "mdev": 0,
            "stddev": 0,
            "min": 0,
            "p10": 0,
            "p90": 0,
            "p99": 0,
            "max": 0
          },
          "workerStart": {
            "median": 0,
            "mean": 0,
            "mdev": 0,
            "stddev": 0,
            "min": 0,
            "p10": 0,
            "p90": 0,
            "p99": 0,
            "max": 0
          }
        },
        "pageTimings": {
          "backEndTime": {
            "median": 960,
            "mean": 960,
            "mdev": 19.799,
            "stddev": 28,
            "min": 932,
            "p10": 932,
            "p90": 988,
            "p99": 988,
            "max": 988
          },
          "domContentLoadedTime": {
            "median": 7211,
            "mean": 7211,
            "mdev": 376.1808,
            "stddev": 532,
            "min": 6679,
            "p10": 6679,
            "p90": 7743,
            "p99": 7743,
            "max": 7743
          },
          "domInteractiveTime": {
            "median": 7030,
            "mean": 7030,
            "mdev": 428.1532,
            "stddev": 606,
            "min": 6424,
            "p10": 6424,
            "p90": 7635,
            "p99": 7635,
            "max": 7635
          },
          "domainLookupTime": {
            "median": 0,
            "mean": 0,
            "mdev": 0,
            "stddev": 0,
            "min": 0,
            "p10": 0,
            "p90": 0,
            "p99": 0,
            "max": 0
          },
          "frontEndTime": {
            "median": 17772,
            "mean": 17772,
            "mdev": 4931.0091,
            "stddev": 6974,
            "min": 10798,
            "p10": 10798,
            "p90": 24745,
            "p99": 24745,
            "max": 24745
          },
          "pageDownloadTime": {
            "median": 0,
            "mean": 0,
            "mdev": 0,
            "stddev": 0,
            "min": 0,
            "p10": 0,
            "p90": 0,
            "p99": 0,
            "max": 0
          },
          "pageLoadTime": {
            "median": 18732,
            "mean": 18732,
            "mdev": 4911.2101,
            "stddev": 6946,
            "min": 11786,
            "p10": 11786,
            "p90": 25677,
            "p99": 25677,
            "max": 25677
          },
          "redirectionTime": {
            "median": 0,
            "mean": 0,
            "mdev": 0,
            "stddev": 0,
            "min": 0,
            "p10": 0,
            "p90": 0,
            "p99": 0,
            "max": 0
          },
          "serverConnectionTime": {
            "median": 492,
            "mean": 492,
            "mdev": 10.9602,
            "stddev": 16,
            "min": 476,
            "p10": 476,
            "p90": 507,
            "p99": 507,
            "max": 507
          },
          "serverResponseTime": {
            "median": 333,
            "mean": 333,
            "mdev": 2.8284,
            "stddev": 4,
            "min": 329,
            "p10": 329,
            "p90": 337,
            "p99": 337,
            "max": 337
          }
        },
        "rumSpeedIndex": {
          "median": 960,
          "mean": 960,
          "mdev": 19.4454,
          "stddev": 28,
          "min": 932,
          "p10": 932,
          "p90": 987,
          "p99": 987,
          "max": 987
        },
        "timeToContentfulPaint": {
          "median": 6945,
          "mean": 6945,
          "mdev": 448.6593,
          "stddev": 635,
          "min": 6310,
          "p10": 6310,
          "p90": 7579,
          "p99": 7579,
          "max": 7579
        },
        "timeToDomContentFlushed": {
          "median": 7276,
          "mean": 7276,
          "mdev": 471.6402,
          "stddev": 667,
          "min": 6609,
          "p10": 6609,
          "p90": 7943,
          "p99": 7943,
          "max": 7943
        }
      }
    }
  },
  {
    "info": {
      "browsertime": {
        "version": "8.4.0"
      },
      "url": "https://website.com",
      "timestamp": "2021-05-07T17:52:02+04:00",
      "connectivity": {
        "engine": "external",
        "profile": "native"
      },
      "extra": {}
    },
    "files": {
      "video": [],
      "screenshot": [],
      "timeline": [],
      "consoleLog": [],
      "netLog": [],
      "perfLog": []
    },
    "cdp": {
      "performance": []
    },
    "timestamps": [
      "2021-05-07T17:51:36+04:00",
      "2021-05-07T17:52:58+04:00"
    ],
    "browserScripts": [
      {
        "browser": {
          "appConstants": {
            "ACCESSIBILITY": true,
            "ANDROID_PACKAGE_NAME": "org.mozilla.firefox",
            "ASAN": false,
            "ASAN_REPORTER": false,
            "BROWSER_CHROME_URL": "chrome://browser/content/browser.xul",
            "DEBUG": false,
            "DEBUG_JS_MODULES": "",
            "DLL_PREFIX": "lib",
            "DLL_SUFFIX": ".so",
            "EARLY_BETA_OR_EARLIER": false,
            "FENNEC_NIGHTLY": false,
            "HAVE_SHELL_SERVICE": false,
            "HAVE_USR_LIB64_DIR": false,
            "MENUBAR_CAN_AUTOHIDE": false,
            "MOZILLA_OFFICIAL": true,
            "MOZ_ALLOW_LEGACY_EXTENSIONS": false,
            "MOZ_ANDROID_ACTIVITY_STREAM": false,
            "MOZ_ANDROID_HISTORY": true,
            "MOZ_ANDROID_MOZILLA_ONLINE": false,
            "MOZ_APP_NAME": "fennec",
            "MOZ_APP_VERSION": "68.1.1",
            "MOZ_APP_VERSION_DISPLAY": "68.1.1",
            "MOZ_BING_API_CLIENTID": "no-bing-api-clientid",
            "MOZ_BING_API_KEY": "no-bing-api-key",
            "MOZ_BITS_DOWNLOAD": false,
            "MOZ_BUILD_APP": "mobile/android",
            "MOZ_CODE_COVERAGE": false,
            "MOZ_CRASHREPORTER": true,
            "MOZ_DATA_REPORTING": true,
            "MOZ_DEV_EDITION": false,
            "MOZ_GECKO_PROFILER": true,
            "MOZ_GOOGLE_LOCATION_SERVICE_API_KEY": "AIzaSyB2h2OuRcUgy5N-5hsZqiPW6sH3n_rptiQ",
            "MOZ_GOOGLE_SAFEBROWSING_API_KEY": "AIzaSyC7jsptDS3am4tPx4r3nxis7IMjBc5Dovo",
            "MOZ_GRAPHENE": false,
            "MOZ_MACBUNDLE_NAME": "Firefox.app",
            "MOZ_MAINTENANCE_SERVICE": false,
            "MOZ_MOZILLA_API_KEY": "3b4d27dd-703d-4094-8398-4de2c763505a",
            "MOZ_NEW_CERT_STORAGE": false,
            "MOZ_NEW_NOTIFICATION_STORE": false,
            "MOZ_NEW_XULSTORE": false,
            "MOZ_OFFICIAL_BRANDING": false,
            "MOZ_PLACES": false,
            "MOZ_REQUIRE_SIGNING": false,
            "MOZ_SANDBOX": false,
            "MOZ_SERVICES_HEALTHREPORT": true,
            "MOZ_SERVICES_SYNC": false,
            "MOZ_SWITCHBOARD": true,
            "MOZ_SYSTEM_NSS": false,
            "MOZ_TELEMETRY_ON_BY_DEFAULT": false,
            "MOZ_TELEMETRY_REPORTING": true,
            "MOZ_UNSIGNED_SCOPES": 0,
            "MOZ_UPDATER": false,
            "MOZ_UPDATE_CHANNEL": "release",
            "MOZ_WEBRTC": true,
            "MOZ_WIDGET_GTK": false,
            "MOZ_WIDGET_TOOLKIT": "android",
            "NIGHTLY_BUILD": false,
            "OMNIJAR_NAME": "assets/omni.ja",
            "RELEASE_OR_BETA": true,
            "SOURCE_REVISION_URL": "https://hg.mozilla.org/releases/mozilla-esr68/rev/d2e0b9e17b9bc1ef02606c8006b73293f7892ad5",
            "TELEMETRY_PING_FORMAT_VERSION": 4,
            "XP_UNIX": true,
            "isPlatformAndVersionAtLeast": {},
            "isPlatformAndVersionAtMost": {},
            "platform": "android"
          },
          "asyncAppConstants": {
            "ACCESSIBILITY": true,
            "ANDROID_PACKAGE_NAME": "org.mozilla.firefox",
            "ASAN": false,
            "ASAN_REPORTER": false,
            "BROWSER_CHROME_URL": "chrome://browser/content/browser.xul",
            "DEBUG": false,
            "DEBUG_JS_MODULES": "",
            "DLL_PREFIX": "lib",
            "DLL_SUFFIX": ".so",
            "EARLY_BETA_OR_EARLIER": false,
            "FENNEC_NIGHTLY": false,
            "HAVE_SHELL_SERVICE": false,
            "HAVE_USR_LIB64_DIR": false,
            "MENUBAR_CAN_AUTOHIDE": false,
            "MOZILLA_OFFICIAL": true,
            "MOZ_ALLOW_LEGACY_EXTENSIONS": false,
            "MOZ_ANDROID_ACTIVITY_STREAM": false,
            "MOZ_ANDROID_HISTORY": true,
            "MOZ_ANDROID_MOZILLA_ONLINE": false,
            "MOZ_APP_NAME": "fennec",
            "MOZ_APP_VERSION": "68.1.1",
            "MOZ_APP_VERSION_DISPLAY": "68.1.1",
            "MOZ_BING_API_CLIENTID": "no-bing-api-clientid",
            "MOZ_BING_API_KEY": "no-bing-api-key",
            "MOZ_BITS_DOWNLOAD": false,
            "MOZ_BUILD_APP": "mobile/android",
            "MOZ_CODE_COVERAGE": false,
            "MOZ_CRASHREPORTER": true,
            "MOZ_DATA_REPORTING": true,
            "MOZ_DEV_EDITION": false,
            "MOZ_GECKO_PROFILER": true,
            "MOZ_GOOGLE_LOCATION_SERVICE_API_KEY": "AIzaSyB2h2OuRcUgy5N-5hsZqiPW6sH3n_rptiQ",
            "MOZ_GOOGLE_SAFEBROWSING_API_KEY": "AIzaSyC7jsptDS3am4tPx4r3nxis7IMjBc5Dovo",
            "MOZ_GRAPHENE": false,
            "MOZ_MACBUNDLE_NAME": "Firefox.app",
            "MOZ_MAINTENANCE_SERVICE": false,
            "MOZ_MOZILLA_API_KEY": "3b4d27dd-703d-4094-8398-4de2c763505a",
            "MOZ_NEW_CERT_STORAGE": false,
            "MOZ_NEW_NOTIFICATION_STORE": false,
            "MOZ_NEW_XULSTORE": false,
            "MOZ_OFFICIAL_BRANDING": false,
            "MOZ_PLACES": false,
            "MOZ_REQUIRE_SIGNING": false,
            "MOZ_SANDBOX": false,
            "MOZ_SERVICES_HEALTHREPORT": true,
            "MOZ_SERVICES_SYNC": false,
            "MOZ_SWITCHBOARD": true,
            "MOZ_SYSTEM_NSS": false,
            "MOZ_TELEMETRY_ON_BY_DEFAULT": false,
            "MOZ_TELEMETRY_REPORTING": true,
            "MOZ_UNSIGNED_SCOPES": 0,
            "MOZ_UPDATER": false,
            "MOZ_UPDATE_CHANNEL": "release",
            "MOZ_WEBRTC": true,
            "MOZ_WIDGET_GTK": false,
            "MOZ_WIDGET_TOOLKIT": "android",
            "NIGHTLY_BUILD": false,
            "OMNIJAR_NAME": "assets/omni.ja",
            "RELEASE_OR_BETA": true,
            "SOURCE_REVISION_URL": "https://hg.mozilla.org/releases/mozilla-esr68/rev/d2e0b9e17b9bc1ef02606c8006b73293f7892ad5",
            "TELEMETRY_PING_FORMAT_VERSION": 4,
            "XP_UNIX": true,
            "isPlatformAndVersionAtLeast": {},
            "isPlatformAndVersionAtMost": {},
            "platform": "android"
          },
          "userAgent": "Mozilla/5.0 (Android 8.1.0; Mobile; rv:68.0) Gecko/68.0 Firefox/68.0",
          "windowSize": "360x560"
        },
        "pageinfo": {
          "documentHeight": 12689,
          "documentSize": {
            "decodedBodySize": 170270,
            "encodedBodySize": 28007,
            "transferSize": 28882
          },
          "documentTitle": "Create Your Free Website | Free Website Builder | Website.com",
          "documentWidth": 360,
          "domElements": 955,
          "navigationStartTime": 1620395496897,
          "nextHopProtocol": "h2",
          "resources": {
            "count": 0,
            "duration": 0
          },
          "responsive": true,
          "url": "https://www.website.com/",
          "visualElements": {
            "heroes": [
              {
                "filename": null,
                "height": 208,
                "name": "Heading",
                "width": 324,
                "x": 18,
                "y": 132
              }
            ],
            "viewport": {
              "height": 560,
              "width": 360
            }
          }
        },
        "timings": {
          "firstPaint": 4459,
          "loadEventEnd": 6389,
          "navigationTiming": {
            "connectStart": 1854,
            "domComplete": 6379,
            "domContentLoadedEventEnd": 6329,
            "domContentLoadedEventStart": 6230,
            "domInteractive": 6191,
            "domainLookupEnd": 1853,
            "domainLookupStart": 1853,
            "duration": 6389,
            "fetchStart": 1626,
            "loadEventEnd": 6389,
            "loadEventStart": 6379,
            "redirectEnd": 1586,
            "redirectStart": 11,
            "requestStart": 1866,
            "responseEnd": 3903,
            "responseStart": 3877,
            "secureConnectionStart": 0,
            "startTime": 0,
            "unloadEventEnd": 0,
            "unloadEventStart": 0,
            "workerStart": 0
          },
          "pageTimings": {
            "backEndTime": 3877,
            "domContentLoadedTime": 6230,
            "domInteractiveTime": 6191,
            "domainLookupTime": 0,
            "frontEndTime": 2476,
            "pageDownloadTime": 27,
            "pageLoadTime": 6379,
            "redirectionTime": 1575,
            "serverConnectionTime": 0,
            "serverResponseTime": 2037
          },
          "rumSpeedIndex": 3876,
          "timeToContentfulPaint": 4589,
          "timeToDomContentFlushed": 6203,
          "userTimings": {
            "marks": [],
            "measures": []
          }
        }
      },
      {
        "browser": {
          "appConstants": {
            "ACCESSIBILITY": true,
            "ANDROID_PACKAGE_NAME": "org.mozilla.firefox",
            "ASAN": false,
            "ASAN_REPORTER": false,
            "BROWSER_CHROME_URL": "chrome://browser/content/browser.xul",
            "DEBUG": false,
            "DEBUG_JS_MODULES": "",
            "DLL_PREFIX": "lib",
            "DLL_SUFFIX": ".so",
            "EARLY_BETA_OR_EARLIER": false,
            "FENNEC_NIGHTLY": false,
            "HAVE_SHELL_SERVICE": false,
            "HAVE_USR_LIB64_DIR": false,
            "MENUBAR_CAN_AUTOHIDE": false,
            "MOZILLA_OFFICIAL": true,
            "MOZ_ALLOW_LEGACY_EXTENSIONS": false,
            "MOZ_ANDROID_ACTIVITY_STREAM": false,
            "MOZ_ANDROID_HISTORY": true,
            "MOZ_ANDROID_MOZILLA_ONLINE": false,
            "MOZ_APP_NAME": "fennec",
            "MOZ_APP_VERSION": "68.1.1",
            "MOZ_APP_VERSION_DISPLAY": "68.1.1",
            "MOZ_BING_API_CLIENTID": "no-bing-api-clientid",
            "MOZ_BING_API_KEY": "no-bing-api-key",
            "MOZ_BITS_DOWNLOAD": false,
            "MOZ_BUILD_APP": "mobile/android",
            "MOZ_CODE_COVERAGE": false,
            "MOZ_CRASHREPORTER": true,
            "MOZ_DATA_REPORTING": true,
            "MOZ_DEV_EDITION": false,
            "MOZ_GECKO_PROFILER": true,
            "MOZ_GOOGLE_LOCATION_SERVICE_API_KEY": "AIzaSyB2h2OuRcUgy5N-5hsZqiPW6sH3n_rptiQ",
            "MOZ_GOOGLE_SAFEBROWSING_API_KEY": "AIzaSyC7jsptDS3am4tPx4r3nxis7IMjBc5Dovo",
            "MOZ_GRAPHENE": false,
            "MOZ_MACBUNDLE_NAME": "Firefox.app",
            "MOZ_MAINTENANCE_SERVICE": false,
            "MOZ_MOZILLA_API_KEY": "3b4d27dd-703d-4094-8398-4de2c763505a",
            "MOZ_NEW_CERT_STORAGE": false,
            "MOZ_NEW_NOTIFICATION_STORE": false,
            "MOZ_NEW_XULSTORE": false,
            "MOZ_OFFICIAL_BRANDING": false,
            "MOZ_PLACES": false,
            "MOZ_REQUIRE_SIGNING": false,
            "MOZ_SANDBOX": false,
            "MOZ_SERVICES_HEALTHREPORT": true,
            "MOZ_SERVICES_SYNC": false,
            "MOZ_SWITCHBOARD": true,
            "MOZ_SYSTEM_NSS": false,
            "MOZ_TELEMETRY_ON_BY_DEFAULT": false,
            "MOZ_TELEMETRY_REPORTING": true,
            "MOZ_UNSIGNED_SCOPES": 0,
            "MOZ_UPDATER": false,
            "MOZ_UPDATE_CHANNEL": "release",
            "MOZ_WEBRTC": true,
            "MOZ_WIDGET_GTK": false,
            "MOZ_WIDGET_TOOLKIT": "android",
            "NIGHTLY_BUILD": false,
            "OMNIJAR_NAME": "assets/omni.ja",
            "RELEASE_OR_BETA": true,
            "SOURCE_REVISION_URL": "https://hg.mozilla.org/releases/mozilla-esr68/rev/d2e0b9e17b9bc1ef02606c8006b73293f7892ad5",
            "TELEMETRY_PING_FORMAT_VERSION": 4,
            "XP_UNIX": true,
            "isPlatformAndVersionAtLeast": {},
            "isPlatformAndVersionAtMost": {},
            "platform": "android"
          },
          "asyncAppConstants": {
            "ACCESSIBILITY": true,
            "ANDROID_PACKAGE_NAME": "org.mozilla.firefox",
            "ASAN": false,
            "ASAN_REPORTER": false,
            "BROWSER_CHROME_URL": "chrome://browser/content/browser.xul",
            "DEBUG": false,
            "DEBUG_JS_MODULES": "",
            "DLL_PREFIX": "lib",
            "DLL_SUFFIX": ".so",
            "EARLY_BETA_OR_EARLIER": false,
            "FENNEC_NIGHTLY": false,
            "HAVE_SHELL_SERVICE": false,
            "HAVE_USR_LIB64_DIR": false,
            "MENUBAR_CAN_AUTOHIDE": false,
            "MOZILLA_OFFICIAL": true,
            "MOZ_ALLOW_LEGACY_EXTENSIONS": false,
            "MOZ_ANDROID_ACTIVITY_STREAM": false,
            "MOZ_ANDROID_HISTORY": true,
            "MOZ_ANDROID_MOZILLA_ONLINE": false,
            "MOZ_APP_NAME": "fennec",
            "MOZ_APP_VERSION": "68.1.1",
            "MOZ_APP_VERSION_DISPLAY": "68.1.1",
            "MOZ_BING_API_CLIENTID": "no-bing-api-clientid",
            "MOZ_BING_API_KEY": "no-bing-api-key",
            "MOZ_BITS_DOWNLOAD": false,
            "MOZ_BUILD_APP": "mobile/android",
            "MOZ_CODE_COVERAGE": false,
            "MOZ_CRASHREPORTER": true,
            "MOZ_DATA_REPORTING": true,
            "MOZ_DEV_EDITION": false,
            "MOZ_GECKO_PROFILER": true,
            "MOZ_GOOGLE_LOCATION_SERVICE_API_KEY": "AIzaSyB2h2OuRcUgy5N-5hsZqiPW6sH3n_rptiQ",
            "MOZ_GOOGLE_SAFEBROWSING_API_KEY": "AIzaSyC7jsptDS3am4tPx4r3nxis7IMjBc5Dovo",
            "MOZ_GRAPHENE": false,
            "MOZ_MACBUNDLE_NAME": "Firefox.app",
            "MOZ_MAINTENANCE_SERVICE": false,
            "MOZ_MOZILLA_API_KEY": "3b4d27dd-703d-4094-8398-4de2c763505a",
            "MOZ_NEW_CERT_STORAGE": false,
            "MOZ_NEW_NOTIFICATION_STORE": false,
            "MOZ_NEW_XULSTORE": false,
            "MOZ_OFFICIAL_BRANDING": false,
            "MOZ_PLACES": false,
            "MOZ_REQUIRE_SIGNING": false,
            "MOZ_SANDBOX": false,
            "MOZ_SERVICES_HEALTHREPORT": true,
            "MOZ_SERVICES_SYNC": false,
            "MOZ_SWITCHBOARD": true,
            "MOZ_SYSTEM_NSS": false,
            "MOZ_TELEMETRY_ON_BY_DEFAULT": false,
            "MOZ_TELEMETRY_REPORTING": true,
            "MOZ_UNSIGNED_SCOPES": 0,
            "MOZ_UPDATER": false,
            "MOZ_UPDATE_CHANNEL": "release",
            "MOZ_WEBRTC": true,
            "MOZ_WIDGET_GTK": false,
            "MOZ_WIDGET_TOOLKIT": "android",
            "NIGHTLY_BUILD": false,
            "OMNIJAR_NAME": "assets/omni.ja",
            "RELEASE_OR_BETA": true,
            "SOURCE_REVISION_URL": "https://hg.mozilla.org/releases/mozilla-esr68/rev/d2e0b9e17b9bc1ef02606c8006b73293f7892ad5",
            "TELEMETRY_PING_FORMAT_VERSION": 4,
            "XP_UNIX": true,
            "isPlatformAndVersionAtLeast": {},
            "isPlatformAndVersionAtMost": {},
            "platform": "android"
          },
          "userAgent": "Mozilla/5.0 (Android 8.1.0; Mobile; rv:68.0) Gecko/68.0 Firefox/68.0",
          "windowSize": "360x560"
        },
        "pageinfo": {
          "documentHeight": 12689,
          "documentSize": {
            "decodedBodySize": 170268,
            "encodedBodySize": 27972,
            "transferSize": 28847
          },
          "documentTitle": "Create Your Free Website | Free Website Builder | Website.com",
          "documentWidth": 360,
          "domElements": 955,
          "navigationStartTime": 1620395578996,
          "nextHopProtocol": "h2",
          "resources": {
            "count": 0,
            "duration": 0
          },
          "responsive": true,
          "url": "https://www.website.com/",
          "visualElements": {
            "heroes": [
              {
                "filename": null,
                "height": 208,
                "name": "Heading",
                "width": 324,
                "x": 18,
                "y": 132
              }
            ],
            "viewport": {
              "height": 560,
              "width": 360
            }
          }
        },
        "timings": {
          "firstPaint": 3745,
          "loadEventEnd": 5745,
          "navigationTiming": {
            "connectStart": 1606,
            "domComplete": 5738,
            "domContentLoadedEventEnd": 5672,
            "domContentLoadedEventStart": 5567,
            "domInteractive": 5390,
            "domainLookupEnd": 1606,
            "domainLookupStart": 1606,
            "duration": 5745,
            "fetchStart": 1581,
            "loadEventEnd": 5745,
            "loadEventStart": 5738,
            "redirectEnd": 1578,
            "redirectStart": 2,
            "requestStart": 1617,
            "responseEnd": 3288,
            "responseStart": 3250,
            "secureConnectionStart": 0,
            "startTime": 0,
            "unloadEventEnd": 0,
            "unloadEventStart": 0,
            "workerStart": 0
          },
          "pageTimings": {
            "backEndTime": 3250,
            "domContentLoadedTime": 5567,
            "domInteractiveTime": 5390,
            "domainLookupTime": 0,
            "frontEndTime": 2450,
            "pageDownloadTime": 38,
            "pageLoadTime": 5738,
            "redirectionTime": 1576,
            "serverConnectionTime": 0,
            "serverResponseTime": 1671
          },
          "rumSpeedIndex": 3249,
          "timeToContentfulPaint": 3870,
          "timeToDomContentFlushed": 5401,
          "userTimings": {
            "marks": [],
            "measures": []
          }
        }
      }
    ],
    "visualMetrics": [],
    "cpu": [],
    "extras": [
      {},
      {}
    ],
    "fullyLoaded": [],
    "errors": [
      [],
      []
    ],
    "statistics": {
      "browser": {
        "appConstants": {
          "MOZ_UNSIGNED_SCOPES": {
            "median": 0,
            "mean": 0,
            "mdev": 0,
            "stddev": 0,
            "min": 0,
            "p10": 0,
            "p90": 0,
            "p99": 0,
            "max": 0
          },
          "TELEMETRY_PING_FORMAT_VERSION": {
            "median": 4,
            "mean": 4,
            "mdev": 0,
            "stddev": 0,
            "min": 4,
            "p10": 4,
            "p90": 4,
            "p99": 4,
            "max": 4
          }
        },
        "asyncAppConstants": {
          "MOZ_UNSIGNED_SCOPES": {
            "median": 0,
            "mean": 0,
            "mdev": 0,
            "stddev": 0,
            "min": 0,
            "p10": 0,
            "p90": 0,
            "p99": 0,
            "max": 0
          },
          "TELEMETRY_PING_FORMAT_VERSION": {
            "median": 4,
            "mean": 4,
            "mdev": 0,
            "stddev": 0,
            "min": 4,
            "p10": 4,
            "p90": 4,
            "p99": 4,
            "max": 4
          }
        }
      },
      "pageinfo": {
        "documentHeight": {
          "median": 12689,
          "mean": 12689,
          "mdev": 0,
          "stddev": 0,
          "min": 12689,
          "p10": 12689,
          "p90": 12689,
          "p99": 12689,
          "max": 12689
        },
        "documentSize": {
          "decodedBodySize": {
            "median": 170269,
            "mean": 170269,
            "mdev": 0.7071,
            "stddev": 1,
            "min": 170268,
            "p10": 170268,
            "p90": 170270,
            "p99": 170270,
            "max": 170270
          },
          "encodedBodySize": {
            "median": 27990,
            "mean": 27990,
            "mdev": 12.3744,
            "stddev": 18,
            "min": 27972,
            "p10": 27972,
            "p90": 28007,
            "p99": 28007,
            "max": 28007
          },
          "transferSize": {
            "median": 28865,
            "mean": 28865,
            "mdev": 12.3744,
            "stddev": 18,
            "min": 28847,
            "p10": 28847,
            "p90": 28882,
            "p99": 28882,
            "max": 28882
          }
        },
        "documentWidth": {
          "median": 360,
          "mean": 360,
          "mdev": 0,
          "stddev": 0,
          "min": 360,
          "p10": 360,
          "p90": 360,
          "p99": 360,
          "max": 360
        },
        "domElements": {
          "median": 955,
          "mean": 955,
          "mdev": 0,
          "stddev": 0,
          "min": 955,
          "p10": 955,
          "p90": 955,
          "p99": 955,
          "max": 955
        },
        "navigationStartTime": {
          "median": 1620395537947,
          "mean": 1620395537947,
          "mdev": 28377.9204,
          "stddev": 40132,
          "min": 1620395496897,
          "p10": 1620395496897,
          "p90": 1620395578996,
          "p99": 1620395578996,
          "max": 1620395578996
        },
        "resources": {
          "count": {
            "median": 0,
            "mean": 0,
            "mdev": 0,
            "stddev": 0,
            "min": 0,
            "p10": 0,
            "p90": 0,
            "p99": 0,
            "max": 0
          },
          "duration": {
            "median": 0,
            "mean": 0,
            "mdev": 0,
            "stddev": 0,
            "min": 0,
            "p10": 0,
            "p90": 0,
            "p99": 0,
            "max": 0
          }
        },
        "visualElements": {
          "heroes": [
            {
              "height": {
                "median": 208,
                "mean": 208,
                "mdev": 0,
                "stddev": 0,
                "min": 208,
                "p10": 208,
                "p90": 208,
                "p99": 208,
                "max": 208
              },
              "width": {
                "median": 324,
                "mean": 324,
                "mdev": 0,
                "stddev": 0,
                "min": 324,
                "p10": 324,
                "p90": 324,
                "p99": 324,
                "max": 324
              },
              "x": {
                "median": 18,
                "mean": 18,
                "mdev": 0,
                "stddev": 0,
                "min": 18,
                "p10": 18,
                "p90": 18,
                "p99": 18,
                "max": 18
              },
              "y": {
                "median": 132,
                "mean": 132,
                "mdev": 0,
                "stddev": 0,
                "min": 132,
                "p10": 132,
                "p90": 132,
                "p99": 132,
                "max": 132
              }
            }
          ],
          "viewport": {
            "height": {
              "median": 560,
              "mean": 560,
              "mdev": 0,
              "stddev": 0,
              "min": 560,
              "p10": 560,
              "p90": 560,
              "p99": 560,
              "max": 560
            },
            "width": {
              "median": 360,
              "mean": 360,
              "mdev": 0,
              "stddev": 0,
              "min": 360,
              "p10": 360,
              "p90": 360,
              "p99": 360,
              "max": 360
            }
          }
        }
      },
      "timings": {
        "firstPaint": {
          "median": 4102,
          "mean": 4102,
          "mdev": 252.4371,
          "stddev": 357,
          "min": 3745,
          "p10": 3745,
          "p90": 4459,
          "p99": 4459,
          "max": 4459
        },
        "loadEventEnd": {
          "median": 6067,
          "mean": 6067,
          "mdev": 227.6884,
          "stddev": 322,
          "min": 5745,
          "p10": 5745,
          "p90": 6389,
          "p99": 6389,
          "max": 6389
        },
        "navigationTiming": {
          "connectStart": {
            "median": 1730,
            "mean": 1730,
            "mdev": 87.6812,
            "stddev": 124,
            "min": 1606,
            "p10": 1606,
            "p90": 1854,
            "p99": 1854,
            "max": 1854
          },
          "domComplete": {
            "median": 6059,
            "mean": 6059,
            "mdev": 226.6277,
            "stddev": 321,
            "min": 5738,
            "p10": 5738,
            "p90": 6379,
            "p99": 6379,
            "max": 6379
          },
          "domContentLoadedEventEnd": {
            "median": 6001,
            "mean": 6001,
            "mdev": 232.2846,
            "stddev": 329,
            "min": 5672,
            "p10": 5672,
            "p90": 6329,
            "p99": 6329,
            "max": 6329
          },
          "domContentLoadedEventStart": {
            "median": 5899,
            "mean": 5899,
            "mdev": 234.4059,
            "stddev": 332,
            "min": 5567,
            "p10": 5567,
            "p90": 6230,
            "p99": 6230,
            "max": 6230
          },
          "domInteractive": {
            "median": 5791,
            "mean": 5791,
            "mdev": 283.1963,
            "stddev": 401,
            "min": 5390,
            "p10": 5390,
            "p90": 6191,
            "p99": 6191,
            "max": 6191
          },
          "domainLookupEnd": {
            "median": 1730,
            "mean": 1730,
            "mdev": 87.3277,
            "stddev": 124,
            "min": 1606,
            "p10": 1606,
            "p90": 1853,
            "p99": 1853,
            "max": 1853
          },
          "domainLookupStart": {
            "median": 1730,
            "mean": 1730,
            "mdev": 87.3277,
            "stddev": 124,
            "min": 1606,
            "p10": 1606,
            "p90": 1853,
            "p99": 1853,
            "max": 1853
          },
          "duration": {
            "median": 6067,
            "mean": 6067,
            "mdev": 227.6884,
            "stddev": 322,
            "min": 5745,
            "p10": 5745,
            "p90": 6389,
            "p99": 6389,
            "max": 6389
          },
          "fetchStart": {
            "median": 1604,
            "mean": 1604,
            "mdev": 15.9099,
            "stddev": 23,
            "min": 1581,
            "p10": 1581,
            "p90": 1626,
            "p99": 1626,
            "max": 1626
          },
          "loadEventEnd": {
            "median": 6067,
            "mean": 6067,
            "mdev": 227.6884,
            "stddev": 322,
            "min": 5745,
            "p10": 5745,
            "p90": 6389,
            "p99": 6389,
            "max": 6389
          },
          "loadEventStart": {
            "median": 6059,
            "mean": 6059,
            "mdev": 226.6277,
            "stddev": 321,
            "min": 5738,
            "p10": 5738,
            "p90": 6379,
            "p99": 6379,
            "max": 6379
          },
          "redirectEnd": {
            "median": 1582,
            "mean": 1582,
            "mdev": 2.8284,
            "stddev": 4,
            "min": 1578,
            "p10": 1578,
            "p90": 1586,
            "p99": 1586,
            "max": 1586
          },
          "redirectStart": {
            "median": 7,
            "mean": 7,
            "mdev": 3.182,
            "stddev": 5,
            "min": 2,
            "p10": 2,
            "p90": 11,
            "p99": 11,
            "max": 11
          },
          "requestStart": {
            "median": 1742,
            "mean": 1742,
            "mdev": 88.0348,
            "stddev": 125,
            "min": 1617,
            "p10": 1617,
            "p90": 1866,
            "p99": 1866,
            "max": 1866
          },
          "responseEnd": {
            "median": 3596,
            "mean": 3596,
            "mdev": 217.4353,
            "stddev": 308,
            "min": 3288,
            "p10": 3288,
            "p90": 3903,
            "p99": 3903,
            "max": 3903
          },
          "responseStart": {
            "median": 3564,
            "mean": 3564,
            "mdev": 221.678,
            "stddev": 314,
            "min": 3250,
            "p10": 3250,
            "p90": 3877,
            "p99": 3877,
            "max": 3877
          },
          "secureConnectionStart": {
            "median": 0,
            "mean": 0,
            "mdev": 0,
            "stddev": 0,
            "min": 0,
            "p10": 0,
            "p90": 0,
            "p99": 0,
            "max": 0
          },
          "startTime": {
            "median": 0,
            "mean": 0,
            "mdev": 0,
            "stddev": 0,
            "min": 0,
            "p10": 0,
            "p90": 0,
            "p99": 0,
            "max": 0
          },
          "unloadEventEnd": {
            "median": 0,
            "mean": 0,
            "mdev": 0,
            "stddev": 0,
            "min": 0,
            "p10": 0,
            "p90": 0,
            "p99": 0,
            "max": 0
          },
          "unloadEventStart": {
            "median": 0,
            "mean": 0,
            "mdev": 0,
            "stddev": 0,
            "min": 0,
            "p10": 0,
            "p90": 0,
            "p99": 0,
            "max": 0
          },
          "workerStart": {
            "median": 0,
            "mean": 0,
            "mdev": 0,
            "stddev": 0,
            "min": 0,
            "p10": 0,
            "p90": 0,
            "p99": 0,
            "max": 0
          }
        },
        "pageTimings": {
          "backEndTime": {
            "median": 3564,
            "mean": 3564,
            "mdev": 221.678,
            "stddev": 314,
            "min": 3250,
            "p10": 3250,
            "p90": 3877,
            "p99": 3877,
            "max": 3877
          },
          "domContentLoadedTime": {
            "median": 5899,
            "mean": 5899,
            "mdev": 234.4059,
            "stddev": 332,
            "min": 5567,
            "p10": 5567,
            "p90": 6230,
            "p99": 6230,
            "max": 6230
          },
          "domInteractiveTime": {
            "median": 5791,
            "mean": 5791,
            "mdev": 283.1963,
            "stddev": 401,
            "min": 5390,
            "p10": 5390,
            "p90": 6191,
            "p99": 6191,
            "max": 6191
          },
          "domainLookupTime": {
            "median": 0,
            "mean": 0,
            "mdev": 0,
            "stddev": 0,
            "min": 0,
            "p10": 0,
            "p90": 0,
            "p99": 0,
            "max": 0
          },
          "frontEndTime": {
            "median": 2463,
            "mean": 2463,
            "mdev": 9.1924,
            "stddev": 13,
            "min": 2450,
            "p10": 2450,
            "p90": 2476,
            "p99": 2476,
            "max": 2476
          },
          "pageDownloadTime": {
            "median": 33,
            "mean": 33,
            "mdev": 3.8891,
            "stddev": 6,
            "min": 27,
            "p10": 27,
            "p90": 38,
            "p99": 38,
            "max": 38
          },
          "pageLoadTime": {
            "median": 6059,
            "mean": 6059,
            "mdev": 226.6277,
            "stddev": 321,
            "min": 5738,
            "p10": 5738,
            "p90": 6379,
            "p99": 6379,
            "max": 6379
          },
          "redirectionTime": {
            "median": 1576,
            "mean": 1576,
            "mdev": 0.3536,
            "stddev": 1,
            "min": 1575,
            "p10": 1575,
            "p90": 1576,
            "p99": 1576,
            "max": 1576
          },
          "serverConnectionTime": {
            "median": 0,
            "mean": 0,
            "mdev": 0,
            "stddev": 0,
            "min": 0,
            "p10": 0,
            "p90": 0,
            "p99": 0,
            "max": 0
          },
          "serverResponseTime": {
            "median": 1854,
            "mean": 1854,
            "mdev": 129.4005,
            "stddev": 183,
            "min": 1671,
            "p10": 1671,
            "p90": 2037,
            "p99": 2037,
            "max": 2037
          }
        },
        "rumSpeedIndex": {
          "median": 3563,
          "mean": 3563,
          "mdev": 221.678,
          "stddev": 314,
          "min": 3249,
          "p10": 3249,
          "p90": 3876,
          "p99": 3876,
          "max": 3876
        },
        "timeToContentfulPaint": {
          "median": 4230,
          "mean": 4230,
          "mdev": 254.2049,
          "stddev": 360,
          "min": 3870,
          "p10": 3870,
          "p90": 4589,
          "p99": 4589,
          "max": 4589
        },
        "timeToDomContentFlushed": {
          "median": 5802,
          "mean": 5802,
          "mdev": 283.5498,
          "stddev": 401,
          "min": 5401,
          "p10": 5401,
          "p90": 6203,
          "p99": 6203,
          "max": 6203
        }
      }
    }
  },
  {
    "info": {
      "browsertime": {
        "version": "8.4.0"
      },
      "url": "https://sportsmedicine.mayoclinic.org/?browsertime_run=2",
      "timestamp": "2021-05-07T17:52:02+04:00",
      "connectivity": {
        "engine": "external",
        "profile": "native"
      },
      "extra": {}
    },
    "files": {
      "video": [],
      "screenshot": [],
      "timeline": [],
      "consoleLog": [],
      "netLog": [],
      "perfLog": []
    },
    "cdp": {
      "performance": []
    },
    "timestamps": [
      "2021-05-07T17:51:50+04:00",
      "2021-05-07T17:53:11+04:00"
    ],
    "browserScripts": [
      {
        "browser": {
          "appConstants": {
            "ACCESSIBILITY": true,
            "ANDROID_PACKAGE_NAME": "org.mozilla.firefox",
            "ASAN": false,
            "ASAN_REPORTER": false,
            "BROWSER_CHROME_URL": "chrome://browser/content/browser.xul",
            "DEBUG": false,
            "DEBUG_JS_MODULES": "",
            "DLL_PREFIX": "lib",
            "DLL_SUFFIX": ".so",
            "EARLY_BETA_OR_EARLIER": false,
            "FENNEC_NIGHTLY": false,
            "HAVE_SHELL_SERVICE": false,
            "HAVE_USR_LIB64_DIR": false,
            "MENUBAR_CAN_AUTOHIDE": false,
            "MOZILLA_OFFICIAL": true,
            "MOZ_ALLOW_LEGACY_EXTENSIONS": false,
            "MOZ_ANDROID_ACTIVITY_STREAM": false,
            "MOZ_ANDROID_HISTORY": true,
            "MOZ_ANDROID_MOZILLA_ONLINE": false,
            "MOZ_APP_NAME": "fennec",
            "MOZ_APP_VERSION": "68.1.1",
            "MOZ_APP_VERSION_DISPLAY": "68.1.1",
            "MOZ_BING_API_CLIENTID": "no-bing-api-clientid",
            "MOZ_BING_API_KEY": "no-bing-api-key",
            "MOZ_BITS_DOWNLOAD": false,
            "MOZ_BUILD_APP": "mobile/android",
            "MOZ_CODE_COVERAGE": false,
            "MOZ_CRASHREPORTER": true,
            "MOZ_DATA_REPORTING": true,
            "MOZ_DEV_EDITION": false,
            "MOZ_GECKO_PROFILER": true,
            "MOZ_GOOGLE_LOCATION_SERVICE_API_KEY": "AIzaSyB2h2OuRcUgy5N-5hsZqiPW6sH3n_rptiQ",
            "MOZ_GOOGLE_SAFEBROWSING_API_KEY": "AIzaSyC7jsptDS3am4tPx4r3nxis7IMjBc5Dovo",
            "MOZ_GRAPHENE": false,
            "MOZ_MACBUNDLE_NAME": "Firefox.app",
            "MOZ_MAINTENANCE_SERVICE": false,
            "MOZ_MOZILLA_API_KEY": "3b4d27dd-703d-4094-8398-4de2c763505a",
            "MOZ_NEW_CERT_STORAGE": false,
            "MOZ_NEW_NOTIFICATION_STORE": false,
            "MOZ_NEW_XULSTORE": false,
            "MOZ_OFFICIAL_BRANDING": false,
            "MOZ_PLACES": false,
            "MOZ_REQUIRE_SIGNING": false,
            "MOZ_SANDBOX": false,
            "MOZ_SERVICES_HEALTHREPORT": true,
            "MOZ_SERVICES_SYNC": false,
            "MOZ_SWITCHBOARD": true,
            "MOZ_SYSTEM_NSS": false,
            "MOZ_TELEMETRY_ON_BY_DEFAULT": false,
            "MOZ_TELEMETRY_REPORTING": true,
            "MOZ_UNSIGNED_SCOPES": 0,
            "MOZ_UPDATER": false,
            "MOZ_UPDATE_CHANNEL": "release",
            "MOZ_WEBRTC": true,
            "MOZ_WIDGET_GTK": false,
            "MOZ_WIDGET_TOOLKIT": "android",
            "NIGHTLY_BUILD": false,
            "OMNIJAR_NAME": "assets/omni.ja",
            "RELEASE_OR_BETA": true,
            "SOURCE_REVISION_URL": "https://hg.mozilla.org/releases/mozilla-esr68/rev/d2e0b9e17b9bc1ef02606c8006b73293f7892ad5",
            "TELEMETRY_PING_FORMAT_VERSION": 4,
            "XP_UNIX": true,
            "isPlatformAndVersionAtLeast": {},
            "isPlatformAndVersionAtMost": {},
            "platform": "android"
          },
          "asyncAppConstants": {
            "ACCESSIBILITY": true,
            "ANDROID_PACKAGE_NAME": "org.mozilla.firefox",
            "ASAN": false,
            "ASAN_REPORTER": false,
            "BROWSER_CHROME_URL": "chrome://browser/content/browser.xul",
            "DEBUG": false,
            "DEBUG_JS_MODULES": "",
            "DLL_PREFIX": "lib",
            "DLL_SUFFIX": ".so",
            "EARLY_BETA_OR_EARLIER": false,
            "FENNEC_NIGHTLY": false,
            "HAVE_SHELL_SERVICE": false,
            "HAVE_USR_LIB64_DIR": false,
            "MENUBAR_CAN_AUTOHIDE": false,
            "MOZILLA_OFFICIAL": true,
            "MOZ_ALLOW_LEGACY_EXTENSIONS": false,
            "MOZ_ANDROID_ACTIVITY_STREAM": false,
            "MOZ_ANDROID_HISTORY": true,
            "MOZ_ANDROID_MOZILLA_ONLINE": false,
            "MOZ_APP_NAME": "fennec",
            "MOZ_APP_VERSION": "68.1.1",
            "MOZ_APP_VERSION_DISPLAY": "68.1.1",
            "MOZ_BING_API_CLIENTID": "no-bing-api-clientid",
            "MOZ_BING_API_KEY": "no-bing-api-key",
            "MOZ_BITS_DOWNLOAD": false,
            "MOZ_BUILD_APP": "mobile/android",
            "MOZ_CODE_COVERAGE": false,
            "MOZ_CRASHREPORTER": true,
            "MOZ_DATA_REPORTING": true,
            "MOZ_DEV_EDITION": false,
            "MOZ_GECKO_PROFILER": true,
            "MOZ_GOOGLE_LOCATION_SERVICE_API_KEY": "AIzaSyB2h2OuRcUgy5N-5hsZqiPW6sH3n_rptiQ",
            "MOZ_GOOGLE_SAFEBROWSING_API_KEY": "AIzaSyC7jsptDS3am4tPx4r3nxis7IMjBc5Dovo",
            "MOZ_GRAPHENE": false,
            "MOZ_MACBUNDLE_NAME": "Firefox.app",
            "MOZ_MAINTENANCE_SERVICE": false,
            "MOZ_MOZILLA_API_KEY": "3b4d27dd-703d-4094-8398-4de2c763505a",
            "MOZ_NEW_CERT_STORAGE": false,
            "MOZ_NEW_NOTIFICATION_STORE": false,
            "MOZ_NEW_XULSTORE": false,
            "MOZ_OFFICIAL_BRANDING": false,
            "MOZ_PLACES": false,
            "MOZ_REQUIRE_SIGNING": false,
            "MOZ_SANDBOX": false,
            "MOZ_SERVICES_HEALTHREPORT": true,
            "MOZ_SERVICES_SYNC": false,
            "MOZ_SWITCHBOARD": true,
            "MOZ_SYSTEM_NSS": false,
            "MOZ_TELEMETRY_ON_BY_DEFAULT": false,
            "MOZ_TELEMETRY_REPORTING": true,
            "MOZ_UNSIGNED_SCOPES": 0,
            "MOZ_UPDATER": false,
            "MOZ_UPDATE_CHANNEL": "release",
            "MOZ_WEBRTC": true,
            "MOZ_WIDGET_GTK": false,
            "MOZ_WIDGET_TOOLKIT": "android",
            "NIGHTLY_BUILD": false,
            "OMNIJAR_NAME": "assets/omni.ja",
            "RELEASE_OR_BETA": true,
            "SOURCE_REVISION_URL": "https://hg.mozilla.org/releases/mozilla-esr68/rev/d2e0b9e17b9bc1ef02606c8006b73293f7892ad5",
            "TELEMETRY_PING_FORMAT_VERSION": 4,
            "XP_UNIX": true,
            "isPlatformAndVersionAtLeast": {},
            "isPlatformAndVersionAtMost": {},
            "platform": "android"
          },
          "userAgent": "Mozilla/5.0 (Android 8.1.0; Mobile; rv:68.0) Gecko/68.0 Firefox/68.0",
          "windowSize": "360x560"
        },
        "pageinfo": {
          "documentHeight": 4116,
          "documentSize": {
            "decodedBodySize": 30516,
            "encodedBodySize": 6954,
            "transferSize": 7428
          },
          "documentTitle": "Mayo Clinic Orthopedics and Sports Medicine",
          "documentWidth": 3237,
          "domElements": 390,
          "navigationStartTime": 1620395510896,
          "nextHopProtocol": "h2",
          "resources": {
            "count": 0,
            "duration": 0
          },
          "responsive": true,
          "url": "https://sportsmedicine.mayoclinic.org/",
          "visualElements": {
            "heroes": [],
            "viewport": {
              "height": 560,
              "width": 360
            }
          }
        },
        "timings": {
          "firstPaint": 2038,
          "loadEventEnd": 5296,
          "navigationTiming": {
            "connectStart": 53,
            "domComplete": 5208,
            "domContentLoadedEventEnd": 3178,
            "domContentLoadedEventStart": 3140,
            "domInteractive": 2984,
            "domainLookupEnd": 53,
            "domainLookupStart": 53,
            "duration": 5296,
            "fetchStart": 53,
            "loadEventEnd": 5296,
            "loadEventStart": 5208,
            "redirectEnd": 0,
            "redirectStart": 0,
            "requestStart": 146,
            "responseEnd": 506,
            "responseStart": 506,
            "secureConnectionStart": 0,
            "startTime": 0,
            "unloadEventEnd": 0,
            "unloadEventStart": 0,
            "workerStart": 0
          },
          "pageTimings": {
            "backEndTime": 506,
            "domContentLoadedTime": 3140,
            "domInteractiveTime": 2984,
            "domainLookupTime": 0,
            "frontEndTime": 4702,
            "pageDownloadTime": 0,
            "pageLoadTime": 5208,
            "redirectionTime": 0,
            "serverConnectionTime": 0,
            "serverResponseTime": 360
          },
          "rumSpeedIndex": 505,
          "timeToContentfulPaint": 2808,
          "timeToDomContentFlushed": 3027,
          "userTimings": {
            "marks": [],
            "measures": []
          }
        }
      },
      {
        "browser": {
          "appConstants": {
            "ACCESSIBILITY": true,
            "ANDROID_PACKAGE_NAME": "org.mozilla.firefox",
            "ASAN": false,
            "ASAN_REPORTER": false,
            "BROWSER_CHROME_URL": "chrome://browser/content/browser.xul",
            "DEBUG": false,
            "DEBUG_JS_MODULES": "",
            "DLL_PREFIX": "lib",
            "DLL_SUFFIX": ".so",
            "EARLY_BETA_OR_EARLIER": false,
            "FENNEC_NIGHTLY": false,
            "HAVE_SHELL_SERVICE": false,
            "HAVE_USR_LIB64_DIR": false,
            "MENUBAR_CAN_AUTOHIDE": false,
            "MOZILLA_OFFICIAL": true,
            "MOZ_ALLOW_LEGACY_EXTENSIONS": false,
            "MOZ_ANDROID_ACTIVITY_STREAM": false,
            "MOZ_ANDROID_HISTORY": true,
            "MOZ_ANDROID_MOZILLA_ONLINE": false,
            "MOZ_APP_NAME": "fennec",
            "MOZ_APP_VERSION": "68.1.1",
            "MOZ_APP_VERSION_DISPLAY": "68.1.1",
            "MOZ_BING_API_CLIENTID": "no-bing-api-clientid",
            "MOZ_BING_API_KEY": "no-bing-api-key",
            "MOZ_BITS_DOWNLOAD": false,
            "MOZ_BUILD_APP": "mobile/android",
            "MOZ_CODE_COVERAGE": false,
            "MOZ_CRASHREPORTER": true,
            "MOZ_DATA_REPORTING": true,
            "MOZ_DEV_EDITION": false,
            "MOZ_GECKO_PROFILER": true,
            "MOZ_GOOGLE_LOCATION_SERVICE_API_KEY": "AIzaSyB2h2OuRcUgy5N-5hsZqiPW6sH3n_rptiQ",
            "MOZ_GOOGLE_SAFEBROWSING_API_KEY": "AIzaSyC7jsptDS3am4tPx4r3nxis7IMjBc5Dovo",
            "MOZ_GRAPHENE": false,
            "MOZ_MACBUNDLE_NAME": "Firefox.app",
            "MOZ_MAINTENANCE_SERVICE": false,
            "MOZ_MOZILLA_API_KEY": "3b4d27dd-703d-4094-8398-4de2c763505a",
            "MOZ_NEW_CERT_STORAGE": false,
            "MOZ_NEW_NOTIFICATION_STORE": false,
            "MOZ_NEW_XULSTORE": false,
            "MOZ_OFFICIAL_BRANDING": false,
            "MOZ_PLACES": false,
            "MOZ_REQUIRE_SIGNING": false,
            "MOZ_SANDBOX": false,
            "MOZ_SERVICES_HEALTHREPORT": true,
            "MOZ_SERVICES_SYNC": false,
            "MOZ_SWITCHBOARD": true,
            "MOZ_SYSTEM_NSS": false,
            "MOZ_TELEMETRY_ON_BY_DEFAULT": false,
            "MOZ_TELEMETRY_REPORTING": true,
            "MOZ_UNSIGNED_SCOPES": 0,
            "MOZ_UPDATER": false,
            "MOZ_UPDATE_CHANNEL": "release",
            "MOZ_WEBRTC": true,
            "MOZ_WIDGET_GTK": false,
            "MOZ_WIDGET_TOOLKIT": "android",
            "NIGHTLY_BUILD": false,
            "OMNIJAR_NAME": "assets/omni.ja",
            "RELEASE_OR_BETA": true,
            "SOURCE_REVISION_URL": "https://hg.mozilla.org/releases/mozilla-esr68/rev/d2e0b9e17b9bc1ef02606c8006b73293f7892ad5",
            "TELEMETRY_PING_FORMAT_VERSION": 4,
            "XP_UNIX": true,
            "isPlatformAndVersionAtLeast": {},
            "isPlatformAndVersionAtMost": {},
            "platform": "android"
          },
          "asyncAppConstants": {
            "ACCESSIBILITY": true,
            "ANDROID_PACKAGE_NAME": "org.mozilla.firefox",
            "ASAN": false,
            "ASAN_REPORTER": false,
            "BROWSER_CHROME_URL": "chrome://browser/content/browser.xul",
            "DEBUG": false,
            "DEBUG_JS_MODULES": "",
            "DLL_PREFIX": "lib",
            "DLL_SUFFIX": ".so",
            "EARLY_BETA_OR_EARLIER": false,
            "FENNEC_NIGHTLY": false,
            "HAVE_SHELL_SERVICE": false,
            "HAVE_USR_LIB64_DIR": false,
            "MENUBAR_CAN_AUTOHIDE": false,
            "MOZILLA_OFFICIAL": true,
            "MOZ_ALLOW_LEGACY_EXTENSIONS": false,
            "MOZ_ANDROID_ACTIVITY_STREAM": false,
            "MOZ_ANDROID_HISTORY": true,
            "MOZ_ANDROID_MOZILLA_ONLINE": false,
            "MOZ_APP_NAME": "fennec",
            "MOZ_APP_VERSION": "68.1.1",
            "MOZ_APP_VERSION_DISPLAY": "68.1.1",
            "MOZ_BING_API_CLIENTID": "no-bing-api-clientid",
            "MOZ_BING_API_KEY": "no-bing-api-key",
            "MOZ_BITS_DOWNLOAD": false,
            "MOZ_BUILD_APP": "mobile/android",
            "MOZ_CODE_COVERAGE": false,
            "MOZ_CRASHREPORTER": true,
            "MOZ_DATA_REPORTING": true,
            "MOZ_DEV_EDITION": false,
            "MOZ_GECKO_PROFILER": true,
            "MOZ_GOOGLE_LOCATION_SERVICE_API_KEY": "AIzaSyB2h2OuRcUgy5N-5hsZqiPW6sH3n_rptiQ",
            "MOZ_GOOGLE_SAFEBROWSING_API_KEY": "AIzaSyC7jsptDS3am4tPx4r3nxis7IMjBc5Dovo",
            "MOZ_GRAPHENE": false,
            "MOZ_MACBUNDLE_NAME": "Firefox.app",
            "MOZ_MAINTENANCE_SERVICE": false,
            "MOZ_MOZILLA_API_KEY": "3b4d27dd-703d-4094-8398-4de2c763505a",
            "MOZ_NEW_CERT_STORAGE": false,
            "MOZ_NEW_NOTIFICATION_STORE": false,
            "MOZ_NEW_XULSTORE": false,
            "MOZ_OFFICIAL_BRANDING": false,
            "MOZ_PLACES": false,
            "MOZ_REQUIRE_SIGNING": false,
            "MOZ_SANDBOX": false,
            "MOZ_SERVICES_HEALTHREPORT": true,
            "MOZ_SERVICES_SYNC": false,
            "MOZ_SWITCHBOARD": true,
            "MOZ_SYSTEM_NSS": false,
            "MOZ_TELEMETRY_ON_BY_DEFAULT": false,
            "MOZ_TELEMETRY_REPORTING": true,
            "MOZ_UNSIGNED_SCOPES": 0,
            "MOZ_UPDATER": false,
            "MOZ_UPDATE_CHANNEL": "release",
            "MOZ_WEBRTC": true,
            "MOZ_WIDGET_GTK": false,
            "MOZ_WIDGET_TOOLKIT": "android",
            "NIGHTLY_BUILD": false,
            "OMNIJAR_NAME": "assets/omni.ja",
            "RELEASE_OR_BETA": true,
            "SOURCE_REVISION_URL": "https://hg.mozilla.org/releases/mozilla-esr68/rev/d2e0b9e17b9bc1ef02606c8006b73293f7892ad5",
            "TELEMETRY_PING_FORMAT_VERSION": 4,
            "XP_UNIX": true,
            "isPlatformAndVersionAtLeast": {},
            "isPlatformAndVersionAtMost": {},
            "platform": "android"
          },
          "userAgent": "Mozilla/5.0 (Android 8.1.0; Mobile; rv:68.0) Gecko/68.0 Firefox/68.0",
          "windowSize": "360x560"
        },
        "pageinfo": {
          "documentHeight": 4116,
          "documentSize": {
            "decodedBodySize": 30516,
            "encodedBodySize": 6954,
            "transferSize": 7428
          },
          "documentTitle": "Mayo Clinic Orthopedics and Sports Medicine",
          "documentWidth": 3237,
          "domElements": 390,
          "navigationStartTime": 1620395591463,
          "nextHopProtocol": "h2",
          "resources": {
            "count": 0,
            "duration": 0
          },
          "responsive": true,
          "url": "https://sportsmedicine.mayoclinic.org/",
          "visualElements": {
            "heroes": [],
            "viewport": {
              "height": 560,
              "width": 360
            }
          }
        },
        "timings": {
          "firstPaint": 2044,
          "loadEventEnd": 5211,
          "navigationTiming": {
            "connectStart": 4,
            "domComplete": 5129,
            "domContentLoadedEventEnd": 2881,
            "domContentLoadedEventStart": 2843,
            "domInteractive": 2814,
            "domainLookupEnd": 4,
            "domainLookupStart": 4,
            "duration": 5211,
            "fetchStart": 4,
            "loadEventEnd": 5211,
            "loadEventStart": 5129,
            "redirectEnd": 0,
            "redirectStart": 0,
            "requestStart": 208,
            "responseEnd": 694,
            "responseStart": 694,
            "secureConnectionStart": 0,
            "startTime": 0,
            "unloadEventEnd": 0,
            "unloadEventStart": 0,
            "workerStart": 0
          },
          "pageTimings": {
            "backEndTime": 694,
            "domContentLoadedTime": 2843,
            "domInteractiveTime": 2814,
            "domainLookupTime": 0,
            "frontEndTime": 4435,
            "pageDownloadTime": 0,
            "pageLoadTime": 5129,
            "redirectionTime": 0,
            "serverConnectionTime": 0,
            "serverResponseTime": 486
          },
          "rumSpeedIndex": 693,
          "timeToContentfulPaint": 2625,
          "timeToDomContentFlushed": 2929,
          "userTimings": {
            "marks": [],
            "measures": []
          }
        }
      }
    ],
    "visualMetrics": [],
    "cpu": [],
    "extras": [
      {},
      {}
    ],
    "fullyLoaded": [],
    "errors": [
      [],
      []
    ],
    "statistics": {
      "browser": {
        "appConstants": {
          "MOZ_UNSIGNED_SCOPES": {
            "median": 0,
            "mean": 0,
            "mdev": 0,
            "stddev": 0,
            "min": 0,
            "p10": 0,
            "p90": 0,
            "p99": 0,
            "max": 0
          },
          "TELEMETRY_PING_FORMAT_VERSION": {
            "median": 4,
            "mean": 4,
            "mdev": 0,
            "stddev": 0,
            "min": 4,
            "p10": 4,
            "p90": 4,
            "p99": 4,
            "max": 4
          }
        },
        "asyncAppConstants": {
          "MOZ_UNSIGNED_SCOPES": {
            "median": 0,
            "mean": 0,
            "mdev": 0,
            "stddev": 0,
            "min": 0,
            "p10": 0,
            "p90": 0,
            "p99": 0,
            "max": 0
          },
          "TELEMETRY_PING_FORMAT_VERSION": {
            "median": 4,
            "mean": 4,
            "mdev": 0,
            "stddev": 0,
            "min": 4,
            "p10": 4,
            "p90": 4,
            "p99": 4,
            "max": 4
          }
        }
      },
      "pageinfo": {
        "documentHeight": {
          "median": 4116,
          "mean": 4116,
          "mdev": 0,
          "stddev": 0,
          "min": 4116,
          "p10": 4116,
          "p90": 4116,
          "p99": 4116,
          "max": 4116
        },
        "documentSize": {
          "decodedBodySize": {
            "median": 30516,
            "mean": 30516,
            "mdev": 0,
            "stddev": 0,
            "min": 30516,
            "p10": 30516,
            "p90": 30516,
            "p99": 30516,
            "max": 30516
          },
          "encodedBodySize": {
            "median": 6954,
            "mean": 6954,
            "mdev": 0,
            "stddev": 0,
            "min": 6954,
            "p10": 6954,
            "p90": 6954,
            "p99": 6954,
            "max": 6954
          },
          "transferSize": {
            "median": 7428,
            "mean": 7428,
            "mdev": 0,
            "stddev": 0,
            "min": 7428,
            "p10": 7428,
            "p90": 7428,
            "p99": 7428,
            "max": 7428
          }
        },
        "documentWidth": {
          "median": 3237,
          "mean": 3237,
          "mdev": 0,
          "stddev": 0,
          "min": 3237,
          "p10": 3237,
          "p90": 3237,
          "p99": 3237,
          "max": 3237
        },
        "domElements": {
          "median": 390,
          "mean": 390,
          "mdev": 0,
          "stddev": 0,
          "min": 390,
          "p10": 390,
          "p90": 390,
          "p99": 390,
          "max": 390
        },
        "navigationStartTime": {
          "median": 1620395551180,
          "mean": 1620395551180,
          "mdev": 28377.9204,
          "stddev": 40132,
          "min": 1620395510896,
          "p10": 1620395510896,
          "p90": 1620395591463,
          "p99": 1620395591463,
          "max": 1620395591463
        },
        "resources": {
          "count": {
            "median": 0,
            "mean": 0,
            "mdev": 0,
            "stddev": 0,
            "min": 0,
            "p10": 0,
            "p90": 0,
            "p99": 0,
            "max": 0
          },
          "duration": {
            "median": 0,
            "mean": 0,
            "mdev": 0,
            "stddev": 0,
            "min": 0,
            "p10": 0,
            "p90": 0,
            "p99": 0,
            "max": 0
          }
        },
        "visualElements": {
          "viewport": {
            "height": {
              "median": 560,
              "mean": 560,
              "mdev": 0,
              "stddev": 0,
              "min": 560,
              "p10": 560,
              "p90": 560,
              "p99": 560,
              "max": 560
            },
            "width": {
              "median": 360,
              "mean": 360,
              "mdev": 0,
              "stddev": 0,
              "min": 360,
              "p10": 360,
              "p90": 360,
              "p99": 360,
              "max": 360
            }
          }
        }
      },
      "timings": {
        "firstPaint": {
          "median": 2041,
          "mean": 2041,
          "mdev": 2.1213,
          "stddev": 3,
          "min": 2038,
          "p10": 2038,
          "p90": 2044,
          "p99": 2044,
          "max": 2044
        },
        "loadEventEnd": {
          "median": 5254,
          "mean": 5254,
          "mdev": 30.052,
          "stddev": 43,
          "min": 5211,
          "p10": 5211,
          "p90": 5296,
          "p99": 5296,
          "max": 5296
        },
        "navigationTiming": {
          "connectStart": {
            "median": 29,
            "mean": 29,
            "mdev": 17.3241,
            "stddev": 25,
            "min": 4,
            "p10": 4,
            "p90": 53,
            "p99": 53,
            "max": 53
          },
          "domComplete": {
            "median": 5169,
            "mean": 5169,
            "mdev": 27.9307,
            "stddev": 40,
            "min": 5129,
            "p10": 5129,
            "p90": 5208,
            "p99": 5208,
            "max": 5208
          },
          "domContentLoadedEventEnd": {
            "median": 3030,
            "mean": 3030,
            "mdev": 105.0054,
            "stddev": 149,
            "min": 2881,
            "p10": 2881,
            "p90": 3178,
            "p99": 3178,
            "max": 3178
          },
          "domContentLoadedEventStart": {
            "median": 2992,
            "mean": 2992,
            "mdev": 105.0054,
            "stddev": 149,
            "min": 2843,
            "p10": 2843,
            "p90": 3140,
            "p99": 3140,
            "max": 3140
          },
          "domInteractive": {
            "median": 2899,
            "mean": 2899,
            "mdev": 60.1041,
            "stddev": 85,
            "min": 2814,
            "p10": 2814,
            "p90": 2984,
            "p99": 2984,
            "max": 2984
          },
          "domainLookupEnd": {
            "median": 29,
            "mean": 29,
            "mdev": 17.3241,
            "stddev": 25,
            "min": 4,
            "p10": 4,
            "p90": 53,
            "p99": 53,
            "max": 53
          },
          "domainLookupStart": {
            "median": 29,
            "mean": 29,
            "mdev": 17.3241,
            "stddev": 25,
            "min": 4,
            "p10": 4,
            "p90": 53,
            "p99": 53,
            "max": 53
          },
          "duration": {
            "median": 5254,
            "mean": 5254,
            "mdev": 30.052,
            "stddev": 43,
            "min": 5211,
            "p10": 5211,
            "p90": 5296,
            "p99": 5296,
            "max": 5296
          },
          "fetchStart": {
            "median": 29,
            "mean": 29,
            "mdev": 17.3241,
            "stddev": 25,
            "min": 4,
            "p10": 4,
            "p90": 53,
            "p99": 53,
            "max": 53
          },
          "loadEventEnd": {
            "median": 5254,
            "mean": 5254,
            "mdev": 30.052,
            "stddev": 43,
            "min": 5211,
            "p10": 5211,
            "p90": 5296,
            "p99": 5296,
            "max": 5296
          },
          "loadEventStart": {
            "median": 5169,
            "mean": 5169,
            "mdev": 27.9307,
            "stddev": 40,
            "min": 5129,
            "p10": 5129,
            "p90": 5208,
            "p99": 5208,
            "max": 5208
          },
          "redirectEnd": {
            "median": 0,
            "mean": 0,
            "mdev": 0,
            "stddev": 0,
            "min": 0,
            "p10": 0,
            "p90": 0,
            "p99": 0,
            "max": 0
          },
          "redirectStart": {
            "median": 0,
            "mean": 0,
            "mdev": 0,
            "stddev": 0,
            "min": 0,
            "p10": 0,
            "p90": 0,
            "p99": 0,
            "max": 0
          },
          "requestStart": {
            "median": 177,
            "mean": 177,
            "mdev": 21.9203,
            "stddev": 31,
            "min": 146,
            "p10": 146,
            "p90": 208,
            "p99": 208,
            "max": 208
          },
          "responseEnd": {
            "median": 600,
            "mean": 600,
            "mdev": 66.468,
            "stddev": 94,
            "min": 506,
            "p10": 506,
            "p90": 694,
            "p99": 694,
            "max": 694
          },
          "responseStart": {
            "median": 600,
            "mean": 600,
            "mdev": 66.468,
            "stddev": 94,
            "min": 506,
            "p10": 506,
            "p90": 694,
            "p99": 694,
            "max": 694
          },
          "secureConnectionStart": {
            "median": 0,
            "mean": 0,
            "mdev": 0,
            "stddev": 0,
            "min": 0,
            "p10": 0,
            "p90": 0,
            "p99": 0,
            "max": 0
          },
          "startTime": {
            "median": 0,
            "mean": 0,
            "mdev": 0,
            "stddev": 0,
            "min": 0,
            "p10": 0,
            "p90": 0,
            "p99": 0,
            "max": 0
          },
          "unloadEventEnd": {
            "median": 0,
            "mean": 0,
            "mdev": 0,
            "stddev": 0,
            "min": 0,
            "p10": 0,
            "p90": 0,
            "p99": 0,
            "max": 0
          },
          "unloadEventStart": {
            "median": 0,
            "mean": 0,
            "mdev": 0,
            "stddev": 0,
            "min": 0,
            "p10": 0,
            "p90": 0,
            "p99": 0,
            "max": 0
          },
          "workerStart": {
            "median": 0,
            "mean": 0,
            "mdev": 0,
            "stddev": 0,
            "min": 0,
            "p10": 0,
            "p90": 0,
            "p99": 0,
            "max": 0
          }
        },
        "pageTimings": {
          "backEndTime": {
            "median": 600,
            "mean": 600,
            "mdev": 66.468,
            "stddev": 94,
            "min": 506,
            "p10": 506,
            "p90": 694,
            "p99": 694,
            "max": 694
          },
          "domContentLoadedTime": {
            "median": 2992,
            "mean": 2992,
            "mdev": 105.0054,
            "stddev": 149,
            "min": 2843,
            "p10": 2843,
            "p90": 3140,
            "p99": 3140,
            "max": 3140
          },
          "domInteractiveTime": {
            "median": 2899,
            "mean": 2899,
            "mdev": 60.1041,
            "stddev": 85,
            "min": 2814,
            "p10": 2814,
            "p90": 2984,
            "p99": 2984,
            "max": 2984
          },
          "domainLookupTime": {
            "median": 0,
            "mean": 0,
            "mdev": 0,
            "stddev": 0,
            "min": 0,
            "p10": 0,
            "p90": 0,
            "p99": 0,
            "max": 0
          },
          "frontEndTime": {
            "median": 4569,
            "mean": 4569,
            "mdev": 94.3988,
            "stddev": 134,
            "min": 4435,
            "p10": 4435,
            "p90": 4702,
            "p99": 4702,
            "max": 4702
          },
          "pageDownloadTime": {
            "median": 0,
            "mean": 0,
            "mdev": 0,
            "stddev": 0,
            "min": 0,
            "p10": 0,
            "p90": 0,
            "p99": 0,
            "max": 0
          },
          "pageLoadTime": {
            "median": 5169,
            "mean": 5169,
            "mdev": 27.9307,
            "stddev": 40,
            "min": 5129,
            "p10": 5129,
            "p90": 5208,
            "p99": 5208,
            "max": 5208
          },
          "redirectionTime": {
            "median": 0,
            "mean": 0,
            "mdev": 0,
            "stddev": 0,
            "min": 0,
            "p10": 0,
            "p90": 0,
            "p99": 0,
            "max": 0
          },
          "serverConnectionTime": {
            "median": 0,
            "mean": 0,
            "mdev": 0,
            "stddev": 0,
            "min": 0,
            "p10": 0,
            "p90": 0,
            "p99": 0,
            "max": 0
          },
          "serverResponseTime": {
            "median": 423,
            "mean": 423,
            "mdev": 44.5477,
            "stddev": 63,
            "min": 360,
            "p10": 360,
            "p90": 486,
            "p99": 486,
            "max": 486
          }
        },
        "rumSpeedIndex": {
          "median": 599,
          "mean": 599,
          "mdev": 66.468,
          "stddev": 94,
          "min": 505,
          "p10": 505,
          "p90": 693,
          "p99": 693,
          "max": 693
        },
        "timeToContentfulPaint": {
          "median": 2717,
          "mean": 2717,
          "mdev": 64.7003,
          "stddev": 92,
          "min": 2625,
          "p10": 2625,
          "p90": 2808,
          "p99": 2808,
          "max": 2808
        },
        "timeToDomContentFlushed": {
          "median": 2978,
          "mean": 2978,
          "mdev": 34.6482,
          "stddev": 49,
          "min": 2929,
          "p10": 2929,
          "p90": 3027,
          "p99": 3027,
          "max": 3027
        }
      }
    }
  }
]