[{"info":{"browsertime":{"version":"8.4.0"},"url":"https://github.com/","timestamp":"2021-03-12T22:50:51+04:00","connectivity":{"engine":"external","profile":"native"},"extra":{}},"files":{"video":[],"screenshot":[],"timeline":[],"consoleLog":[],"netLog":[],"perfLog":[]},"cdp":{"performance":[]},"timestamps":["2021-03-12T22:50:10+04:00","2021-03-12T22:51:06+04:00","2021-03-12T22:52:04+04:00"],"browserScripts":[{"browser":{"appConstants":{"ACCESSIBILITY":true,"ANDROID_PACKAGE_NAME":"org.mozilla.firefox","ASAN":false,"ASAN_REPORTER":false,"BROWSER_CHROME_URL":"chrome://browser/content/browser.xul","DEBUG":false,"DEBUG_JS_MODULES":"","DLL_PREFIX":"lib","DLL_SUFFIX":".so","EARLY_BETA_OR_EARLIER":false,"FENNEC_NIGHTLY":false,"HAVE_SHELL_SERVICE":false,"HAVE_USR_LIB64_DIR":false,"MENUBAR_CAN_AUTOHIDE":false,"MOZILLA_OFFICIAL":true,"MOZ_ALLOW_LEGACY_EXTENSIONS":false,"MOZ_ANDROID_ACTIVITY_STREAM":false,"MOZ_ANDROID_HISTORY":true,"MOZ_ANDROID_MOZILLA_ONLINE":false,"MOZ_APP_NAME":"fennec","MOZ_APP_VERSION":"68.1.1","MOZ_APP_VERSION_DISPLAY":"68.1.1","MOZ_BING_API_CLIENTID":"no-bing-api-clientid","MOZ_BING_API_KEY":"no-bing-api-key","MOZ_BITS_DOWNLOAD":false,"MOZ_BUILD_APP":"mobile/android","MOZ_CODE_COVERAGE":false,"MOZ_CRASHREPORTER":true,"MOZ_DATA_REPORTING":true,"MOZ_DEV_EDITION":false,"MOZ_GECKO_PROFILER":true,"MOZ_GOOGLE_LOCATION_SERVICE_API_KEY":"AIzaSyB2h2OuRcUgy5N-5hsZqiPW6sH3n_rptiQ","MOZ_GOOGLE_SAFEBROWSING_API_KEY":"AIzaSyC7jsptDS3am4tPx4r3nxis7IMjBc5Dovo","MOZ_GRAPHENE":false,"MOZ_MACBUNDLE_NAME":"Firefox.app","MOZ_MAINTENANCE_SERVICE":false,"MOZ_MOZILLA_API_KEY":"3b4d27dd-703d-4094-8398-4de2c763505a","MOZ_NEW_CERT_STORAGE":false,"MOZ_NEW_NOTIFICATION_STORE":false,"MOZ_NEW_XULSTORE":false,"MOZ_OFFICIAL_BRANDING":false,"MOZ_PLACES":false,"MOZ_REQUIRE_SIGNING":false,"MOZ_SANDBOX":false,"MOZ_SERVICES_HEALTHREPORT":true,"MOZ_SERVICES_SYNC":false,"MOZ_SWITCHBOARD":true,"MOZ_SYSTEM_NSS":false,"MOZ_TELEMETRY_ON_BY_DEFAULT":false,"MOZ_TELEMETRY_REPORTING":true,"MOZ_UNSIGNED_SCOPES":0,"MOZ_UPDATER":false,"MOZ_UPDATE_CHANNEL":"release","MOZ_WEBRTC":true,"MOZ_WIDGET_GTK":false,"MOZ_WIDGET_TOOLKIT":"android","NIGHTLY_BUILD":false,"OMNIJAR_NAME":"assets/omni.ja","RELEASE_OR_BETA":true,"SOURCE_REVISION_URL":"https://hg.mozilla.org/releases/mozilla-esr68/rev/d2e0b9e17b9bc1ef02606c8006b73293f7892ad5","TELEMETRY_PING_FORMAT_VERSION":4,"XP_UNIX":true,"isPlatformAndVersionAtLeast":{},"isPlatformAndVersionAtMost":{},"platform":"android"},"asyncAppConstants":{"ACCESSIBILITY":true,"ANDROID_PACKAGE_NAME":"org.mozilla.firefox","ASAN":false,"ASAN_REPORTER":false,"BROWSER_CHROME_URL":"chrome://browser/content/browser.xul","DEBUG":false,"DEBUG_JS_MODULES":"","DLL_PREFIX":"lib","DLL_SUFFIX":".so","EARLY_BETA_OR_EARLIER":false,"FENNEC_NIGHTLY":false,"HAVE_SHELL_SERVICE":false,"HAVE_USR_LIB64_DIR":false,"MENUBAR_CAN_AUTOHIDE":false,"MOZILLA_OFFICIAL":true,"MOZ_ALLOW_LEGACY_EXTENSIONS":false,"MOZ_ANDROID_ACTIVITY_STREAM":false,"MOZ_ANDROID_HISTORY":true,"MOZ_ANDROID_MOZILLA_ONLINE":false,"MOZ_APP_NAME":"fennec","MOZ_APP_VERSION":"68.1.1","MOZ_APP_VERSION_DISPLAY":"68.1.1","MOZ_BING_API_CLIENTID":"no-bing-api-clientid","MOZ_BING_API_KEY":"no-bing-api-key","MOZ_BITS_DOWNLOAD":false,"MOZ_BUILD_APP":"mobile/android","MOZ_CODE_COVERAGE":false,"MOZ_CRASHREPORTER":true,"MOZ_DATA_REPORTING":true,"MOZ_DEV_EDITION":false,"MOZ_GECKO_PROFILER":true,"MOZ_GOOGLE_LOCATION_SERVICE_API_KEY":"AIzaSyB2h2OuRcUgy5N-5hsZqiPW6sH3n_rptiQ","MOZ_GOOGLE_SAFEBROWSING_API_KEY":"AIzaSyC7jsptDS3am4tPx4r3nxis7IMjBc5Dovo","MOZ_GRAPHENE":false,"MOZ_MACBUNDLE_NAME":"Firefox.app","MOZ_MAINTENANCE_SERVICE":false,"MOZ_MOZILLA_API_KEY":"3b4d27dd-703d-4094-8398-4de2c763505a","MOZ_NEW_CERT_STORAGE":false,"MOZ_NEW_NOTIFICATION_STORE":false,"MOZ_NEW_XULSTORE":false,"MOZ_OFFICIAL_BRANDING":false,"MOZ_PLACES":false,"MOZ_REQUIRE_SIGNING":false,"MOZ_SANDBOX":false,"MOZ_SERVICES_HEALTHREPORT":true,"MOZ_SERVICES_SYNC":false,"MOZ_SWITCHBOARD":true,"MOZ_SYSTEM_NSS":false,"MOZ_TELEMETRY_ON_BY_DEFAULT":false,"MOZ_TELEMETRY_REPORTING":true,"MOZ_UNSIGNED_SCOPES":0,"MOZ_UPDATER":false,"MOZ_UPDATE_CHANNEL":"release","MOZ_WEBRTC":true,"MOZ_WIDGET_GTK":false,"MOZ_WIDGET_TOOLKIT":"android","NIGHTLY_BUILD":false,"OMNIJAR_NAME":"assets/omni.ja","RELEASE_OR_BETA":true,"SOURCE_REVISION_URL":"https://hg.mozilla.org/releases/mozilla-esr68/rev/d2e0b9e17b9bc1ef02606c8006b73293f7892ad5","TELEMETRY_PING_FORMAT_VERSION":4,"XP_UNIX":true,"isPlatformAndVersionAtLeast":{},"isPlatformAndVersionAtMost":{},"platform":"android"},"userAgent":"Mozilla/5.0 (Android 8.1.0; Mobile; rv:68.0) Gecko/68.0 Firefox/68.0","windowSize":"360x560"},"pageinfo":{"documentHeight":17195,"documentSize":{"decodedBodySize":199679,"encodedBodySize":36779,"transferSize":39294},"documentTitle":"GitHub: Where the world builds software · GitHub","documentWidth":360,"domElements":1321,"navigationStartTime":1615575010493,"nextHopProtocol":"h2","resources":{"count":0,"duration":0},"responsive":true,"url":"https://github.com/","visualElements":{"heroes":[{"filename":"hero-glow.svg","height":417,"name":"LargestImage","width":720,"x":-180,"y":227},{"filename":null,"height":70,"name":"Heading","width":332,"x":14,"y":172}],"viewport":{"height":560,"width":360}}},"timings":{"firstPaint":6188,"loadEventEnd":24396,"navigationTiming":{"connectStart":203,"domComplete":24395,"domContentLoadedEventEnd":5072,"domContentLoadedEventStart":5047,"domInteractive":1797,"domainLookupEnd":203,"domainLookupStart":203,"duration":24396,"fetchStart":3,"loadEventEnd":24396,"loadEventStart":24395,"redirectEnd":0,"redirectStart":0,"requestStart":676,"responseEnd":876,"responseStart":876,"secureConnectionStart":410,"startTime":0,"unloadEventEnd":0,"unloadEventStart":0,"workerStart":0},"pageTimings":{"backEndTime":876,"domContentLoadedTime":5047,"domInteractiveTime":1797,"domainLookupTime":0,"frontEndTime":23518,"pageDownloadTime":0,"pageLoadTime":24395,"redirectionTime":0,"serverConnectionTime":472,"serverResponseTime":200},"rumSpeedIndex":876,"timeToContentfulPaint":10159,"timeToDomContentFlushed":4579,"userTimings":{"marks":[],"measures":[]}}},{"browser":{"appConstants":{"ACCESSIBILITY":true,"ANDROID_PACKAGE_NAME":"org.mozilla.firefox","ASAN":false,"ASAN_REPORTER":false,"BROWSER_CHROME_URL":"chrome://browser/content/browser.xul","DEBUG":false,"DEBUG_JS_MODULES":"","DLL_PREFIX":"lib","DLL_SUFFIX":".so","EARLY_BETA_OR_EARLIER":false,"FENNEC_NIGHTLY":false,"HAVE_SHELL_SERVICE":false,"HAVE_USR_LIB64_DIR":false,"MENUBAR_CAN_AUTOHIDE":false,"MOZILLA_OFFICIAL":true,"MOZ_ALLOW_LEGACY_EXTENSIONS":false,"MOZ_ANDROID_ACTIVITY_STREAM":false,"MOZ_ANDROID_HISTORY":true,"MOZ_ANDROID_MOZILLA_ONLINE":false,"MOZ_APP_NAME":"fennec","MOZ_APP_VERSION":"68.1.1","MOZ_APP_VERSION_DISPLAY":"68.1.1","MOZ_BING_API_CLIENTID":"no-bing-api-clientid","MOZ_BING_API_KEY":"no-bing-api-key","MOZ_BITS_DOWNLOAD":false,"MOZ_BUILD_APP":"mobile/android","MOZ_CODE_COVERAGE":false,"MOZ_CRASHREPORTER":true,"MOZ_DATA_REPORTING":true,"MOZ_DEV_EDITION":false,"MOZ_GECKO_PROFILER":true,"MOZ_GOOGLE_LOCATION_SERVICE_API_KEY":"AIzaSyB2h2OuRcUgy5N-5hsZqiPW6sH3n_rptiQ","MOZ_GOOGLE_SAFEBROWSING_API_KEY":"AIzaSyC7jsptDS3am4tPx4r3nxis7IMjBc5Dovo","MOZ_GRAPHENE":false,"MOZ_MACBUNDLE_NAME":"Firefox.app","MOZ_MAINTENANCE_SERVICE":false,"MOZ_MOZILLA_API_KEY":"3b4d27dd-703d-4094-8398-4de2c763505a","MOZ_NEW_CERT_STORAGE":false,"MOZ_NEW_NOTIFICATION_STORE":false,"MOZ_NEW_XULSTORE":false,"MOZ_OFFICIAL_BRANDING":false,"MOZ_PLACES":false,"MOZ_REQUIRE_SIGNING":false,"MOZ_SANDBOX":false,"MOZ_SERVICES_HEALTHREPORT":true,"MOZ_SERVICES_SYNC":false,"MOZ_SWITCHBOARD":true,"MOZ_SYSTEM_NSS":false,"MOZ_TELEMETRY_ON_BY_DEFAULT":false,"MOZ_TELEMETRY_REPORTING":true,"MOZ_UNSIGNED_SCOPES":0,"MOZ_UPDATER":false,"MOZ_UPDATE_CHANNEL":"release","MOZ_WEBRTC":true,"MOZ_WIDGET_GTK":false,"MOZ_WIDGET_TOOLKIT":"android","NIGHTLY_BUILD":false,"OMNIJAR_NAME":"assets/omni.ja","RELEASE_OR_BETA":true,"SOURCE_REVISION_URL":"https://hg.mozilla.org/releases/mozilla-esr68/rev/d2e0b9e17b9bc1ef02606c8006b73293f7892ad5","TELEMETRY_PING_FORMAT_VERSION":4,"XP_UNIX":true,"isPlatformAndVersionAtLeast":{},"isPlatformAndVersionAtMost":{},"platform":"android"},"asyncAppConstants":{"ACCESSIBILITY":true,"ANDROID_PACKAGE_NAME":"org.mozilla.firefox","ASAN":false,"ASAN_REPORTER":false,"BROWSER_CHROME_URL":"chrome://browser/content/browser.xul","DEBUG":false,"DEBUG_JS_MODULES":"","DLL_PREFIX":"lib","DLL_SUFFIX":".so","EARLY_BETA_OR_EARLIER":false,"FENNEC_NIGHTLY":false,"HAVE_SHELL_SERVICE":false,"HAVE_USR_LIB64_DIR":false,"MENUBAR_CAN_AUTOHIDE":false,"MOZILLA_OFFICIAL":true,"MOZ_ALLOW_LEGACY_EXTENSIONS":false,"MOZ_ANDROID_ACTIVITY_STREAM":false,"MOZ_ANDROID_HISTORY":true,"MOZ_ANDROID_MOZILLA_ONLINE":false,"MOZ_APP_NAME":"fennec","MOZ_APP_VERSION":"68.1.1","MOZ_APP_VERSION_DISPLAY":"68.1.1","MOZ_BING_API_CLIENTID":"no-bing-api-clientid","MOZ_BING_API_KEY":"no-bing-api-key","MOZ_BITS_DOWNLOAD":false,"MOZ_BUILD_APP":"mobile/android","MOZ_CODE_COVERAGE":false,"MOZ_CRASHREPORTER":true,"MOZ_DATA_REPORTING":true,"MOZ_DEV_EDITION":false,"MOZ_GECKO_PROFILER":true,"MOZ_GOOGLE_LOCATION_SERVICE_API_KEY":"AIzaSyB2h2OuRcUgy5N-5hsZqiPW6sH3n_rptiQ","MOZ_GOOGLE_SAFEBROWSING_API_KEY":"AIzaSyC7jsptDS3am4tPx4r3nxis7IMjBc5Dovo","MOZ_GRAPHENE":false,"MOZ_MACBUNDLE_NAME":"Firefox.app","MOZ_MAINTENANCE_SERVICE":false,"MOZ_MOZILLA_API_KEY":"3b4d27dd-703d-4094-8398-4de2c763505a","MOZ_NEW_CERT_STORAGE":false,"MOZ_NEW_NOTIFICATION_STORE":false,"MOZ_NEW_XULSTORE":false,"MOZ_OFFICIAL_BRANDING":false,"MOZ_PLACES":false,"MOZ_REQUIRE_SIGNING":false,"MOZ_SANDBOX":false,"MOZ_SERVICES_HEALTHREPORT":true,"MOZ_SERVICES_SYNC":false,"MOZ_SWITCHBOARD":true,"MOZ_SYSTEM_NSS":false,"MOZ_TELEMETRY_ON_BY_DEFAULT":false,"MOZ_TELEMETRY_REPORTING":true,"MOZ_UNSIGNED_SCOPES":0,"MOZ_UPDATER":false,"MOZ_UPDATE_CHANNEL":"release","MOZ_WEBRTC":true,"MOZ_WIDGET_GTK":false,"MOZ_WIDGET_TOOLKIT":"android","NIGHTLY_BUILD":false,"OMNIJAR_NAME":"assets/omni.ja","RELEASE_OR_BETA":true,"SOURCE_REVISION_URL":"https://hg.mozilla.org/releases/mozilla-esr68/rev/d2e0b9e17b9bc1ef02606c8006b73293f7892ad5","TELEMETRY_PING_FORMAT_VERSION":4,"XP_UNIX":true,"isPlatformAndVersionAtLeast":{},"isPlatformAndVersionAtMost":{},"platform":"android"},"userAgent":"Mozilla/5.0 (Android 8.1.0; Mobile; rv:68.0) Gecko/68.0 Firefox/68.0","windowSize":"360x560"},"pageinfo":{"documentHeight":17195,"documentSize":{"decodedBodySize":199685,"encodedBodySize":36785,"transferSize":39292},"documentTitle":"GitHub: Where the world builds software · GitHub","documentWidth":360,"domElements":1321,"navigationStartTime":1615575066692,"nextHopProtocol":"h2","resources":{"count":0,"duration":0},"responsive":true,"url":"https://github.com/","visualElements":{"heroes":[{"filename":"hero-glow.svg","height":417,"name":"LargestImage","width":720,"x":-180,"y":227},{"filename":null,"height":70,"name":"Heading","width":332,"x":14,"y":172}],"viewport":{"height":560,"width":360}}},"timings":{"firstPaint":5899,"loadEventEnd":23763,"navigationTiming":{"connectStart":266,"domComplete":23762,"domContentLoadedEventEnd":5094,"domContentLoadedEventStart":5074,"domInteractive":1877,"domainLookupEnd":266,"domainLookupStart":265,"duration":23763,"fetchStart":3,"loadEventEnd":23763,"loadEventStart":23762,"redirectEnd":0,"redirectStart":0,"requestStart":737,"responseEnd":935,"responseStart":935,"secureConnectionStart":464,"startTime":0,"unloadEventEnd":0,"unloadEventStart":0,"workerStart":0},"pageTimings":{"backEndTime":935,"domContentLoadedTime":5074,"domInteractiveTime":1877,"domainLookupTime":0,"frontEndTime":22827,"pageDownloadTime":0,"pageLoadTime":23762,"redirectionTime":0,"serverConnectionTime":469,"serverResponseTime":198},"rumSpeedIndex":934,"timeToContentfulPaint":9494,"timeToDomContentFlushed":4729,"userTimings":{"marks":[],"measures":[]}}},{"browser":{"appConstants":{"ACCESSIBILITY":true,"ANDROID_PACKAGE_NAME":"org.mozilla.firefox","ASAN":false,"ASAN_REPORTER":false,"BROWSER_CHROME_URL":"chrome://browser/content/browser.xul","DEBUG":false,"DEBUG_JS_MODULES":"","DLL_PREFIX":"lib","DLL_SUFFIX":".so","EARLY_BETA_OR_EARLIER":false,"FENNEC_NIGHTLY":false,"HAVE_SHELL_SERVICE":false,"HAVE_USR_LIB64_DIR":false,"MENUBAR_CAN_AUTOHIDE":false,"MOZILLA_OFFICIAL":true,"MOZ_ALLOW_LEGACY_EXTENSIONS":false,"MOZ_ANDROID_ACTIVITY_STREAM":false,"MOZ_ANDROID_HISTORY":true,"MOZ_ANDROID_MOZILLA_ONLINE":false,"MOZ_APP_NAME":"fennec","MOZ_APP_VERSION":"68.1.1","MOZ_APP_VERSION_DISPLAY":"68.1.1","MOZ_BING_API_CLIENTID":"no-bing-api-clientid","MOZ_BING_API_KEY":"no-bing-api-key","MOZ_BITS_DOWNLOAD":false,"MOZ_BUILD_APP":"mobile/android","MOZ_CODE_COVERAGE":false,"MOZ_CRASHREPORTER":true,"MOZ_DATA_REPORTING":true,"MOZ_DEV_EDITION":false,"MOZ_GECKO_PROFILER":true,"MOZ_GOOGLE_LOCATION_SERVICE_API_KEY":"AIzaSyB2h2OuRcUgy5N-5hsZqiPW6sH3n_rptiQ","MOZ_GOOGLE_SAFEBROWSING_API_KEY":"AIzaSyC7jsptDS3am4tPx4r3nxis7IMjBc5Dovo","MOZ_GRAPHENE":false,"MOZ_MACBUNDLE_NAME":"Firefox.app","MOZ_MAINTENANCE_SERVICE":false,"MOZ_MOZILLA_API_KEY":"3b4d27dd-703d-4094-8398-4de2c763505a","MOZ_NEW_CERT_STORAGE":false,"MOZ_NEW_NOTIFICATION_STORE":false,"MOZ_NEW_XULSTORE":false,"MOZ_OFFICIAL_BRANDING":false,"MOZ_PLACES":false,"MOZ_REQUIRE_SIGNING":false,"MOZ_SANDBOX":false,"MOZ_SERVICES_HEALTHREPORT":true,"MOZ_SERVICES_SYNC":false,"MOZ_SWITCHBOARD":true,"MOZ_SYSTEM_NSS":false,"MOZ_TELEMETRY_ON_BY_DEFAULT":false,"MOZ_TELEMETRY_REPORTING":true,"MOZ_UNSIGNED_SCOPES":0,"MOZ_UPDATER":false,"MOZ_UPDATE_CHANNEL":"release","MOZ_WEBRTC":true,"MOZ_WIDGET_GTK":false,"MOZ_WIDGET_TOOLKIT":"android","NIGHTLY_BUILD":false,"OMNIJAR_NAME":"assets/omni.ja","RELEASE_OR_BETA":true,"SOURCE_REVISION_URL":"https://hg.mozilla.org/releases/mozilla-esr68/rev/d2e0b9e17b9bc1ef02606c8006b73293f7892ad5","TELEMETRY_PING_FORMAT_VERSION":4,"XP_UNIX":true,"isPlatformAndVersionAtLeast":{},"isPlatformAndVersionAtMost":{},"platform":"android"},"asyncAppConstants":{"ACCESSIBILITY":true,"ANDROID_PACKAGE_NAME":"org.mozilla.firefox","ASAN":false,"ASAN_REPORTER":false,"BROWSER_CHROME_URL":"chrome://browser/content/browser.xul","DEBUG":false,"DEBUG_JS_MODULES":"","DLL_PREFIX":"lib","DLL_SUFFIX":".so","EARLY_BETA_OR_EARLIER":false,"FENNEC_NIGHTLY":false,"HAVE_SHELL_SERVICE":false,"HAVE_USR_LIB64_DIR":false,"MENUBAR_CAN_AUTOHIDE":false,"MOZILLA_OFFICIAL":true,"MOZ_ALLOW_LEGACY_EXTENSIONS":false,"MOZ_ANDROID_ACTIVITY_STREAM":false,"MOZ_ANDROID_HISTORY":true,"MOZ_ANDROID_MOZILLA_ONLINE":false,"MOZ_APP_NAME":"fennec","MOZ_APP_VERSION":"68.1.1","MOZ_APP_VERSION_DISPLAY":"68.1.1","MOZ_BING_API_CLIENTID":"no-bing-api-clientid","MOZ_BING_API_KEY":"no-bing-api-key","MOZ_BITS_DOWNLOAD":false,"MOZ_BUILD_APP":"mobile/android","MOZ_CODE_COVERAGE":false,"MOZ_CRASHREPORTER":true,"MOZ_DATA_REPORTING":true,"MOZ_DEV_EDITION":false,"MOZ_GECKO_PROFILER":true,"MOZ_GOOGLE_LOCATION_SERVICE_API_KEY":"AIzaSyB2h2OuRcUgy5N-5hsZqiPW6sH3n_rptiQ","MOZ_GOOGLE_SAFEBROWSING_API_KEY":"AIzaSyC7jsptDS3am4tPx4r3nxis7IMjBc5Dovo","MOZ_GRAPHENE":false,"MOZ_MACBUNDLE_NAME":"Firefox.app","MOZ_MAINTENANCE_SERVICE":false,"MOZ_MOZILLA_API_KEY":"3b4d27dd-703d-4094-8398-4de2c763505a","MOZ_NEW_CERT_STORAGE":false,"MOZ_NEW_NOTIFICATION_STORE":false,"MOZ_NEW_XULSTORE":false,"MOZ_OFFICIAL_BRANDING":false,"MOZ_PLACES":false,"MOZ_REQUIRE_SIGNING":false,"MOZ_SANDBOX":false,"MOZ_SERVICES_HEALTHREPORT":true,"MOZ_SERVICES_SYNC":false,"MOZ_SWITCHBOARD":true,"MOZ_SYSTEM_NSS":false,"MOZ_TELEMETRY_ON_BY_DEFAULT":false,"MOZ_TELEMETRY_REPORTING":true,"MOZ_UNSIGNED_SCOPES":0,"MOZ_UPDATER":false,"MOZ_UPDATE_CHANNEL":"release","MOZ_WEBRTC":true,"MOZ_WIDGET_GTK":false,"MOZ_WIDGET_TOOLKIT":"android","NIGHTLY_BUILD":false,"OMNIJAR_NAME":"assets/omni.ja","RELEASE_OR_BETA":true,"SOURCE_REVISION_URL":"https://hg.mozilla.org/releases/mozilla-esr68/rev/d2e0b9e17b9bc1ef02606c8006b73293f7892ad5","TELEMETRY_PING_FORMAT_VERSION":4,"XP_UNIX":true,"isPlatformAndVersionAtLeast":{},"isPlatformAndVersionAtMost":{},"platform":"android"},"userAgent":"Mozilla/5.0 (Android 8.1.0; Mobile; rv:68.0) Gecko/68.0 Firefox/68.0","windowSize":"360x560"},"pageinfo":{"documentHeight":17195,"documentSize":{"decodedBodySize":199409,"encodedBodySize":36719,"transferSize":39234},"documentTitle":"GitHub: Where the world builds software · GitHub","documentWidth":360,"domElements":1318,"navigationStartTime":1615575124959,"nextHopProtocol":"h2","resources":{"count":0,"duration":0},"responsive":true,"url":"https://github.com/","visualElements":{"heroes":[{"filename":"hero-glow.svg","height":417,"name":"LargestImage","width":720,"x":-180,"y":227},{"filename":null,"height":70,"name":"Heading","width":332,"x":14,"y":172}],"viewport":{"height":560,"width":360}}},"timings":{"firstPaint":9213,"loadEventEnd":26971,"navigationTiming":{"connectStart":160,"domComplete":26970,"domContentLoadedEventEnd":5733,"domContentLoadedEventStart":5713,"domInteractive":2180,"domainLookupEnd":160,"domainLookupStart":160,"duration":26971,"fetchStart":2,"loadEventEnd":26971,"loadEventStart":26970,"redirectEnd":0,"redirectStart":0,"requestStart":1005,"responseEnd":1225,"responseStart":1225,"secureConnectionStart":721,"startTime":0,"unloadEventEnd":0,"unloadEventStart":0,"workerStart":0},"pageTimings":{"backEndTime":1225,"domContentLoadedTime":5713,"domInteractiveTime":2180,"domainLookupTime":0,"frontEndTime":25745,"pageDownloadTime":0,"pageLoadTime":26970,"redirectionTime":0,"serverConnectionTime":844,"serverResponseTime":220},"rumSpeedIndex":1225,"timeToContentfulPaint":12884,"timeToDomContentFlushed":5335,"userTimings":{"marks":[],"measures":[]}}}],"visualMetrics":[],"cpu":[],"extras":[{},{},{}],"fullyLoaded":[],"errors":[[],[],[]],"statistics":{"browser":{"appConstants":{"MOZ_UNSIGNED_SCOPES":{"median":0,"mean":0,"mdev":0,"stddev":0,"min":0,"p10":0,"p90":0,"p99":0,"max":0},"TELEMETRY_PING_FORMAT_VERSION":{"median":4,"mean":4,"mdev":0,"stddev":0,"min":4,"p10":4,"p90":4,"p99":4,"max":4}},"asyncAppConstants":{"MOZ_UNSIGNED_SCOPES":{"median":0,"mean":0,"mdev":0,"stddev":0,"min":0,"p10":0,"p90":0,"p99":0,"max":0},"TELEMETRY_PING_FORMAT_VERSION":{"median":4,"mean":4,"mdev":0,"stddev":0,"min":4,"p10":4,"p90":4,"p99":4,"max":4}}},"pageinfo":{"documentHeight":{"median":17195,"mean":17195,"mdev":0,"stddev":0,"min":17195,"p10":17195,"p90":17195,"p99":17195,"max":17195},"documentSize":{"decodedBodySize":{"median":199679,"mean":199591,"mdev":74.3146,"stddev":129,"min":199409,"p10":199409,"p90":199685,"p99":199685,"max":199685},"encodedBodySize":{"median":36779,"mean":36761,"mdev":17.2047,"stddev":30,"min":36719,"p10":36719,"p90":36785,"p99":36785,"max":36785},"transferSize":{"median":39292,"mean":39273,"mdev":16.0647,"stddev":28,"min":39234,"p10":39234,"p90":39294,"p99":39294,"max":39294}},"documentWidth":{"median":360,"mean":360,"mdev":0,"stddev":0,"min":360,"p10":360,"p90":360,"p99":360,"max":360},"domElements":{"median":1321,"mean":1320,"mdev":0.8165,"stddev":1,"min":1318,"p10":1318,"p90":1321,"p99":1321,"max":1321},"navigationStartTime":{"median":1615575066692,"mean":1615575067381,"mdev":28202.2041,"stddev":48848,"min":1615575010493,"p10":1615575010493,"p90":1615575124959,"p99":1615575124959,"max":1615575124959},"resources":{"count":{"median":0,"mean":0,"mdev":0,"stddev":0,"min":0,"p10":0,"p90":0,"p99":0,"max":0},"duration":{"median":0,"mean":0,"mdev":0,"stddev":0,"min":0,"p10":0,"p90":0,"p99":0,"max":0}},"visualElements":{"heroes":[{"height":{"median":417,"mean":417,"mdev":0,"stddev":0,"min":417,"p10":417,"p90":417,"p99":417,"max":417},"width":{"median":720,"mean":720,"mdev":0,"stddev":0,"min":720,"p10":720,"p90":720,"p99":720,"max":720},"x":{"median":-180,"mean":-180,"mdev":0,"stddev":0,"min":-180,"p10":-180,"p90":-180,"p99":-180,"max":-180},"y":{"median":227,"mean":227,"mdev":0,"stddev":0,"min":227,"p10":227,"p90":227,"p99":227,"max":227}},{"height":{"median":70,"mean":70,"mdev":0,"stddev":0,"min":70,"p10":70,"p90":70,"p99":70,"max":70},"width":{"median":332,"mean":332,"mdev":0,"stddev":0,"min":332,"p10":332,"p90":332,"p99":332,"max":332},"x":{"median":14,"mean":14,"mdev":0,"stddev":0,"min":14,"p10":14,"p90":14,"p99":14,"max":14},"y":{"median":172,"mean":172,"mdev":0,"stddev":0,"min":172,"p10":172,"p90":172,"p99":172,"max":172}}],"viewport":{"height":{"median":560,"mean":560,"mdev":0,"stddev":0,"min":560,"p10":560,"p90":560,"p99":560,"max":560},"width":{"median":360,"mean":360,"mdev":0,"stddev":0,"min":360,"p10":360,"p90":360,"p99":360,"max":360}}}},"timings":{"firstPaint":{"median":6188,"mean":7100,"mdev":865.3139,"stddev":1499,"min":5899,"p10":5899,"p90":9213,"p99":9213,"max":9213},"loadEventEnd":{"median":24396,"mean":25043,"mdev":800.985,"stddev":1387,"min":23763,"p10":23763,"p90":26971,"p99":26971,"max":26971},"navigationTiming":{"connectStart":{"median":203,"mean":210,"mdev":25.1322,"stddev":44,"min":160,"p10":160,"p90":266,"p99":266,"max":266},"domComplete":{"median":24395,"mean":25042,"mdev":800.985,"stddev":1387,"min":23762,"p10":23762,"p90":26970,"p99":26970,"max":26970},"domContentLoadedEventEnd":{"median":5094,"mean":5300,"mdev":176.9836,"stddev":307,"min":5072,"p10":5072,"p90":5733,"p99":5733,"max":5733},"domContentLoadedEventStart":{"median":5074,"mean":5278,"mdev":177.702,"stddev":308,"min":5047,"p10":5047,"p90":5713,"p99":5713,"max":5713},"domInteractive":{"median":1877,"mean":1951,"mdev":95.2381,"stddev":165,"min":1797,"p10":1797,"p90":2180,"p99":2180,"max":2180},"domainLookupEnd":{"median":203,"mean":210,"mdev":25.1322,"stddev":44,"min":160,"p10":160,"p90":266,"p99":266,"max":266},"domainLookupStart":{"median":203,"mean":209,"mdev":24.8834,"stddev":43,"min":160,"p10":160,"p90":265,"p99":265,"max":265},"duration":{"median":24396,"mean":25043,"mdev":800.985,"stddev":1387,"min":23763,"p10":23763,"p90":26971,"p99":26971,"max":26971},"fetchStart":{"median":3,"mean":3,"mdev":0.2722,"stddev":0,"min":2,"p10":2,"p90":3,"p99":3,"max":3},"loadEventEnd":{"median":24396,"mean":25043,"mdev":800.985,"stddev":1387,"min":23763,"p10":23763,"p90":26971,"p99":26971,"max":26971},"loadEventStart":{"median":24395,"mean":25042,"mdev":800.985,"stddev":1387,"min":23762,"p10":23762,"p90":26970,"p99":26970,"max":26970},"redirectEnd":{"median":0,"mean":0,"mdev":0,"stddev":0,"min":0,"p10":0,"p90":0,"p99":0,"max":0},"redirectStart":{"median":0,"mean":0,"mdev":0,"stddev":0,"min":0,"p10":0,"p90":0,"p99":0,"max":0},"requestStart":{"median":737,"mean":806,"mdev":82.5039,"stddev":143,"min":676,"p10":676,"p90":1005,"p99":1005,"max":1005},"responseEnd":{"median":935,"mean":1012,"mdev":88.0618,"stddev":153,"min":876,"p10":876,"p90":1225,"p99":1225,"max":1225},"responseStart":{"median":935,"mean":1012,"mdev":88.0618,"stddev":153,"min":876,"p10":876,"p90":1225,"p99":1225,"max":1225},"secureConnectionStart":{"median":464,"mean":532,"mdev":78.3359,"stddev":136,"min":410,"p10":410,"p90":721,"p99":721,"max":721},"startTime":{"median":0,"mean":0,"mdev":0,"stddev":0,"min":0,"p10":0,"p90":0,"p99":0,"max":0},"unloadEventEnd":{"median":0,"mean":0,"mdev":0,"stddev":0,"min":0,"p10":0,"p90":0,"p99":0,"max":0},"unloadEventStart":{"median":0,"mean":0,"mdev":0,"stddev":0,"min":0,"p10":0,"p90":0,"p99":0,"max":0},"workerStart":{"median":0,"mean":0,"mdev":0,"stddev":0,"min":0,"p10":0,"p90":0,"p99":0,"max":0}},"pageTimings":{"backEndTime":{"median":935,"mean":1012,"mdev":88.0618,"stddev":153,"min":876,"p10":876,"p90":1225,"p99":1225,"max":1225},"domContentLoadedTime":{"median":5074,"mean":5278,"mdev":177.702,"stddev":308,"min":5047,"p10":5047,"p90":5713,"p99":5713,"max":5713},"domInteractiveTime":{"median":1877,"mean":1951,"mdev":95.2381,"stddev":165,"min":1797,"p10":1797,"p90":2180,"p99":2180,"max":2180},"domainLookupTime":{"median":0,"mean":0,"mdev":0,"stddev":0,"min":0,"p10":0,"p90":0,"p99":0,"max":0},"frontEndTime":{"median":23518,"mean":24030,"mdev":718.84,"stddev":1245,"min":22827,"p10":22827,"p90":25745,"p99":25745,"max":25745},"pageDownloadTime":{"median":0,"mean":0,"mdev":0,"stddev":0,"min":0,"p10":0,"p90":0,"p99":0,"max":0},"pageLoadTime":{"median":24395,"mean":25042,"mdev":800.985,"stddev":1387,"min":23762,"p10":23762,"p90":26970,"p99":26970,"max":26970},"redirectionTime":{"median":0,"mean":0,"mdev":0,"stddev":0,"min":0,"p10":0,"p90":0,"p99":0,"max":0},"serverConnectionTime":{"median":472,"mean":595,"mdev":101.6563,"stddev":176,"min":469,"p10":469,"p90":844,"p99":844,"max":844},"serverResponseTime":{"median":200,"mean":206,"mdev":5.7349,"stddev":10,"min":198,"p10":198,"p90":220,"p99":220,"max":220}},"rumSpeedIndex":{"median":934,"mean":1012,"mdev":88.1594,"stddev":153,"min":876,"p10":876,"p90":1225,"p99":1225,"max":1225},"timeToContentfulPaint":{"median":10159,"mean":10846,"mdev":846.7793,"stddev":1467,"min":9494,"p10":9494,"p90":12884,"p99":12884,"max":12884},"timeToDomContentFlushed":{"median":4729,"mean":4881,"mdev":188.6867,"stddev":327,"min":4579,"p10":4579,"p90":5335,"p99":5335,"max":5335}}}}]